Workbook

Sheet High School Players
E1: =iferror(IFS(M1="RHP","RHP",M1="LHP","LHP",M1="C","C",M1="CINF","INF",M1="MINF","INF",M1="COF","OF",M1="CF","OF",M1="1B","INF",M1="2B","INF",M1="3B","INF",M1="OF","OF",M1="INF","INF",M1="SS","INF"),"") | H1: HS PLAYERS | K1: 0.1 Committed 1 Offer 2 High Follow 3 Follow 4 Need to see 5 XX | AJ1: Filter out blanks, then copy paste changes into column K
K2: Filter A-Z | AB2: AUTO PULL FROM RECRUITING FORM
B3: Tier | C3: ID | D3: Name | E3: Pos Group | F3: Date Added: | G3: By: | H3: First Name | I3: Last Name | J3: Class | K3: ★ | L3: Commit | M3: Pos | N3: POS2 | O3: B/T | P3: Hometown | Q3: State | R3: High School | S3: Summer Team | T3: Academic | U3: Email | V3: Phone Number | W3: Seen | X3: Visit Date | Y3: Offer Date | Z3: Comms | AA3: Notes | AB3: Email | AC3: Baseball Statistics(Please insert HS season stats)/Accolades (High School & Summer if available) | AD3: GPA (Unweighted/Weighted) | AE3: Test Scores (SAT/ACT or both) please list. | AF3: Injury History - Please list any sport specific injuries and/or surgeries you have had. | AG3: Do you have any allergies to foods and/or medications? If yes, please list them below. | AH3: Are you currently taking any medications? If yes, please list them below. | AI3: Do you require any academic accommodations(i.e. extra time on tests)? | AJ3: Update ★
B4: 1 | C4: =IFERROR(__xludf.DUMMYFUNCTION("MAP(D4:D2085, K4:K2085, J4:J2085, M4:M2085, Q4:Q2085, LAMBDA(c, k, j, m, q, IF(c="""", """", IFERROR(c & "" ("" & k & "") - "" & ""'2"" & SPLIT(j,""20"") & "" "" & m) & "" "" & q ) ) )"),"John Loudon (0.1) - '25 COF GA") -> John Loudon (0.1) - '25 COF GA | D4: {=MAP(H4:H2085, I4:I2085, LAMBDA(h, i, IF(h="", "", h & " " & i) ) )} -> John Loudon | E4: {=MAP(M4:M2085, LAMBDA(m, IF(m="", "", IFERROR(IFS( m="RHP","RHP", m="LHP","LHP", m="C","C", m="CINF","INF", m="MINF","INF", m="COF","OF", m="CF","OF", m="1B","INF", m="2B","INF", m="3B","INF", m="OF","OF", m="INF","INF", m="SS","INF" ),"") ) ) )} -> OF | H4: John | I4: Loudon | J4: 2025 | K4: 0.1 | L4: NAVY | M4: COF | Q4: GA | R4: Marist | S4: 9th INN Royals | X4: 45937 | AA4: 8/1 Call - Asked great questions. Genuine interest, gpop was army and has talked him into servoce. Had a lot of traffoc today. Need to get on visit asap.AP: Futures. 5'11 190 avg. +SPEED. 6.5 runner. compact swing with decent bat speed. strong body. TR - Lit up the WWBA in the summer. Showed power and an advanced approach at the plate. Swung it well off canes national team. Stole bases at will and had very athletic actions in the outfield. | AB4: {=MAP($D4:$D2085, LAMBDA(d, IF(d="", "", XLOOKUP(d, 'Recruiting Form Responses'!$C:$C, 'Recruiting Form Responses'!D:D, "", 0, 1) ) ) )} | AC4: {=MAP($D4:$D2085, LAMBDA(d, IF(d="", "", XLOOKUP(d, 'Recruiting Form Responses'!$C:$C, 'Recruiting Form Responses'!G:G, "", 0, 1) ) ) )} | AD4: {=MAP($D4:$D2085, LAMBDA(d, IF(d="", "", XLOOKUP(d, 'Recruiting Form Responses'!$C:$C, 'Recruiting Form Responses'!H:H, "", 0, 1) ) ) )} | AE4: {=MAP($D4:$D2085, LAMBDA(d, IF(d="", "", XLOOKUP(d, 'Recruiting Form Responses'!$C:$C, 'Recruiting Form Responses'!I:I, "", 0, 1) ) ) )} | AF4: {=MAP($D4:$D2085, LAMBDA(d, IF(d="", "", XLOOKUP(d, 'Recruiting Form Responses'!$C:$C, 'Recruiting Form Responses'!J:J, "", 0, 1) ) ) )} | AG4: {=MAP($D4:$D2085, LAMBDA(d, IF(d="", "", XLOOKUP(d, 'Recruiting Form Responses'!$C:$C, 'Recruiting Form Responses'!K:K, "", 0, 1) ) ) )} | AH4: {=MAP($D4:$D2085, LAMBDA(d, IF(d="", "", XLOOKUP(d, 'Recruiting Form Responses'!$C:$C, 'Recruiting Form Responses'!L:L, "", 0, 1) ) ) )} | AI4: {=MAP($D4:$D2085, LAMBDA(d, IF(d="", "", XLOOKUP(d, 'Recruiting Form Responses'!$C:$C, 'Recruiting Form Responses'!M:M, "", 0, 1) ) ) )} | AJ4: {=MAP($D4:$D2085, LAMBDA(d, IF(d="", "", XLOOKUP(d, StarUpdater!$A:$A, StarUpdater!D:D, "", 0, 1) ) ) )}
B5: 1 | C5: =IFERROR(__xludf.DUMMYFUNCTION("""COMPUTED_VALUE"""),"Noah Stead (0.1) - '25 MINF CA") -> Noah Stead (0.1) - '25 MINF CA | D5: Noah Stead | E5: INF | H5: Noah | I5: Stead | J5: 2025 | K5: 0.1 | L5: NAVY | M5: MINF | Q5: CA | R5: Westlake | S5: So Cal Giants | X5: 45527 | AA5: TR: Dude day. Moves well very good hands separates the ball below his knees. enough arm to play ss with a quick release. Unorthodox swing but gets on plane and has really good bat to ball. Power and extrra base hit guy. .320 with 7 HRs in HS. HS and summer coach both say all the right things about kid and parents. Going to hit 3rd and play ss at Westlake HS this year. was the only junior in an all senior d1 committed lineup last year. Ready to offer. | AB5: Steadnoah5@gmail.com | AC5: All Ventura County First Team/ Scholar Athlete 2 Years/ Offensive Player of the Year for Varsity | AD5: 4.0 Weighted | AE5: None Yet. Taking in November | AF5: None | AG5: None | AH5: None | AI5: None
B6: 1 | C6: =IFERROR(__xludf.DUMMYFUNCTION("""COMPUTED_VALUE"""),"Owen Phypers (0.1) - '25 RHP FL") -> Owen Phypers (0.1) - '25 RHP FL | D6: Owen Phypers | E6: RHP | H6: Owen | I6: Phypers | J6: 2025 | K6: 0.1 | L6: NAVY | M6: RHP | Q6: FL | R6: St. John Neumann | S6: Florida Burn | X6: 45474
B7: 1 | C7: =IFERROR(__xludf.DUMMYFUNCTION("""COMPUTED_VALUE"""),"Patrick Walsh (0.1) - '25 CINF NC") -> Patrick Walsh (0.1) - '25 CINF NC | D7: Patrick Walsh | E7: INF | H7: Patrick | I7: Walsh | J7: 2025 | K7: 0.1 | L7: NAVY | M7: CINF | Q7: NC | R7: Christ the king Catholic | S7: wow factor | AA7: 6'1 195 strong LHH. Manning comp. Avg run 4.3 down the line. Power potential in bat. Fringe def. Good arm. Was 87-89 (91) at June Navy prospect camp. Performace history good. POTY in 1A conference. | AB7: walsh.patrick.2025@gmail.com | AC7: Slash Line: 0.487/0.610/1.064 2B: 10 3B: 4 HR: 9 RBI: 38 SB: 13 BB: 22 R: 36 GP:28 PA: 105 Pitching IP: 38.2 ERA: 3.44 K:56 2024 CSAC CPOY 2024 NCBA 1st Team All-State 2024 Charlotte Observer 1st Team All-Area | AD7: 4.44 | AE7: SAT:1230 ACT: Not yet Taken | AF7: No Baseball Related injuries. MLC Sprain in October 2023 playing football. Hamstring avulsion playing football in August 2022. | AG7: No | AH7: No | AI7: No
B8: 1 | C8: =IFERROR(__xludf.DUMMYFUNCTION("""COMPUTED_VALUE"""),"Sachin Gopal (0.1) - '25 RHP MA") -> Sachin Gopal (0.1) - '25 RHP MA | D8: Sachin Gopal | E8: RHP | H8: Sachin | I8: Gopal | J8: 2025 | K8: 0.1 | L8: NAVY | M8: RHP | Q8: MA | R8: Dexter Southfield | S8: Nokona | X8: 45461 | AB8: sachingopal@yahoo.com | AC8: This High school season: CNEPSBL all star and All NEPSAC HM, 31IP 30K 6BB 1.58ERA .935 WHIP .200 BAA. Last Summer: 40IP (3 CG’s), 45K, 11BB, 1.75 ERA, .950 WHIP, and a .180 BAA. | AD8: 3.7 UW | AE8: 1420 SAT | AF8: No injuries | AG8: No allergies | AH8: No medication | AI8: I am eligible for accommodations but don’t actually use them or need them
B9: 1 | C9: =IFERROR(__xludf.DUMMYFUNCTION("""COMPUTED_VALUE"""),"Sinjon Lash (0.1) - '25 RHP GA") -> Sinjon Lash (0.1) - '25 RHP GA | D9: Sinjon Lash | E9: RHP | H9: Sinjon | I9: Lash | J9: 2025 | K9: 0.1 | L9: NAVY | M9: RHP | Q9: GA | R9: LaGrange HS | S9: Atlanta Braves Scout | X9: 45951 | AA9: AP: have not seen yet. 6'4 200 good frame. 85-88 w/ 75 CB, has CH. Talked with him on the phone and he seems interested. will see him throw this fall. moved to GA from WA few years ago. was with EC Astros but now with Titans (ATL Braves scout team)
B10: 1 | C10: =IFERROR(__xludf.DUMMYFUNCTION("""COMPUTED_VALUE"""),"Tyler Cripe (0.1) - '25 CF FL") -> Tyler Cripe (0.1) - '25 CF FL | D10: Tyler Cripe | E10: OF | H10: Tyler | I10: Cripe | J10: 2025 | K10: 0.1 | L10: NAVY | M10: CF | Q10: FL | R10: Florida Burn | X10: 45972 | AA10: JK-been in touch since his vist. High interest. Likely wants to commit. Allergy report came in on Dec 12. Looks like all allergies have subsided. Have to run up the chain. No reservations about the abililty/player. Questionable info on personality fit from HS coach. JK- Lean frame. Whippy barrel. Good runner/floats. K/F7/1b64
B11: 1 | C11: =IFERROR(__xludf.DUMMYFUNCTION("""COMPUTED_VALUE"""),"Will Howard (0.1) - '25 C KS") -> Will Howard (0.1) - '25 C KS | D11: Will Howard | E11: C | H11: Will | I11: Howard | J11: 2025 | K11: 0.1 | L11: NAVY | M11: C | Q11: KS | S11: Royals Scout Team | AA11: TR NPI: physical build moves well. Very good catch and throw 1.9-2.0 on the bag, quick release. Good stance and flex. Like the swing and athelticism in the box. Didn't get much offensive look need to see again. Good first call sounds very inetersted and has always wanted to serve. Very normal kid, hit .420 in HS with 4 HR. Looks like a string kid.
B12: 1 | C12: =IFERROR(__xludf.DUMMYFUNCTION("""COMPUTED_VALUE"""),"Ben Baldessare (2) - '25 MINF NC") -> Ben Baldessare (2) - '25 MINF NC | D12: Ben Baldessare | E12: INF | H12: Ben | I12: Baldessare | J12: 2025 | K12: 2 | M12: MINF | Q12: NC | R12: Providence | S12: Richmond braves | AA12: JK email notes: Top 500 #2 1B in NC.
B13: 1 | C13: =IFERROR(__xludf.DUMMYFUNCTION("""COMPUTED_VALUE"""),"Cal Travers (2) - '25 LHP VA") -> Cal Travers (2) - '25 LHP VA | D13: Cal Travers | E13: LHP | H13: Cal | I13: Travers | J13: 2025 | K13: 2 | M13: LHP | Q13: VA | R13: Godwin | S13: 101mph Dragum | AA13: TR: Spoke with Cal, had an offer from VMI. Didn't have a good spring, didn't pitch much told me he's 85-87 on FB 77-78 on SL. Told me he was inconsistent. Goldy told me he has a connection to the kid and that he was coming ot camp. JK email notes: High follow pg 17 ranked in VA. 6'1" 190
B14: 1 | C14: =IFERROR(__xludf.DUMMYFUNCTION("""COMPUTED_VALUE"""),"Eric Harrison (2) - '25 MINF FL") -> Eric Harrison (2) - '25 MINF FL | D14: Eric Harrison | E14: INF | H14: Eric | I14: Harrison | J14: 2025 | K14: 2 | M14: MINF | Q14: FL | R14: Avon Park | S14: Southern Squeeze | AA14: JK: Email notes: 8 on pg. 6'2" 215. High follow as 3rd baseman.
B15: 1 | C15: =IFERROR(__xludf.DUMMYFUNCTION("""COMPUTED_VALUE"""),"Jake Hooten (2) - '25 CF FL") -> Jake Hooten (2) - '25 CF FL | D15: Jake Hooten | E15: OF | H15: Jake | I15: Hooten | J15: 2025 | K15: 2 | M15: CF | Q15: FL | R15: Gulf Breeze | S15: East Coast Sox Scout | AA15: June Camp: 6'2 190 strong bodied and runs. Ran 6.7 and 6.8 at camp. Need to see how well bat plays | AB15: jr3hooten@gmail.com | AC15: 22 games .375 avg, .467 obp, .998 ops, 74PA, 24/64 hits/ab, 6 doubles, 2HR, 18R, 17rbi Team MVP, Pitching: 4-1 18 innings, 29k, .79 ERA | AD15: 4.83 | AE15: 34 ACT 1390 SAT | AF15: Broken ankle/screws; Broken finger | AG15: No | AH15: No | AI15: No
B16: 1 | C16: =IFERROR(__xludf.DUMMYFUNCTION("""COMPUTED_VALUE"""),"La'akea Correa (2) - '25 LHP HI") -> La'akea Correa (2) - '25 LHP HI | D16: La'akea Correa | E16: LHP | H16: La'akea | I16: Correa | J16: 2025 | K16: 2 | M16: LHP | Q16: HI | AA16: JK: 83-85, 72-74 spin, 74-75 CH, Fb to both sides for sure. CH can be solid. Spin is avg.
B17: 1 | C17: =IFERROR(__xludf.DUMMYFUNCTION("""COMPUTED_VALUE"""),"Lucas Collins (2) - '25 LHP IN") -> Lucas Collins (2) - '25 LHP IN | D17: Lucas Collins | E17: LHP | H17: Lucas | I17: Collins | J17: 2025 | K17: 2 | M17: LHP | Q17: IN | R17: Bishop dwenger | S17: Canes Midwest | AA17: JK email notes: up to 89 on pbr. #4 lhp in IN.
B18: 1 | C18: =IFERROR(__xludf.DUMMYFUNCTION("""COMPUTED_VALUE"""),"Michael Fiatrone (2) - '25 MINF CT") -> Michael Fiatrone (2) - '25 MINF CT | D18: Michael Fiatrone | E18: INF | H18: Michael | I18: Fiatrone | J18: 2025 | K18: 2 | M18: MINF | Q18: CT | R18: Salisbury School | AA18: JK- solid film. SS at Salisbury. Will see in spring. Saw briefly in FL. Liked the frame and actions. Didn't have a blowaway showing.
B19: 1 | C19: =IFERROR(__xludf.DUMMYFUNCTION("""COMPUTED_VALUE"""),"Nathan Lake (2) - '25 LHP VA") -> Nathan Lake (2) - '25 LHP VA | D19: Nathan Lake | E19: LHP | H19: Nathan | I19: Lake | J19: 2025 | K19: 2 | M19: LHP | Q19: VA | S19: VA Stars | AA19: JK-3 pitch/pitchability LHP. Wont wow but can pitch a bit. High int in academy. Would like second set of eyes on him | AB19: Nathan.lake@outlook.com | AC19: 1.4 era 1st team all district | AD19: 3.8 | AE19: 1180 | AG19: No | AH19: Claritin | AI19: No
B20: 1 | C20: =IFERROR(__xludf.DUMMYFUNCTION("""COMPUTED_VALUE"""),"Sam Harry (2) - '25 COF CO") -> Sam Harry (2) - '25 COF CO | D20: Sam Harry | E20: OF | H20: Sam | I20: Harry | J20: 2025 | K20: 2 | M20: COF | Q20: CO | R20: Castle View | AA20: TR: Watched at Slammers event. He has a pro body 4.6 on turn and 4.3/3 through the base. Runs and moves like a big leaguer. Swing is atheltic but was not making good contact early in the weekend when he lets it go its an atheltic and quick swing. His numbers from HS were .456 w/ 9k/6bb. Only 1 HR in CO. I'm worried about power, his approach is to drive the ball the other way and he may be able to do that well. Holz told me he was about to commit to Charleston So. and mom dragged it out trying to get more money. They gave him 3k more and the coaching change happened. Kuhn told him they can't take his commitment now but theyre goign to watch him. Dad wears pins on his crocs.
B21: 1 | C21: =IFERROR(__xludf.DUMMYFUNCTION("""COMPUTED_VALUE"""),"Tate Elliott (2) - '25 C TX") -> Tate Elliott (2) - '25 C TX | D21: Tate Elliott | E21: C | H21: Tate | I21: Elliott | J21: 2025 | K21: 2 | M21: C | Q21: TX | R21: Midlothian | S21: TBT Texas | AA21: JK: Can really throw. athletic frame. hands probably not as good as wells but throws better. avg runner. Worried about bat. | AB21: tateelliott1131@gmail.com | AC21: Preseason All American, All district, Texas 5a All star | AD21: 3.5 | AE21: 1070
B22: 1 | C22: =IFERROR(__xludf.DUMMYFUNCTION("""COMPUTED_VALUE"""),"Trent Prosperi (2) - '25 MINF TX") -> Trent Prosperi (2) - '25 MINF TX | D22: Trent Prosperi | E22: INF | H22: Trent | I22: Prosperi | J22: 2025 | K22: 2 | M22: MINF | Q22: TX | R22: Boswell HS | S22: Cooperstown Cobras | AA22: JK: HIt 2. Like this kid but playing 2B. Good turns, barrell contact. Does he have enough arm for left side???
B23: 1 | C23: =IFERROR(__xludf.DUMMYFUNCTION("""COMPUTED_VALUE"""),"Aiden Szydlik (3) - '25 MINF MD") -> Aiden Szydlik (3) - '25 MINF MD | D23: Aiden Szydlik | E23: INF | H23: Aiden | I23: Szydlik | J23: 2025 | K23: 3 | M23: MINF | Q23: MD | R23: Severn School | S23: Canes Mid Atlantic | AA23: JK-physical switch hitting IF/possible corner OF. Elite student. Parents are W.Point grads but the kid seems really interested in Navy
B24: 1 | C24: =IFERROR(__xludf.DUMMYFUNCTION("""COMPUTED_VALUE"""),"Ayden Munoz (3) - '25 COF CA") -> Ayden Munoz (3) - '25 COF CA | D24: Ayden Munoz | E24: OF | H24: Ayden | I24: Munoz | J24: 2025 | K24: 3 | M24: COF | Q24: CA | R24: Carlsbad | S24: So Cal Giants | AA24: AP: 5'9 170, very small. LHH with a good swing and good bat speed. low ceiling bc/ of size. athletic.6.7 runner
B25: 1 | C25: =IFERROR(__xludf.DUMMYFUNCTION("""COMPUTED_VALUE"""),"Benjy Cardone (3) - '25 C VA") -> Benjy Cardone (3) - '25 C VA | D25: Benjy Cardone | E25: C | H25: Benjy | I25: Cardone | J25: 2025 | K25: 3 | M25: C | Q25: VA | R25: Highland HS | X25: 45952 | AA25: Hit .276 JR yr. AP: update: high motor, vocal player, good skills behind the dish with quick release. avg arm. good swing with doubles pwr. doesnt run. ceiling limited bc of size. offensive comp eddie Diaz. JK-been in contact via text/email. Dad is CIA. Solid catch/release. Arm has carry. Showed pop in BP despite more compact frame. Reminds me of Killelea a bit. Really good kid on visit. Has his shit together. JK-has continued to keep in touch.
B26: 1 | C26: =IFERROR(__xludf.DUMMYFUNCTION("""COMPUTED_VALUE"""),"Bobby Herzman (3) - '25 CINF CT") -> Bobby Herzman (3) - '25 CINF CT | D26: Bobby Herzman | E26: INF | H26: Bobby | I26: Herzman | J26: 2025 | K26: 3 | M26: CINF | Q26: CT | R26: HC Wilcox | AA26: AP: Futures. not a need right now. 6'2 235, big boy/softer body right now. 1B only: LHH who gets his swing off. good bat speed and good swing. looks good in the box, feel for hitting/approach. avg def. avg arm. 7.8 not a runner.
B27: 1 | C27: =IFERROR(__xludf.DUMMYFUNCTION("""COMPUTED_VALUE"""),"Braxton Graber (3) - '25 RHP AR") -> Braxton Graber (3) - '25 RHP AR | D27: Braxton Graber | E27: RHP | H27: Braxton | I27: Graber | J27: 2025 | K27: 3 | M27: RHP | Q27: AR | R27: East Coast SandHogs | AA27: JK-85-86/spin 72 12/6 shape. Loose arm/clean
B28: 1 | C28: =IFERROR(__xludf.DUMMYFUNCTION("""COMPUTED_VALUE"""),"Brooks Bradshaw (3) - '25 RHP GA") -> Brooks Bradshaw (3) - '25 RHP GA | D28: Brooks Bradshaw | E28: RHP | H28: Brooks | I28: Bradshaw | J28: 2025 | K28: 3 | M28: RHP | Q28: GA | R28: Benedictine Military | S28: CBU Stofsky | AA28: JK email notes: 6'3" 205 pg top 1000.
B29: 1 | C29: =IFERROR(__xludf.DUMMYFUNCTION("""COMPUTED_VALUE"""),"Caden Davidson (3) - '25 MINF NC") -> Caden Davidson (3) - '25 MINF NC | D29: Caden Davidson | E29: INF | H29: Caden | I29: Davidson | J29: 2025 | K29: 3 | M29: MINF | Q29: NC | R29: USA Prime Coastal | S29: 5 Star | AA29: JK-physical kid. Didn't see enough to weigh in. Need to see more if interest. #7 3b in NC.
B30: 1 | C30: =IFERROR(__xludf.DUMMYFUNCTION("""COMPUTED_VALUE"""),"Colton Roberts (3) - '25 RHP KS") -> Colton Roberts (3) - '25 RHP KS | D30: Colton Roberts | E30: RHP | H30: Colton | I30: Roberts | J30: 2025 | K30: 3 | M30: RHP | Q30: KS | R30: Rose Hill | AA30: TR- texted 1/3 to connect. Futures. 87-89 / 75. Loose quick arm. Ath feel for spin. Presence and poise.
B31: 1 | C31: =IFERROR(__xludf.DUMMYFUNCTION("""COMPUTED_VALUE"""),"Cy Herkelroath (3) - '25 LHP PA") -> Cy Herkelroath (3) - '25 LHP PA | D31: Cy Herkelroath | E31: LHP | H31: Cy | I31: Herkelroath | J31: 2025 | K31: 3 | M31: LHP | Q31: PA | R31: TOPS | S31: Elizabeth Forward | AA31: JK email notes: High follow 6'3" 200. #11 lhp in state
B32: 1 | C32: =IFERROR(__xludf.DUMMYFUNCTION("""COMPUTED_VALUE"""),"Davis Beilstein (3) - '25 COF GA") -> Davis Beilstein (3) - '25 COF GA | D32: Davis Beilstein | E32: OF | H32: Davis | I32: Beilstein | J32: 2025 | K32: 3 | M32: COF | Q32: GA | R32: 643 | AA32: JK-strong interest in Navy. Listed as a C but likely corner OF. Physical frame. Have to see if he hits enough to even consider.
B33: 1 | C33: =IFERROR(__xludf.DUMMYFUNCTION("""COMPUTED_VALUE"""),"Drew Flores (3) - '25 C TX") -> Drew Flores (3) - '25 C TX | D33: Drew Flores | E33: C | H33: Drew | I33: Flores | J33: 2025 | K33: 3 | M33: C | Q33: TX | R33: 5 star performance national | AA33: JK: Could be catcher in the mix. Check in on him
B34: 1 | C34: =IFERROR(__xludf.DUMMYFUNCTION("""COMPUTED_VALUE"""),"Drew Kindlon (3) - '25 RHP NY") -> Drew Kindlon (3) - '25 RHP NY | D34: Drew Kindlon | E34: RHP | H34: Drew | I34: Kindlon | J34: 2025 | K34: 3 | M34: RHP | Q34: NY | R34: P27 Academy | AA34: AP: update, 82-86, not great looking in short outing. arm tightened up and exited game. TR: recommended by Josh Murphy. Decommitt from UVA. Looks like a high level arm with a high level brekaign ball and plus spin on FB. 6'3" 210 pg 9. Josh told me he is coming off a back injury but recent videos look very good. Have reached out to kid. Recruiting heating up have to see Fri PBR 17U | AB34: kindlondrew632@gmail.com | AD34: 3.8 | AE34: 1240 | AF34: Ucl strain Back fracture | AG34: No | AH34: No | AI34: No
B35: 1 | C35: =IFERROR(__xludf.DUMMYFUNCTION("""COMPUTED_VALUE"""),"Drew McTagertt (3) - '25 C IN") -> Drew McTagertt (3) - '25 C IN | D35: Drew McTagertt | E35: C | H35: Drew | I35: McTagertt | J35: 2025 | K35: 3 | M35: C | Q35: IN | R35: William Henry Harrison | S35: Indiana Bulls | AA35: AP: update: has not gotten stronger, maybe backtracked strength wise. 6'3 180 good body. didn't see a ton from him. Future Games kid. their coaches like him. JK- saw briefly in FL. Good enough to reach out/gauge interest/see again if he is a fit.
B36: 1 | C36: =IFERROR(__xludf.DUMMYFUNCTION("""COMPUTED_VALUE"""),"Ethan Johnson (3) - '25 MINF CA") -> Ethan Johnson (3) - '25 MINF CA | D36: Ethan Johnson | E36: INF | H36: Ethan | I36: Johnson | J36: 2025 | K36: 3 | M36: MINF | Q36: CA | R36: Kings Acdemy | S36: ATL Blue Jays | AA36: JK email notes: 8.5 top 1000. C/1b 6'2" 210
B37: 1 | C37: =IFERROR(__xludf.DUMMYFUNCTION("""COMPUTED_VALUE"""),"Gabe Pegues (3) - '25 COF VA") -> Gabe Pegues (3) - '25 COF VA | D37: Gabe Pegues | E37: OF | H37: Gabe | I37: Pegues | J37: 2025 | K37: 3 | M37: COF | Q37: VA | R37: Stars | S37: McLean HS | AA37: JK- Comfortable on balls in air. Supposedly elite runner. Physical RH hitter. Looks athletic. Below avg arm53 (4.37)/Klook.Poor rating on PG
B38: 1 | C38: =IFERROR(__xludf.DUMMYFUNCTION("""COMPUTED_VALUE"""),"Grant Belcher (3) - '25 RHP CO") -> Grant Belcher (3) - '25 RHP CO | D38: Grant Belcher | E38: RHP | H38: Grant | I38: Belcher | J38: 2025 | K38: 3 | M38: RHP | Q38: CO | R38: Ralston Valley | S38: Elite | AA38: AP: update: slow start to 24 season. lots of BB's/HBP's. not good enough 6'1 180 86-89, 73 -/+ SL, CH. decent FB but got hit. quick arm. Future Gamer. Needs to show success in 24 spring season
B39: 1 | C39: =IFERROR(__xludf.DUMMYFUNCTION("""COMPUTED_VALUE"""),"Jacob Pettit (3) - '25 COF SC") -> Jacob Pettit (3) - '25 COF SC | D39: Jacob Pettit | E39: OF | H39: Jacob | I39: Pettit | J39: 2025 | K39: 3 | M39: COF | Q39: SC | R39: SoChar Panthers | AA39: JK-saw in GA. Switch hitter. May be transitioning to OF. Def. follow if interested. - 368 hitter in 33 PG games in summer.
B40: 1 | C40: =IFERROR(__xludf.DUMMYFUNCTION("""COMPUTED_VALUE"""),"Jaxon Sparks (3) - '25 LHP IN") -> Jaxon Sparks (3) - '25 LHP IN | D40: Jaxon Sparks | E40: LHP | H40: Jaxon | I40: Sparks | J40: 2025 | K40: 3 | M40: LHP | Q40: IN | R40: Carroll (IN) | S40: Indiana Bulls | AA40: AP: rec from Dan Held (Bulls), duel guy. 6'1 215 strong build. mid 80's with decent SL. good HS stats as SO on mound. Runs 6.63! LHH with juice but only hit .270 as SO. outfielder. Future Games. have not seen.
B41: 1 | C41: =IFERROR(__xludf.DUMMYFUNCTION("""COMPUTED_VALUE"""),"JD Mace (3) - '25 RHP NC") -> JD Mace (3) - '25 RHP NC | D41: JD Mace | E41: RHP | H41: JD | I41: Mace | J41: 2025 | K41: 3 | M41: RHP | Q41: NC | R41: Golden spikes | S41: burlington christian | AA41: JK email notes: potential prep candidate. 6'6" 195 high follow pg.
B42: 1 | C42: =IFERROR(__xludf.DUMMYFUNCTION("""COMPUTED_VALUE"""),"John Kosobud (3) - '25 RHP GA") -> John Kosobud (3) - '25 RHP GA | D42: John Kosobud | E42: RHP | H42: John | I42: Kosobud | J42: 2025 | K42: 3 | M42: RHP | Q42: GA | R42: 9th Inn | AA42: JK-85-86/heavy with cut. Homeschooled kid. Need to see more
B43: 1 | C43: =IFERROR(__xludf.DUMMYFUNCTION("""COMPUTED_VALUE"""),"Keegan Luxem (3) - '25 RHP IL") -> Keegan Luxem (3) - '25 RHP IL | D43: Keegan Luxem | E43: RHP | H43: Keegan | I43: Luxem | J43: 2025 | K43: 3 | M43: RHP | Q43: IL | R43: Hersey | AA43: TR-texted 1/3 after checking in on twitter. '23 stats 58IP 64k/14bb / 2.88era.setting up a call. Futures. Huge frame 85-87. 76 on the slider with 22 spin.
A44: https://www.perfectgame.org/Players/Playerprofile.aspx?ID=988538 | B44: 1 | C44: =IFERROR(__xludf.DUMMYFUNCTION("""COMPUTED_VALUE"""),"Matthew Roussey (3) - '25 RHP VA") -> Matthew Roussey (3) - '25 RHP VA | D44: Matthew Roussey | E44: RHP | H44: Matthew | I44: Roussey | J44: 2025 | K44: 3 | M44: RHP | Q44: VA | R44: Mid Atl Red Sox | AA44: JK-85/shorter AA. 74 spin. Down angle. Check.
B45: 1 | C45: =IFERROR(__xludf.DUMMYFUNCTION("""COMPUTED_VALUE"""),"Mickey Fox (3) - '25 LHP AZ") -> Mickey Fox (3) - '25 LHP AZ | D45: Mickey Fox | E45: LHP | H45: Mickey | I45: Fox | J45: 2025 | K45: 3 | M45: LHP | Q45: AZ | R45: Yuma Catholic | AA45: TR- Texted 1/3. check in, 56IP/2.11/89k/29BB. Texted to connect. Futures games. 85-86/74 with 24 spin. Quick arm. Body and athleticism project.
B46: 1 | C46: =IFERROR(__xludf.DUMMYFUNCTION("""COMPUTED_VALUE"""),"Robert(Lujack) Cole (3) - '25 RHP SC") -> Robert(Lujack) Cole (3) - '25 RHP SC | D46: Robert(Lujack) Cole | E46: RHP | H46: Robert(Lujack) | I46: Cole | J46: 2025 | K46: 3 | M46: RHP | Q46: SC | R46: Christ Church Episcopal | AA46: AP: update: surgery Feb 24. Futures. 6'3 200 good build. 87-88, 80 CH, 78-79 SL short tight 2000spin. projectable and high ceiling. secondary stuff maybe a little short. just a Follow. Grades aren't listed anywhere
B47: 1 | C47: =IFERROR(__xludf.DUMMYFUNCTION("""COMPUTED_VALUE"""),"Rylan Moses (3) - '25 CF TN") -> Rylan Moses (3) - '25 CF TN | D47: Rylan Moses | E47: OF | H47: Rylan | I47: Moses | J47: 2025 | K47: 3 | M47: CF | Q47: TN | R47: Goodpasture | S47: Knights | AA47: AP: 6'0 175 small frame. LHH with clean swing. runner. 6.7. no pwr. fringe arm. hit .412 in HS. Just follow
B48: 1 | C48: =IFERROR(__xludf.DUMMYFUNCTION("""COMPUTED_VALUE"""),"Thomas Allen (3) - '25 RHP LA") -> Thomas Allen (3) - '25 RHP LA | D48: Thomas Allen | E48: RHP | H48: Thomas | I48: Allen | J48: 2025 | K48: 3 | M48: RHP | Q48: LA | R48: Benton | S48: Team Louisiana | AA48: AP: 6'2 180 tall lean Fast arm! 87-90. below avg BB. Future gamer. low follow. needs to improve BB. saw at PG 17u Hoover
B49: 1 | C49: =IFERROR(__xludf.DUMMYFUNCTION("""COMPUTED_VALUE"""),"Tobey Bajda (3) - '25 RHP CT") -> Tobey Bajda (3) - '25 RHP CT | D49: Tobey Bajda | E49: RHP | H49: Tobey | I49: Bajda | J49: 2025 | K49: 3 | M49: RHP | Q49: CT | R49: Clubhouse | AA49: JK-sprayed in only inning I saw. Porzio rec. Said big arm strength. Said up to 90/91 but I saw 84-86 w/ spin at 74.
B50: 1 | C50: =IFERROR(__xludf.DUMMYFUNCTION("""COMPUTED_VALUE"""),"Trent Kulig (3) - '25 RHP IN") -> Trent Kulig (3) - '25 RHP IN | D50: Trent Kulig | E50: RHP | H50: Trent | I50: Kulig | J50: 2025 | K50: 3 | M50: RHP | Q50: IN | R50: Andrean HS | S50: Indiana Bulls | AA50: AP: update: check with HS coach spring 24 season. 6'3 200 good body. ott arm slot. mid 80's up to 90 FB. 72-75 12/6 CB. was a little eratic early in outing I saw but projects to be a good arm. HS coach likes him but verified command issues. JK-didn't get to see pitch. Played on really good team. Physical/strong looking kid.
B51: 1 | C51: =IFERROR(__xludf.DUMMYFUNCTION("""COMPUTED_VALUE"""),"Trey Lamay (3) - '25 RHP CT") -> Trey Lamay (3) - '25 RHP CT | D51: Trey Lamay | E51: RHP | H51: Trey | I51: Lamay | J51: 2025 | K51: 3 | M51: RHP | Q51: CT | R51: Clubhouse | AA51: JK-82-84 soph summer in Ft Myers. Worth a follow. Threw K's, decent spin. Lanky frame
B52: 1 | C52: =IFERROR(__xludf.DUMMYFUNCTION("""COMPUTED_VALUE"""),"Tyler Baker (3) - '25 COF CA") -> Tyler Baker (3) - '25 COF CA | D52: Tyler Baker | E52: OF | H52: Tyler | I52: Baker | J52: 2025 | K52: 3 | M52: COF | Q52: CA | R52: Dana Hills | AA52: Emailed - Saw at So Cal workout, just ok but worth keeping in touch with
B53: 1 | C53: =IFERROR(__xludf.DUMMYFUNCTION("""COMPUTED_VALUE"""),"Tyler Martin (3) - '25 RHP IA") -> Tyler Martin (3) - '25 RHP IA | D53: Tyler Martin | E53: RHP | H53: Tyler | I53: Martin | J53: 2025 | K53: 3 | M53: RHP | Q53: IA | R53: Mount Ayr | S53: Royals Scout Team | AA53: JK email notes: converted catcher.
B54: 1 | C54: =IFERROR(__xludf.DUMMYFUNCTION("""COMPUTED_VALUE"""),"Von Pelow (3) - '25 C NC") -> Von Pelow (3) - '25 C NC | D54: Von Pelow | E54: C | H54: Von | I54: Pelow | J54: 2025 | K54: 3 | M54: C | Q54: NC | R54: Cannon School | AA54: Came to camp. Solid all around player. Nothing explosive but just solid all around, controlled the game. Spoke with him after camp, doesn't have much going on on recrutiing front. TR PBR Cup - Von was a descent catcher btwn inning throws were accurate 2.1. Not a big guy but built like a catcher. Received and blocked well. Had 3 good at bats. F9/HC 1b to RF/2B with drive to LC. He is a solid option played well good kid on the phone. Nothing jumps out as great but all around a very solid player.
B55: 1 | C55: =IFERROR(__xludf.DUMMYFUNCTION("""COMPUTED_VALUE"""),"Aiden Oviendo (4) - '25 MINF KS") -> Aiden Oviendo (4) - '25 MINF KS | D55: Aiden Oviendo | E55: INF | H55: Aiden | I55: Oviendo | J55: 2025 | K55: 4 | M55: MINF | Q55: KS | AA55: TR: Dug up and have had several phone calls. Video looks solid, has some offers but wants to play out fall. Good friends with Will Howard I learned after the fact. Need to see in fall asap.
B56: 1 | C56: =IFERROR(__xludf.DUMMYFUNCTION("""COMPUTED_VALUE"""),"Ben Wilcox (4) - '25 LHP NC") -> Ben Wilcox (4) - '25 LHP NC | D56: Ben Wilcox | E56: LHP | H56: Ben | I56: Wilcox | J56: 2025 | K56: 4 | M56: LHP | Q56: NC | R56: Charlotte Christian | AA56: Followed me on twitter check into.
B57: 1 | C57: =IFERROR(__xludf.DUMMYFUNCTION("""COMPUTED_VALUE"""),"Chase Ecker (4) - '25 COF PA") -> Chase Ecker (4) - '25 COF PA | D57: Chase Ecker | E57: OF | H57: Chase | I57: Ecker | J57: 2025 | K57: 4 | M57: COF | Q57: PA | R57: Malvern Prep | S57: Bellringers | AA57: TR: Have had several phone calls. didn't prioritze as another OF but has had some real interest. Freddy said he checks all boxes not sure about bat at d1 level but elite speed. Spoke with him 8/9 has offers, had a visist cancelled to coastal. not sure his offers are right fit and hoping to play through fall. | AB57: cecker05@malvernprep.org | AC57: Malvern Prep Baseball- Conference Champs, State Champs, played every game most of them being leadoff hitter, earned All League in the Inter Rac. Future games invite, Carpenter Cup Team, Fastest 60 time leaderboard in PA, Best in the US MLB invite. | AD57: 4 | AF57: Hip Flexor Freshman year and a Hand/Wrist injury my junior season. Was still able to play through both. | AG57: No | AH57: No | AI57: No
B58: 1 | C58: =IFERROR(__xludf.DUMMYFUNCTION("""COMPUTED_VALUE"""),"Evan Martinez (4) - '25 LHP TX") -> Evan Martinez (4) - '25 LHP TX | D58: Evan Martinez | E58: LHP | H58: Evan | I58: Martinez | J58: 2025 | K58: 4 | M58: LHP | Q58: TX | R58: Yselta | AA58: 2/3/24: Sounds like Diaz on the phone. Interested in flying. Sounds like a ball player. FB/SL/CH 83-84 up to 86 right now. Doesn't play on the circuit, local team in the summer. Might get to camp.
B59: 1 | C59: =IFERROR(__xludf.DUMMYFUNCTION("""COMPUTED_VALUE"""),"Grant Winkle (4) - '25 LHP TX") -> Grant Winkle (4) - '25 LHP TX | D59: Grant Winkle | E59: LHP | H59: Grant | I59: Winkle | J59: 2025 | K59: 4 | M59: LHP | Q59: TX
B60: 1 | C60: =IFERROR(__xludf.DUMMYFUNCTION("""COMPUTED_VALUE"""),"Kason Herlong (4) - '25 MINF SC") -> Kason Herlong (4) - '25 MINF SC | D60: Kason Herlong | E60: INF | H60: Kason | I60: Herlong | J60: 2025 | K60: 4 | M60: MINF | Q60: SC | R60: Canes | S60: Travellers Rest SC | AA60: JK-video follow. Good enough on film to see in spring. | AB60: rkherl67@gmail.com | AC60: High School: .526 BA 3 HR’s 41 Hits .968 Fielding Percentage | AD60: 5.23 | AE60: 1210 SAT | AF60: N/A | AG60: N/A | AH60: N/A | AI60: N/A
B61: 1 | C61: =IFERROR(__xludf.DUMMYFUNCTION("""COMPUTED_VALUE"""),"Wade Hartrick (4) - '25 RHP CO") -> Wade Hartrick (4) - '25 RHP CO | D61: Wade Hartrick | E61: RHP | H61: Wade | I61: Hartrick | J61: 2025 | K61: 4 | M61: RHP | Q61: CO | R61: USA Prime American | S61: IMG | AA61: TR: Phone call from twitter. Interested in Academy. IMG turned him into pitcher, didn't catch much. SL 80-82. FB up to 89. Plays for USA Prime American 17U. Catching and pitching for Prime. Kind of sounds like Bibb on the phone. Wants to be two way but doesn't know where he is better yet. Has heard from AF & Army. Wants Ivy and thinks he may get an offer soon. But definitely sounded interested.
B62: 1 | C62: =IFERROR(__xludf.DUMMYFUNCTION("""COMPUTED_VALUE"""),"Bryce Wells (XX) - '25 C TX") -> Bryce Wells (XX) - '25 C TX | D62: Bryce Wells | E62: C | H62: Bryce | I62: Wells | J62: 2025 | K62: XX | M62: C | Q62: TX | R62: Smithson Valley | S62: Stix | AA62: AP: 6'0 215 catchers body. Thick lower half. Ran a 4.28 on ball hit to SS. Moves well for body type, twitter claims 6.6 run. 1.9 pop with quick release, avg arm only. Caught clean. Definite follow to high follow to see if bat is good enough. JK: thick strong frame. strong hands good receive, confident behind dish. Hit 5. didn't love arm tool. transfer fine. moves/runs better than expected. Like him. | AB62: Brycewells36@icloud.com | AC62: First team all district | AD62: 3.75 | AE62: 1000. Going to retake in the fall | AF62: None | AG62: None | AH62: None | AI62: None
B63: 1 | C63: =IFERROR(__xludf.DUMMYFUNCTION("""COMPUTED_VALUE"""),"George Willis (XX) - '25 C TX") -> George Willis (XX) - '25 C TX | D63: George Willis | E63: C | H63: George | I63: Willis | J63: 2025 | K63: XX | M63: C | Q63: TX | R63: Kyle Chapman | AA63: JK: Phyiscal solid catch/throw. Hit 4. Good as/carry. Like him in the mix.
B64: 1 | C64: =IFERROR(__xludf.DUMMYFUNCTION("""COMPUTED_VALUE"""),"Jack Fuller (XX) - '25 LHP TX") -> Jack Fuller (XX) - '25 LHP TX | D64: Jack Fuller | E64: LHP | H64: Jack | I64: Fuller | J64: 2025 | K64: XX | M64: LHP | Q64: TX | R64: Southlake Carroll | S64: Stix | AA64: TR Call: Was one of SLC two main starters. 55IP sending stats was all conference. sub 2 era. Has a couple offers. Has some ineterst in Military. Says he is 87-88/89. | AB64: jfullerlefty9@gmail.com | AC64: 4-6A All District Team, Fort Worth Area Team, PBR Futures Games, Perfect Game Junior National, #2 uncommitted pitcher in Texas (Perfect Game) | AD64: 94.86 | AE64: 1280 | AG64: Yes, Tree nuts | AH64: No | AI64: No
B65: 1 | C65: =IFERROR(__xludf.DUMMYFUNCTION("""COMPUTED_VALUE"""),"Jackson Lee (XX) - '25 LHP TN") -> Jackson Lee (XX) - '25 LHP TN | D65: Jackson Lee | E65: LHP | H65: Jackson | I65: Lee | J65: 2025 | K65: XX | M65: LHP | Q65: TN | R65: Columbia Academy | X65: 45542 | AA65: TR Call: Has thrown over 100 IP this year no injury history. Was 87-88/89 lost velo to 85-86 by the end of the summer. 126K in 73 IP. 2nd in K in state won state . | AB65: Jfl82206@gmail.com | AC65: High school stats- 73.2 IP, 126 SO, 10-2 record, 2.00 ERA, All Region Team, All State Team | AD65: 4.3 | AE65: 26-ACT | AF65: None | AG65: None | AH65: None | AI65: No
B66: 1 | C66: =IFERROR(__xludf.DUMMYFUNCTION("""COMPUTED_VALUE"""),"Aidan Nohava (XX) - '25 IL") -> Aidan Nohava (XX) - '25 IL | D66: Aidan Nohava | H66: Aidan | I66: Nohava | J66: 2025 | K66: XX | Q66: IL | R66: Brother Rice | S66: Cangelosi Sparks | AA66: AP: 6'0 190. 3B/1B Hitter, big leg kick and barrelled balls. PRB has 60 at 7.3 but saw him hit a 3B and ran better than that on bases. avg def actions and avg arm. value is a hitter at a good HS.
B67: 1 | C67: =IFERROR(__xludf.DUMMYFUNCTION("""COMPUTED_VALUE"""),"Alexander Menth (XX) - '25 MN") -> Alexander Menth (XX) - '25 MN | D67: Alexander Menth | H67: Alexander | I67: Menth | J67: 2025 | K67: XX | Q67: MN | R67: Minneapolis South | AA67: TR: Call 2/9. Twitter video is loose and whippy. up to 86-87/88. 6'5" 200lbs. Northstar Baseball summer.
B68: 1 | C68: =IFERROR(__xludf.DUMMYFUNCTION("""COMPUTED_VALUE"""),"Alexander Pearson (XX) - '25 OR") -> Alexander Pearson (XX) - '25 OR | D68: Alexander Pearson | H68: Alexander | I68: Pearson | J68: 2025 | K68: XX | Q68: OR | R68: Tigard | AA68: Futures. Left handed stick, kid swings it. Attacks strikes and makes hard LD contact with drive. Has some pop. Also pitched - 82-84/66-67. Competes on mound has more command and velo in the tank. Zero separation or use of ground.
B69: 1 | C69: =IFERROR(__xludf.DUMMYFUNCTION("""COMPUTED_VALUE"""),"Andrew Krupa (XX) - '25 IN") -> Andrew Krupa (XX) - '25 IN | D69: Andrew Krupa | H69: Andrew | I69: Krupa | J69: 2025 | K69: XX | Q69: IN | R69: Center Grove HS | S69: Team INDIANA (Bulls) | AA69: AP: 6'4 180 long lean athlete. 6.7 runner. LHH light w/ bat now but projects. should have some leverage in swing. big upside guy
B70: 1 | C70: =IFERROR(__xludf.DUMMYFUNCTION("""COMPUTED_VALUE"""),"Andrew Winslow (XX) - '25 IL") -> Andrew Winslow (XX) - '25 IL | D70: Andrew Winslow | H70: Andrew | I70: Winslow | J70: 2025 | K70: XX | Q70: IL | R70: Triad | AA70: Futures. This kid is a very different look, can't see the ball. 6'6" wiry frame with a quick arm. Very low slot slinger. 88-89 21 spin. 74-75 22 spin. commands gs and feel for spin. Cmds FB to both sides and hides the ball very well. frame for added velo.
B71: 1 | C71: =IFERROR(__xludf.DUMMYFUNCTION("""COMPUTED_VALUE"""),"Anthony Frobose (XX) - '25 NY") -> Anthony Frobose (XX) - '25 NY | D71: Anthony Frobose | H71: Anthony | I71: Frobose | J71: 2025 | K71: XX | Q71: NY | R71: Lakeland HS | AA71: 8/1 Call - Very good phone call with Anthony and Dad. Were not sure at start and seemed very interested by the end of the call. Really took to $ and setting him up for future. Kid is a ballplayer has a lot of traffic. They are extremely interested in visiting and learning more. Getting him more info today. Tim saw at two events. Del team camp and 16u GA. The kid hits, drives the ball to all fields. Extremely atheltic build, physical with QT. Runs very well with high IQ. Very good actions at SS with plenty of arm. No brainer offer Aug 1. Have spoken with coach and he is interested. Will have a good amount of quality baseball offers.
B72: 1 | C72: =IFERROR(__xludf.DUMMYFUNCTION("""COMPUTED_VALUE"""),"Austin Moran (XX) - '25 NC") -> Austin Moran (XX) - '25 NC | D72: Austin Moran | H72: Austin | I72: Moran | J72: 2025 | K72: XX | Q72: NC | R72: SBA | S72: Cuthbertson HS | AA72: JK-same team as Aldredge. More physical, possibly more offensive and more of a corner guy. Has interest. Reconnected in March 2024. Spoke with his HS coach (former D1 athlete) as well. Glowing recs. HS QB. No questions about him. Kid is close with his family/knows him well. super high character, elite level player in multiple sports
B73: 1 | C73: =IFERROR(__xludf.DUMMYFUNCTION("""COMPUTED_VALUE"""),"Austin Musso (XX) - '25 IL") -> Austin Musso (XX) - '25 IL | D73: Austin Musso | H73: Austin | I73: Musso | J73: 2025 | K73: XX | Q73: IL | R73: Mascoutah | AA73: Call 8/2 - Some interest but leaning toward no. Sending info to follow up AP: Futures. 6'1 180. good arm speed. 86-88 and located. 75 SL good, 2200 spin. not the tallest frame but pitched really well at Futures and carried himself like he was a stud. really liked his look.
B74: 1 | C74: =IFERROR(__xludf.DUMMYFUNCTION("""COMPUTED_VALUE"""),"Baylor Roberts (XX) - '25 MS") -> Baylor Roberts (XX) - '25 MS | D74: Baylor Roberts | H74: Baylor | I74: Roberts | J74: 2025 | K74: XX | Q74: MS | R74: Saltillo HS | AA74: 9/18 Call: Showed some interest. Sent info, need to follow up next week. Not going to be playing again this fall.TR - Saw at PBR Cup. High level athletic actions at SS. Separates his hands below the knees. Runs better functionally than his 60 time. Good turn and BC at the plate. Has a frame to add strength. Plays the game like he loves it. Toldme wasn't interested in service
B75: 1 | C75: =IFERROR(__xludf.DUMMYFUNCTION("""COMPUTED_VALUE"""),"Ben Pulliam (XX) - '25 VA") -> Ben Pulliam (XX) - '25 VA | D75: Ben Pulliam | H75: Ben | I75: Pulliam | J75: 2025 | K75: XX | Q75: VA | R75: Glen Allen HS | S75: Richmond Braves | AA75: TR saw in Ft. Myers. Not a fast mover, runs hunched over. Big body slow bat. Not off list but not a guy for us right now. Video from NCSA - emailed to setup call. Great phone call high interest. 6.7 runner hit 2 hole for HS and leadoff in summer. Sending me some stats. Playing for Rich braves. 4.0 in honors calc as junior.
B76: 1 | C76: =IFERROR(__xludf.DUMMYFUNCTION("""COMPUTED_VALUE"""),"Ben Toft (XX) - '25 IL") -> Ben Toft (XX) - '25 IL | D76: Ben Toft | H76: Ben | I76: Toft | J76: 2025 | K76: XX | Q76: IL | R76: New Trier | AA76: AP: Futures. 5'10 165 very small. LHH with great swing and bat speed for size. 6.8 runner. just a low follow at this point
B77: 1 | C77: =IFERROR(__xludf.DUMMYFUNCTION("""COMPUTED_VALUE"""),"Blake Sebastian (XX) - '25 KS") -> Blake Sebastian (XX) - '25 KS | D77: Blake Sebastian | H77: Blake | I77: Sebastian | J77: 2025 | K77: XX | Q77: KS | R77: Blue Valley North | AA77: TR: Call 2/10. Coach had great things to say. Made big jump over fall. Big strong tough kid could be true 2 way. Not sure he has a position but may be quality arm. max effort but velo rising. Building champions setting up a call. Video and metrics check out. Looks like a high level athlete, digging in.
B78: 1 | C78: =IFERROR(__xludf.DUMMYFUNCTION("""COMPUTED_VALUE"""),"Bobby Christenson (XX) - '25 NJ") -> Bobby Christenson (XX) - '25 NJ | D78: Bobby Christenson | H78: Bobby | I78: Christenson | J78: 2025 | K78: XX | Q78: NJ | R78: St. Joe - Met | AA78: TR: John Murphy recc. Hitting .517 left handed hitter. Playing ss havent seen any def video. Swing looks powerful strong. confident kid on the phone.
B79: 1 | C79: =IFERROR(__xludf.DUMMYFUNCTION("""COMPUTED_VALUE"""),"Brad Marks (XX) - '25 DE") -> Brad Marks (XX) - '25 DE | D79: Brad Marks | H79: Brad | I79: Marks | J79: 2025 | K79: XX | Q79: DE | R79: Cape Henlopen | S79: Richmond braves | AA79: AP: update: not effect at PBR 17u, stuff a tick down. 6'0 170 skinny. Fast arm. Possible 3 pitches. 86-89 (90), 76 SL, good CH deceptive. Fast arm and works fast. Threw strikes and threw put-away pitches. Check performance history. JK email notes: Top 500 #2 rhp in DE.
B80: 1 | C80: =IFERROR(__xludf.DUMMYFUNCTION("""COMPUTED_VALUE"""),"Braden Polsky (XX) - '25 NC") -> Braden Polsky (XX) - '25 NC | D80: Braden Polsky | H80: Braden | I80: Polsky | J80: 2025 | K80: XX | Q80: NC | R80: Cannon | AA80: TR - Saw twice. Not enough strikes. Has some arm speed and arm strength. looks the part and has athleticism. Have had some phone calls need to see again in spring/summer
B81: 1 | C81: =IFERROR(__xludf.DUMMYFUNCTION("""COMPUTED_VALUE"""),"Brady Ferguson (XX) - '25 NE") -> Brady Ferguson (XX) - '25 NE | D81: Brady Ferguson | H81: Brady | I81: Ferguson | J81: 2025 | K81: XX | Q81: NE | R81: Millard West | AA81: AP: Futures. 6'2 190 good body. 86-88 with good SL. good tempo and delivery. 3/4 slot. great arm speed. easy YES
B82: 1 | C82: =IFERROR(__xludf.DUMMYFUNCTION("""COMPUTED_VALUE"""),"Brady Hewitt (XX) - '25 CA") -> Brady Hewitt (XX) - '25 CA | D82: Brady Hewitt | H82: Brady | I82: Hewitt | J82: 2025 | K82: XX | Q82: CA | R82: Royal ? Sierra Canyon HS | S82: SoCal Giants | AA82: AP: 6'1 185. best bat on SoCal Giants. strong body. +bat speed. +swing. = arm, = def, mayby not pure SS, stiff actions.
B83: 1 | C83: =IFERROR(__xludf.DUMMYFUNCTION("""COMPUTED_VALUE"""),"Brady Kaufman (XX) - '25 OH") -> Brady Kaufman (XX) - '25 OH | D83: Brady Kaufman | H83: Brady | I83: Kaufman | J83: 2025 | K83: XX | Q83: OH | X83: 45855 | AA83: JK: 90-91 / SL 77-78. Fast arm twitchy. Athletic. showed CH. | AB83: bradykaufman1111@yahoo.com | AC83: Highschool pitching: 43 innings 74 K’s 8BB 0.00ERA .121BAA | AD83: 3.95 | AE83: Act 22 | AF83: None | AG83: None | AH83: None | AI83: None
B84: 1 | C84: =IFERROR(__xludf.DUMMYFUNCTION("""COMPUTED_VALUE"""),"Brayden Mercier (XX) - '25 MA") -> Brayden Mercier (XX) - '25 MA | D84: Brayden Mercier | H84: Brayden | I84: Mercier | J84: 2025 | K84: XX | Q84: MA | R84: St Johns Shrews | S84: Nor'Easter Runbirds | AA84: JK-spoke on phone. Solid kid. Possible low GPA. 2 C's on transcript. Film was good. Offer from HC. Maine/Bryant/Fairfield/NJIT.
B85: 1 | C85: =IFERROR(__xludf.DUMMYFUNCTION("""COMPUTED_VALUE"""),"Brayton Coomer (XX) - '25 CINF KY") -> Brayton Coomer (XX) - '25 CINF KY | D85: Brayton Coomer | E85: INF | H85: Brayton | I85: Coomer | J85: 2025 | K85: XX | M85: CINF | Q85: KY | R85: Adair Co HS | S85: Louisville legends | AA85: AP: 6'5 210. not a need right now. Hitter. high contact, potential pwr in there bc/ of leverage in swing. room to fill out more. small town country kid, raised himself. avg run, avg arm. only saw play 1B. taking ACT in July. probably a longshot to get to a 26 | AB85: b.coomer45@icloud.com | AD85: 3.8 | AE85: 19 | AF85: nose surgery | AG85: no | AH85: no | AI85: no
B86: 1 | C86: =IFERROR(__xludf.DUMMYFUNCTION("""COMPUTED_VALUE"""),"Brock Ketelsen (XX) - '25 CA") -> Brock Ketelsen (XX) - '25 CA | D86: Brock Ketelsen | H86: Brock | I86: Ketelsen | J86: 2025 | K86: XX | Q86: CA | R86: Valley Christian | AA86: AP: Futures. 6'3 185 tall lean nice body. 6.7 run, moves well. Nice swing with good leverage. potential for some pop. 95 EV max. avg arm. Need to contact HS coach to make sure he checks out
B87: 1 | C87: =IFERROR(__xludf.DUMMYFUNCTION("""COMPUTED_VALUE"""),"Brody Winemiller (XX) - '25 CINF TN") -> Brody Winemiller (XX) - '25 CINF TN | D87: Brody Winemiller | E87: INF | H87: Brody | I87: Winemiller | J87: 2025 | K87: XX | M87: CINF | Q87: TN | R87: Collierville | S87: EC Sox | X87: 45839 | AA87: AP: 6'4 200. BAT! saw hit 500 ft HR. good bat speed and good swing. strong. future game player. avg run, avg def, arm needs work. played corner OF and 1B for HS. HS coach loves the kid, faith is important to kid. sister is in Navy | AB87: Brodywinemiller@icloud.com | AC87: Started varsity since freshman year. 12 total high school home runs. Led the team in RBI’s as a sophomore. Led the team in home runs with 6 as a junior. Won defensive player of the year as a junior. | AD87: 4.3 weighted | AE87: ACT-24 | AF87: Broken foot-Baseball. Concussion-Football | AG87: No | AH87: No | AI87: No
B88: 1 | C88: =IFERROR(__xludf.DUMMYFUNCTION("""COMPUTED_VALUE"""),"Bryce Neely (XX) - '25 VA") -> Bryce Neely (XX) - '25 VA | D88: Bryce Neely | H88: Bryce | I88: Neely | J88: 2025 | K88: XX | Q88: VA | R88: St Christophers | AA88: AP: Futures. 5'11 180 strong body. 6.5 runner, +speed. gets a good swing off. need to see more to see if he can actually hit.
B89: 1 | C89: =IFERROR(__xludf.DUMMYFUNCTION("""COMPUTED_VALUE"""),"Bryce Palms (XX) - '25 MD") -> Bryce Palms (XX) - '25 MD | D89: Bryce Palms | H89: Bryce | I89: Palms | J89: 2025 | K89: XX | Q89: MD | R89: DeMatha Catholic | X89: 45241 | AA89: AP: update 7/20/24 85-87 w/ no BB. not enough for us. 6'0 180 Update: 3/13/24 85-86 arm works. 3 IP 2K, 5-6 balls got barreled. did not throw any offspeed? needs to improve to be a guy for us. 82-85. clean arm, clean delivery. JK-seen and spoke to. Athletic arm. Seems like avg junior year and avg student. Likely a prep candidate at best.
B90: 1 | C90: =IFERROR(__xludf.DUMMYFUNCTION("""COMPUTED_VALUE"""),"Caden Blanck (XX) - '25 MD") -> Caden Blanck (XX) - '25 MD | D90: Caden Blanck | H90: Caden | I90: Blanck | J90: 2025 | K90: XX | Q90: MD | R90: Severn School | S90: US Elite
B91: 1 | C91: =IFERROR(__xludf.DUMMYFUNCTION("""COMPUTED_VALUE"""),"Caden Williamson (XX) - '25 CF CO") -> Caden Williamson (XX) - '25 CF CO | D91: Caden Williamson | E91: OF | H91: Caden | I91: Williamson | J91: 2025 | K91: XX | M91: CF | Q91: CO | R91: Broomfield | S91: Slammers | AA91: AP/TR: 5'10 maybe 175. short but strong. 6.7 runner. good bat speed. 2B's pop. .365 7 2B's 21 SB's in HS '24. saw @ PG Beast of East 6/8/24
B92: 1 | C92: =IFERROR(__xludf.DUMMYFUNCTION("""COMPUTED_VALUE"""),"Caeden Cloud (XX) - '25 MO") -> Caeden Cloud (XX) - '25 MO | D92: Caeden Cloud | H92: Caeden | I92: Cloud | J92: 2025 | K92: XX | Q92: MO | R92: Nixa | AA92: Futures. Very physical and athletic SS. HC kid barrels balls. Very plus actions and arm strength. High end talent. Shooter calls him best SS in country. Dad was Army.
B93: 1 | C93: =IFERROR(__xludf.DUMMYFUNCTION("""COMPUTED_VALUE"""),"Caleb Sweeney (XX) - '25 AZ") -> Caleb Sweeney (XX) - '25 AZ | D93: Caleb Sweeney | H93: Caleb | I93: Sweeney | J93: 2025 | K93: XX | Q93: AZ | R93: Valley Christian | S93: FS21 Stars | AA93: AP: 6'1 200 86-87, avg SL sweeping, =/+ CH good feel. plus pick to 1B.
B94: 1 | C94: =IFERROR(__xludf.DUMMYFUNCTION("""COMPUTED_VALUE"""),"Cameron Millar (XX) - '25 CA") -> Cameron Millar (XX) - '25 CA | D94: Cameron Millar | H94: Cameron | I94: Millar | J94: 2025 | K94: XX | Q94: CA | R94: Alhambra | AA94: AP: 6'2 175. loose arm w/ good hand speed. 88-90, 75-76 SL, 80 CH has some feel for it. really like the look!
B95: 1 | C95: =IFERROR(__xludf.DUMMYFUNCTION("""COMPUTED_VALUE"""),"Carson Zagryn (XX) - '25 GA") -> Carson Zagryn (XX) - '25 GA | D95: Carson Zagryn | H95: Carson | I95: Zagryn | J95: 2025 | K95: XX | Q95: GA | R95: Blessed Trinity | S95: 643 | AA95: JK- no brainer offensive talent. Unclear on interest. Still uncommitted (Dec 2023). Communication gone a bit cold
B96: 1 | C96: =IFERROR(__xludf.DUMMYFUNCTION("""COMPUTED_VALUE"""),"Carter Brown (XX) - '25 AZ") -> Carter Brown (XX) - '25 AZ | D96: Carter Brown | H96: Carter | I96: Brown | J96: 2025 | K96: XX | Q96: AZ | R96: Cacturs Shadows | AA96: AP: update: slow start to 24 on mound. lots of BB's. hitting ok though. saw in academic game AZ fall '23. Hit a HR. Will be duel guy for HS. Starter on the mound. probably more potential on mound. need to find out interest in military
B97: 1 | C97: =IFERROR(__xludf.DUMMYFUNCTION("""COMPUTED_VALUE"""),"Carter Wilcox (XX) - '25 CO") -> Carter Wilcox (XX) - '25 CO | D97: Carter Wilcox | H97: Carter | I97: Wilcox | J97: 2025 | K97: XX | Q97: CO | R97: Cherokee Trail | AA97: Futures. 85-87 20 / 70-73 25. Whippy arm ath frame. High level of pitchability. Check in on.
B98: 1 | C98: =IFERROR(__xludf.DUMMYFUNCTION("""COMPUTED_VALUE"""),"Case Bosch (XX) - '25 MI") -> Case Bosch (XX) - '25 MI | D98: Case Bosch | H98: Case | I98: Bosch | J98: 2025 | K98: XX | Q98: MI | R98: Jenison | AA98: TR-texted 1/3 Futures. 84-86 / 72-75.Keep an eye on. Just ok with spin but athletic and colud clean up arm action. Physical build good frame projects if he cleans some things up.
B99: 1 | C99: =IFERROR(__xludf.DUMMYFUNCTION("""COMPUTED_VALUE"""),"Casey Carpenter (XX) - '25 MD") -> Casey Carpenter (XX) - '25 MD | D99: Casey Carpenter | H99: Casey | I99: Carpenter | J99: 2025 | K99: XX | Q99: MD | R99: BelAir | S99: John Carroll | AA99: JK-Liked during soph year. Good player. Same team as Ryzbinski
B100: 1 | C100: =IFERROR(__xludf.DUMMYFUNCTION("""COMPUTED_VALUE"""),"Cash McDade (XX) - '25 VA") -> Cash McDade (XX) - '25 VA | D100: Cash McDade | H100: Cash | I100: McDade | J100: 2025 | K100: XX | Q100: VA | R100: Gonzaga | AA100: AP: Futures. big time arm! 1.9 pop. Flat strong swing with good bat speed. pwr could develop. non athlete, doesn't move well. had a fantastic future games. threw out every baserunner.
...

Sheet StarUpdater
A1: PASTE UPDATED RANKINGS HERE - They will then appear in Column AJ on Player sheet
A2: Name | B2: Team | C2: Cur ★ | D2: New ★

Sheet Big Board by Position
B1: 0.1 Committed 1 Offer 2 High Follow 3 Follow 4 Need to see XX Commited Elsewhere | H1: RECRUITING BOARD BY POSITION | AJ1: 1
N2: CLASS: | O2: 2027
B3: RHP | H3: LHP | N3: INF | U3: OF | AB3: C
B4: NAME | D4: STATE | E4: TEAM | F4: ★ | H4: NAME | J4: STATE | K4: TEAM | L4: ★ | N4: NAME | P4: B/T | Q4: STATE | R4: TEAM | S4: ★ | U4: NAME | W4: B/T | X4: STATE | Y4: TEAM | Z4: ★ | AB4: NAME | AD4: B/T | AE4: STATE | AF4: TEAM | AG4: ★
B5: =IFERROR(__xludf.DUMMYFUNCTION("iferror(FILTER('High School Players'!$D:$D,$O$2='High School Players'!$J:$J,B3='High School Players'!$M:$M,$AJ$1='High School Players'!$B:$B,'High School Players'!$K:$K<3))"),"Kolby Crosby") -> Kolby Crosby | D5: =IFERROR(__xludf.DUMMYFUNCTION("iferror(FILTER('High School Players'!$Q:$Q,$O$2='High School Players'!$J:$J,B3='High School Players'!$M:$M,$AJ$1='High School Players'!$B:$B,'High School Players'!$K:$K<3))"),"NY") -> NY | E5: =IFERROR(__xludf.DUMMYFUNCTION("iferror(FILTER('High School Players'!$S:$S,$O$2='High School Players'!$J:$J,B3='High School Players'!$M:$M,$AJ$1='High School Players'!$B:$B,'High School Players'!$K:$K<3))"),"TKR Reds") -> TKR Reds | F5: =IFERROR(__xludf.DUMMYFUNCTION("iferror(FILTER('High School Players'!$K:$K,$O$2='High School Players'!$J:$J,B3='High School Players'!$M:$M,$AJ$1='High School Players'!$B:$B,'High School Players'!$K:$K<3))"),0.1) -> 0.1 | H5: =IFERROR(__xludf.DUMMYFUNCTION("iferror(FILTER('High School Players'!$D:$D,$O$2='High School Players'!$J:$J,H3='High School Players'!$M:$M,$AJ$1='High School Players'!$B:$B,'High School Players'!$K:$K<3))"),"Maddux Hasty") -> Maddux Hasty | J5: =IFERROR(__xludf.DUMMYFUNCTION("iferror(FILTER('High School Players'!$Q:$Q,$O$2='High School Players'!$J:$J,H3='High School Players'!$M:$M,$AJ$1='High School Players'!$B:$B,'High School Players'!$K:$K<3))"),"TN") -> TN | K5: =IFERROR(__xludf.DUMMYFUNCTION("iferror(FILTER('High School Players'!$S:$S,$O$2='High School Players'!$J:$J,H3='High School Players'!$M:$M,$AJ$1='High School Players'!$B:$B,'High School Players'!$K:$K<3))"),"") | L5: =IFERROR(__xludf.DUMMYFUNCTION("iferror(FILTER('High School Players'!$K:$K,$O$2='High School Players'!$J:$J,H3='High School Players'!$M:$M,$AJ$1='High School Players'!$B:$B,'High School Players'!$K:$K<3))"),2.0) -> 2 | N5: =IFERROR(__xludf.DUMMYFUNCTION("iferror(FILTER('High School Players'!$D:$D,$O$2='High School Players'!$J:$J,N3='High School Players'!$E:$E,$AJ$1='High School Players'!$B:$B,'High School Players'!$K:$K<3))"),"Zach Madar") -> Zach Madar | P5: =IFERROR(__xludf.DUMMYFUNCTION("iferror(FILTER('High School Players'!$O:$O,$O$2='High School Players'!$J:$J,N3='High School Players'!$E:$E,$AJ$1='High School Players'!$B:$B,'High School Players'!$K:$K<3))"),"R/R") -> R/R | Q5: =IFERROR(__xludf.DUMMYFUNCTION("iferror(FILTER('High School Players'!$Q:$Q,$O$2='High School Players'!$J:$J,N3='High School Players'!$E:$E,$AJ$1='High School Players'!$B:$B,'High School Players'!$K:$K<3))"),"TN") -> TN | R5: =IFERROR(__xludf.DUMMYFUNCTION("iferror(FILTER('High School Players'!$S:$S,$O$2='High School Players'!$J:$J,N3='High School Players'!$E:$E,$AJ$1='High School Players'!$B:$B,'High School Players'!$K:$K<3))"),"FTB Tennessee") -> FTB Tennessee | S5: =IFERROR(__xludf.DUMMYFUNCTION("iferror(FILTER('High School Players'!$K:$K,$O$2='High School Players'!$J:$J,N3='High School Players'!$E:$E,$AJ$1='High School Players'!$B:$B,'High School Players'!$K:$K<3))"),0.1) -> 0.1 | U5: =IFERROR(__xludf.DUMMYFUNCTION("iferror(FILTER('High School Players'!$D:$D,$O$2='High School Players'!$J:$J,U3='High School Players'!$E:$E,$AJ$1='High School Players'!$B:$B,'High School Players'!$K:$K<3))"),"Zachary DeHaas") -> Zachary DeHaas | W5: =IFERROR(__xludf.DUMMYFUNCTION("iferror(FILTER('High School Players'!$O:$O,$O$2='High School Players'!$J:$J,U3='High School Players'!$E:$E,$AJ$1='High School Players'!$B:$B,'High School Players'!$K:$K<3))"),"R/R") -> R/R | X5: =IFERROR(__xludf.DUMMYFUNCTION("iferror(FILTER('High School Players'!$Q:$Q,$O$2='High School Players'!$J:$J,U3='High School Players'!$E:$E,$AJ$1='High School Players'!$B:$B,'High School Players'!$K:$K<3))"),"MO") -> MO | Y5: =IFERROR(__xludf.DUMMYFUNCTION("iferror(FILTER('High School Players'!$S:$S,$O$2='High School Players'!$J:$J,U3='High School Players'!$E:$E,$AJ$1='High School Players'!$B:$B,'High School Players'!$K:$K<3))"),"") | Z5: =IFERROR(__xludf.DUMMYFUNCTION("iferror(FILTER('High School Players'!$K:$K,$O$2='High School Players'!$J:$J,U3='High School Players'!$E:$E,$AJ$1='High School Players'!$B:$B,'High School Players'!$K:$K<3))"),2.0) -> 2 | AB5: =IFERROR(__xludf.DUMMYFUNCTION("iferror(FILTER('High School Players'!$D:$D,$O$2='High School Players'!$J:$J,AB3='High School Players'!$M:$M,$AJ$1='High School Players'!$B:$B,'High School Players'!$K:$K<3))"),"Caleb Flannery") -> Caleb Flannery | AD5: =IFERROR(__xludf.DUMMYFUNCTION("iferror(FILTER('High School Players'!$O:$O,$O$2='High School Players'!$J:$J,AB3='High School Players'!$M:$M,$AJ$1='High School Players'!$B:$B,'High School Players'!$K:$K<3))"),"") | AE5: =IFERROR(__xludf.DUMMYFUNCTION("iferror(FILTER('High School Players'!$Q:$Q,$O$2='High School Players'!$J:$J,AB3='High School Players'!$M:$M,$AJ$1='High School Players'!$B:$B,'High School Players'!$K:$K<3))"),"PA") -> PA | AF5: =IFERROR(__xludf.DUMMYFUNCTION("iferror(FILTER('High School Players'!$S:$S,$O$2='High School Players'!$J:$J,AB3='High School Players'!$M:$M,$AJ$1='High School Players'!$B:$B,'High School Players'!$K:$K<3))"),"") | AG5: =IFERROR(__xludf.DUMMYFUNCTION("iferror(FILTER('High School Players'!$K:$K,$O$2='High School Players'!$J:$J,AB3='High School Players'!$M:$M,$AJ$1='High School Players'!$B:$B,'High School Players'!$K:$K<3))"),0.1) -> 0.1
B6: =IFERROR(__xludf.DUMMYFUNCTION("""COMPUTED_VALUE"""),"Jude Davidson") -> Jude Davidson | D6: =IFERROR(__xludf.DUMMYFUNCTION("""COMPUTED_VALUE"""),"AL") -> AL | E6: =IFERROR(__xludf.DUMMYFUNCTION("""COMPUTED_VALUE"""),"Excel Blue Wave") -> Excel Blue Wave | F6: =IFERROR(__xludf.DUMMYFUNCTION("""COMPUTED_VALUE"""),0.1) -> 0.1 | H6: =IFERROR(__xludf.DUMMYFUNCTION("""COMPUTED_VALUE"""),"Sladen Johnson") -> Sladen Johnson | J6: =IFERROR(__xludf.DUMMYFUNCTION("""COMPUTED_VALUE"""),"MA") -> MA | K6: =IFERROR(__xludf.DUMMYFUNCTION("""COMPUTED_VALUE"""),"Boston Prime") -> Boston Prime | L6: =IFERROR(__xludf.DUMMYFUNCTION("""COMPUTED_VALUE"""),2.0) -> 2 | N6: =IFERROR(__xludf.DUMMYFUNCTION("""COMPUTED_VALUE"""),"Stevie Wellens") -> Stevie Wellens | P6: =IFERROR(__xludf.DUMMYFUNCTION("""COMPUTED_VALUE"""),"R/R") -> R/R | Q6: =IFERROR(__xludf.DUMMYFUNCTION("""COMPUTED_VALUE"""),"CA") -> CA | S6: =IFERROR(__xludf.DUMMYFUNCTION("""COMPUTED_VALUE"""),0.1) -> 0.1 | U6: =IFERROR(__xludf.DUMMYFUNCTION("""COMPUTED_VALUE"""),"Win Hoots") -> Win Hoots | X6: =IFERROR(__xludf.DUMMYFUNCTION("""COMPUTED_VALUE"""),"GA") -> GA | Y6: =IFERROR(__xludf.DUMMYFUNCTION("""COMPUTED_VALUE"""),"643 DP") -> 643 DP | Z6: =IFERROR(__xludf.DUMMYFUNCTION("""COMPUTED_VALUE"""),1.0) -> 1 | AB6: =IFERROR(__xludf.DUMMYFUNCTION("""COMPUTED_VALUE"""),"Parker Filipek") -> Parker Filipek | AD6: =IFERROR(__xludf.DUMMYFUNCTION("""COMPUTED_VALUE"""),"L/R") -> L/R | AE6: =IFERROR(__xludf.DUMMYFUNCTION("""COMPUTED_VALUE"""),"NC") -> NC | AG6: =IFERROR(__xludf.DUMMYFUNCTION("""COMPUTED_VALUE"""),1.0) -> 1
B7: =IFERROR(__xludf.DUMMYFUNCTION("""COMPUTED_VALUE"""),"Jack Van Gemert") -> Jack Van Gemert | D7: =IFERROR(__xludf.DUMMYFUNCTION("""COMPUTED_VALUE"""),"MN") -> MN | E7: =IFERROR(__xludf.DUMMYFUNCTION("""COMPUTED_VALUE"""),"GRB Northstar") -> GRB Northstar | F7: =IFERROR(__xludf.DUMMYFUNCTION("""COMPUTED_VALUE"""),0.1) -> 0.1 | H7: =IFERROR(__xludf.DUMMYFUNCTION("""COMPUTED_VALUE"""),"Owen Sieve") -> Owen Sieve | J7: =IFERROR(__xludf.DUMMYFUNCTION("""COMPUTED_VALUE"""),"TX") -> TX | K7: =IFERROR(__xludf.DUMMYFUNCTION("""COMPUTED_VALUE"""),"Lonestar Baseball Club 2027 National") -> Lonestar Baseball Club 2027 National | L7: =IFERROR(__xludf.DUMMYFUNCTION("""COMPUTED_VALUE"""),2.0) -> 2 | N7: =IFERROR(__xludf.DUMMYFUNCTION("""COMPUTED_VALUE"""),"Bobby Bastek") -> Bobby Bastek | Q7: =IFERROR(__xludf.DUMMYFUNCTION("""COMPUTED_VALUE"""),"GA") -> GA | R7: =IFERROR(__xludf.DUMMYFUNCTION("""COMPUTED_VALUE"""),"643 DP") -> 643 DP | S7: =IFERROR(__xludf.DUMMYFUNCTION("""COMPUTED_VALUE"""),2.0) -> 2 | U7: =IFERROR(__xludf.DUMMYFUNCTION("""COMPUTED_VALUE"""),"Cameron Aguilar") -> Cameron Aguilar | W7: =IFERROR(__xludf.DUMMYFUNCTION("""COMPUTED_VALUE"""),"R/R") -> R/R | X7: =IFERROR(__xludf.DUMMYFUNCTION("""COMPUTED_VALUE"""),"MA") -> MA | Y7: =IFERROR(__xludf.DUMMYFUNCTION("""COMPUTED_VALUE"""),"Nokona") -> Nokona | Z7: =IFERROR(__xludf.DUMMYFUNCTION("""COMPUTED_VALUE"""),2.0) -> 2 | AB7: =IFERROR(__xludf.DUMMYFUNCTION("""COMPUTED_VALUE"""),"Roman Derichsweiler") -> Roman Derichsweiler | AE7: =IFERROR(__xludf.DUMMYFUNCTION("""COMPUTED_VALUE"""),"TX") -> TX | AF7: =IFERROR(__xludf.DUMMYFUNCTION("""COMPUTED_VALUE"""),"Wow Factor Texas 2027") -> Wow Factor Texas 2027 | AG7: =IFERROR(__xludf.DUMMYFUNCTION("""COMPUTED_VALUE"""),2.0) -> 2
B8: =IFERROR(__xludf.DUMMYFUNCTION("""COMPUTED_VALUE"""),"Ethan Wisler") -> Ethan Wisler | D8: =IFERROR(__xludf.DUMMYFUNCTION("""COMPUTED_VALUE"""),"NC") -> NC | E8: =IFERROR(__xludf.DUMMYFUNCTION("""COMPUTED_VALUE"""),"Lynx Baseball") -> Lynx Baseball | F8: =IFERROR(__xludf.DUMMYFUNCTION("""COMPUTED_VALUE"""),0.1) -> 0.1 | H8: =IFERROR(__xludf.DUMMYFUNCTION("""COMPUTED_VALUE"""),"Philip Soltes") -> Philip Soltes | J8: =IFERROR(__xludf.DUMMYFUNCTION("""COMPUTED_VALUE"""),"CT") -> CT | K8: =IFERROR(__xludf.DUMMYFUNCTION("""COMPUTED_VALUE"""),"MVP New England") -> MVP New England | L8: =IFERROR(__xludf.DUMMYFUNCTION("""COMPUTED_VALUE"""),2.0) -> 2 | N8: =IFERROR(__xludf.DUMMYFUNCTION("""COMPUTED_VALUE"""),"Grant Bradley") -> Grant Bradley | Q8: =IFERROR(__xludf.DUMMYFUNCTION("""COMPUTED_VALUE"""),"GA") -> GA | R8: =IFERROR(__xludf.DUMMYFUNCTION("""COMPUTED_VALUE"""),"643 DP") -> 643 DP | S8: =IFERROR(__xludf.DUMMYFUNCTION("""COMPUTED_VALUE"""),1.0) -> 1 | U8: =IFERROR(__xludf.DUMMYFUNCTION("""COMPUTED_VALUE"""),"Matthew Bergin") -> Matthew Bergin | W8: =IFERROR(__xludf.DUMMYFUNCTION("""COMPUTED_VALUE"""),"R/R") -> R/R | Y8: =IFERROR(__xludf.DUMMYFUNCTION("""COMPUTED_VALUE"""),"Boston Prime 17U Navy") -> Boston Prime 17U Navy | Z8: =IFERROR(__xludf.DUMMYFUNCTION("""COMPUTED_VALUE"""),2.0) -> 2 | AB8: =IFERROR(__xludf.DUMMYFUNCTION("""COMPUTED_VALUE"""),"Cruz Garcia") -> Cruz Garcia | AD8: =IFERROR(__xludf.DUMMYFUNCTION("""COMPUTED_VALUE"""),"R/R") -> R/R | AE8: =IFERROR(__xludf.DUMMYFUNCTION("""COMPUTED_VALUE"""),"CA") -> CA | AG8: =IFERROR(__xludf.DUMMYFUNCTION("""COMPUTED_VALUE"""),2.0) -> 2
B9: =IFERROR(__xludf.DUMMYFUNCTION("""COMPUTED_VALUE"""),"Ben Dahlstedt") -> Ben Dahlstedt | D9: =IFERROR(__xludf.DUMMYFUNCTION("""COMPUTED_VALUE"""),"MA") -> MA | E9: =IFERROR(__xludf.DUMMYFUNCTION("""COMPUTED_VALUE"""),"ECNE Expos") -> ECNE Expos | F9: =IFERROR(__xludf.DUMMYFUNCTION("""COMPUTED_VALUE"""),1.0) -> 1 | H9: =IFERROR(__xludf.DUMMYFUNCTION("""COMPUTED_VALUE"""),"Grayson Waters") -> Grayson Waters | J9: =IFERROR(__xludf.DUMMYFUNCTION("""COMPUTED_VALUE"""),"IL") -> IL | K9: =IFERROR(__xludf.DUMMYFUNCTION("""COMPUTED_VALUE"""),"Cangelosi Sparks North 2027") -> Cangelosi Sparks North 2027 | L9: =IFERROR(__xludf.DUMMYFUNCTION("""COMPUTED_VALUE"""),2.0) -> 2 | N9: =IFERROR(__xludf.DUMMYFUNCTION("""COMPUTED_VALUE"""),"Colt Bradshaw") -> Colt Bradshaw | P9: =IFERROR(__xludf.DUMMYFUNCTION("""COMPUTED_VALUE"""),"R/R") -> R/R | Q9: =IFERROR(__xludf.DUMMYFUNCTION("""COMPUTED_VALUE"""),"VA") -> VA | S9: =IFERROR(__xludf.DUMMYFUNCTION("""COMPUTED_VALUE"""),2.0) -> 2 | U9: =IFERROR(__xludf.DUMMYFUNCTION("""COMPUTED_VALUE"""),"Lucas Collure") -> Lucas Collure | W9: =IFERROR(__xludf.DUMMYFUNCTION("""COMPUTED_VALUE"""),"R/R") -> R/R | X9: =IFERROR(__xludf.DUMMYFUNCTION("""COMPUTED_VALUE"""),"NY") -> NY | Z9: =IFERROR(__xludf.DUMMYFUNCTION("""COMPUTED_VALUE"""),2.0) -> 2 | AB9: =IFERROR(__xludf.DUMMYFUNCTION("""COMPUTED_VALUE"""),"Landon Klein") -> Landon Klein | AD9: =IFERROR(__xludf.DUMMYFUNCTION("""COMPUTED_VALUE"""),"R/R") -> R/R | AE9: =IFERROR(__xludf.DUMMYFUNCTION("""COMPUTED_VALUE"""),"WA") -> WA | AG9: =IFERROR(__xludf.DUMMYFUNCTION("""COMPUTED_VALUE"""),2.0) -> 2
B10: =IFERROR(__xludf.DUMMYFUNCTION("""COMPUTED_VALUE"""),"Jaeger Bedford") -> Jaeger Bedford | D10: =IFERROR(__xludf.DUMMYFUNCTION("""COMPUTED_VALUE"""),"FL") -> FL | E10: =IFERROR(__xludf.DUMMYFUNCTION("""COMPUTED_VALUE"""),"Top Tier Roos") -> Top Tier Roos | F10: =IFERROR(__xludf.DUMMYFUNCTION("""COMPUTED_VALUE"""),2.0) -> 2 | H10: =IFERROR(__xludf.DUMMYFUNCTION("""COMPUTED_VALUE"""),"Hutch Weaver") -> Hutch Weaver | J10: =IFERROR(__xludf.DUMMYFUNCTION("""COMPUTED_VALUE"""),"TN") -> TN | K10: =IFERROR(__xludf.DUMMYFUNCTION("""COMPUTED_VALUE"""),"FTB National 2027") -> FTB National 2027 | L10: =IFERROR(__xludf.DUMMYFUNCTION("""COMPUTED_VALUE"""),2.0) -> 2 | N10: =IFERROR(__xludf.DUMMYFUNCTION("""COMPUTED_VALUE"""),"Wesley Dewitt") -> Wesley Dewitt | P10: =IFERROR(__xludf.DUMMYFUNCTION("""COMPUTED_VALUE"""),"L/R") -> L/R | Q10: =IFERROR(__xludf.DUMMYFUNCTION("""COMPUTED_VALUE"""),"UT") -> UT | S10: =IFERROR(__xludf.DUMMYFUNCTION("""COMPUTED_VALUE"""),2.0) -> 2 | U10: =IFERROR(__xludf.DUMMYFUNCTION("""COMPUTED_VALUE"""),"Brayden Goldstein") -> Brayden Goldstein | W10: =IFERROR(__xludf.DUMMYFUNCTION("""COMPUTED_VALUE"""),"L/R") -> L/R | X10: =IFERROR(__xludf.DUMMYFUNCTION("""COMPUTED_VALUE"""),"CA") -> CA | Z10: =IFERROR(__xludf.DUMMYFUNCTION("""COMPUTED_VALUE"""),2.0) -> 2 | AB10: =IFERROR(__xludf.DUMMYFUNCTION("""COMPUTED_VALUE"""),"Cameron Mares") -> Cameron Mares | AD10: =IFERROR(__xludf.DUMMYFUNCTION("""COMPUTED_VALUE"""),"R/R") -> R/R | AE10: =IFERROR(__xludf.DUMMYFUNCTION("""COMPUTED_VALUE"""),"CO") -> CO | AG10: =IFERROR(__xludf.DUMMYFUNCTION("""COMPUTED_VALUE"""),2.0) -> 2
B11: =IFERROR(__xludf.DUMMYFUNCTION("""COMPUTED_VALUE"""),"Connor Christiansen") -> Connor Christiansen | D11: =IFERROR(__xludf.DUMMYFUNCTION("""COMPUTED_VALUE"""),"IN") -> IN | E11: =IFERROR(__xludf.DUMMYFUNCTION("""COMPUTED_VALUE"""),"Canes Midwest") -> Canes Midwest | F11: =IFERROR(__xludf.DUMMYFUNCTION("""COMPUTED_VALUE"""),2.0) -> 2 | H11: =IFERROR(__xludf.DUMMYFUNCTION("""COMPUTED_VALUE"""),"Jackson Wood") -> Jackson Wood | J11: =IFERROR(__xludf.DUMMYFUNCTION("""COMPUTED_VALUE"""),"HI") -> HI | K11: =IFERROR(__xludf.DUMMYFUNCTION("""COMPUTED_VALUE"""),"Hawaii Elite") -> Hawaii Elite | L11: =IFERROR(__xludf.DUMMYFUNCTION("""COMPUTED_VALUE"""),2.0) -> 2 | N11: =IFERROR(__xludf.DUMMYFUNCTION("""COMPUTED_VALUE"""),"Logan Downey") -> Logan Downey | P11: =IFERROR(__xludf.DUMMYFUNCTION("""COMPUTED_VALUE"""),"R/R") -> R/R | Q11: =IFERROR(__xludf.DUMMYFUNCTION("""COMPUTED_VALUE"""),"NJ") -> NJ | R11: =IFERROR(__xludf.DUMMYFUNCTION("""COMPUTED_VALUE"""),"Ghost National 17U Mocha/Mojo") -> Ghost National 17U Mocha/Mojo | S11: =IFERROR(__xludf.DUMMYFUNCTION("""COMPUTED_VALUE"""),2.0) -> 2 | U11: =IFERROR(__xludf.DUMMYFUNCTION("""COMPUTED_VALUE"""),"Ryan Hawken") -> Ryan Hawken | W11: =IFERROR(__xludf.DUMMYFUNCTION("""COMPUTED_VALUE"""),"R/R") -> R/R | X11: =IFERROR(__xludf.DUMMYFUNCTION("""COMPUTED_VALUE"""),"NJ") -> NJ | Y11: =IFERROR(__xludf.DUMMYFUNCTION("""COMPUTED_VALUE"""),"Ghost") -> Ghost | Z11: =IFERROR(__xludf.DUMMYFUNCTION("""COMPUTED_VALUE"""),2.0) -> 2 | AB11: =IFERROR(__xludf.DUMMYFUNCTION("""COMPUTED_VALUE"""),"Eli Quinley") -> Eli Quinley | AD11: =IFERROR(__xludf.DUMMYFUNCTION("""COMPUTED_VALUE"""),"R/R") -> R/R | AE11: =IFERROR(__xludf.DUMMYFUNCTION("""COMPUTED_VALUE"""),"AL") -> AL | AG11: =IFERROR(__xludf.DUMMYFUNCTION("""COMPUTED_VALUE"""),2.0) -> 2
B12: =IFERROR(__xludf.DUMMYFUNCTION("""COMPUTED_VALUE"""),"Caden Christianson") -> Caden Christianson | D12: =IFERROR(__xludf.DUMMYFUNCTION("""COMPUTED_VALUE"""),"CO") -> CO | E12: =IFERROR(__xludf.DUMMYFUNCTION("""COMPUTED_VALUE"""),"East Cobb/SD Padres ST Underclass") -> East Cobb/SD Padres ST Underclass | F12: =IFERROR(__xludf.DUMMYFUNCTION("""COMPUTED_VALUE"""),2.0) -> 2 | H12: =IFERROR(__xludf.DUMMYFUNCTION("""COMPUTED_VALUE"""),"Brayden Rivera") -> Brayden Rivera | J12: =IFERROR(__xludf.DUMMYFUNCTION("""COMPUTED_VALUE"""),"MD") -> MD | K12: =IFERROR(__xludf.DUMMYFUNCTION("""COMPUTED_VALUE"""),"US Elite Mid Atlantic") -> US Elite Mid Atlantic | L12: =IFERROR(__xludf.DUMMYFUNCTION("""COMPUTED_VALUE"""),2.0) -> 2 | N12: =IFERROR(__xludf.DUMMYFUNCTION("""COMPUTED_VALUE"""),"Carter Huff") -> Carter Huff | Q12: =IFERROR(__xludf.DUMMYFUNCTION("""COMPUTED_VALUE"""),"NC") -> NC | R12: =IFERROR(__xludf.DUMMYFUNCTION("""COMPUTED_VALUE"""),"SCP") -> SCP | S12: =IFERROR(__xludf.DUMMYFUNCTION("""COMPUTED_VALUE"""),2.0) -> 2 | U12: =IFERROR(__xludf.DUMMYFUNCTION("""COMPUTED_VALUE"""),"Grant Helms") -> Grant Helms | Y12: =IFERROR(__xludf.DUMMYFUNCTION("""COMPUTED_VALUE"""),"SBA Bolts") -> SBA Bolts | Z12: =IFERROR(__xludf.DUMMYFUNCTION("""COMPUTED_VALUE"""),2.0) -> 2 | AB12: =IFERROR(__xludf.DUMMYFUNCTION("""COMPUTED_VALUE"""),"Jake Lindsey") -> Jake Lindsey | AE12: =IFERROR(__xludf.DUMMYFUNCTION("""COMPUTED_VALUE"""),"MD") -> MD | AF12: =IFERROR(__xludf.DUMMYFUNCTION("""COMPUTED_VALUE"""),"US Elite") -> US Elite | AG12: =IFERROR(__xludf.DUMMYFUNCTION("""COMPUTED_VALUE"""),2.0) -> 2
B13: =IFERROR(__xludf.DUMMYFUNCTION("""COMPUTED_VALUE"""),"Peyton Crews") -> Peyton Crews | D13: =IFERROR(__xludf.DUMMYFUNCTION("""COMPUTED_VALUE"""),"NC") -> NC | E13: =IFERROR(__xludf.DUMMYFUNCTION("""COMPUTED_VALUE"""),"Dirtbags") -> Dirtbags | F13: =IFERROR(__xludf.DUMMYFUNCTION("""COMPUTED_VALUE"""),2.0) -> 2 | H13: =IFERROR(__xludf.DUMMYFUNCTION("""COMPUTED_VALUE"""),"Jack Snakenberg") -> Jack Snakenberg | J13: =IFERROR(__xludf.DUMMYFUNCTION("""COMPUTED_VALUE"""),"TX") -> TX | K13: =IFERROR(__xludf.DUMMYFUNCTION("""COMPUTED_VALUE"""),"Dallas Tigers") -> Dallas Tigers | L13: =IFERROR(__xludf.DUMMYFUNCTION("""COMPUTED_VALUE"""),1.0) -> 1 | N13: =IFERROR(__xludf.DUMMYFUNCTION("""COMPUTED_VALUE"""),"Chayce Kolbert") -> Chayce Kolbert | P13: =IFERROR(__xludf.DUMMYFUNCTION("""COMPUTED_VALUE"""),"R/R") -> R/R | Q13: =IFERROR(__xludf.DUMMYFUNCTION("""COMPUTED_VALUE"""),"NY") -> NY | S13: =IFERROR(__xludf.DUMMYFUNCTION("""COMPUTED_VALUE"""),2.0) -> 2 | U13: =IFERROR(__xludf.DUMMYFUNCTION("""COMPUTED_VALUE"""),"Tyler Honkomp") -> Tyler Honkomp | W13: =IFERROR(__xludf.DUMMYFUNCTION("""COMPUTED_VALUE"""),"R/R") -> R/R | X13: =IFERROR(__xludf.DUMMYFUNCTION("""COMPUTED_VALUE"""),"IA") -> IA | Z13: =IFERROR(__xludf.DUMMYFUNCTION("""COMPUTED_VALUE"""),2.0) -> 2
B14: =IFERROR(__xludf.DUMMYFUNCTION("""COMPUTED_VALUE"""),"Johnny Deaderick") -> Johnny Deaderick | D14: =IFERROR(__xludf.DUMMYFUNCTION("""COMPUTED_VALUE"""),"GA") -> GA | E14: =IFERROR(__xludf.DUMMYFUNCTION("""COMPUTED_VALUE"""),"643 DP") -> 643 DP | F14: =IFERROR(__xludf.DUMMYFUNCTION("""COMPUTED_VALUE"""),2.0) -> 2 | N14: =IFERROR(__xludf.DUMMYFUNCTION("""COMPUTED_VALUE"""),"Justin Labrador") -> Justin Labrador | P14: =IFERROR(__xludf.DUMMYFUNCTION("""COMPUTED_VALUE"""),"R/R") -> R/R | Q14: =IFERROR(__xludf.DUMMYFUNCTION("""COMPUTED_VALUE"""),"NJ") -> NJ | R14: =IFERROR(__xludf.DUMMYFUNCTION("""COMPUTED_VALUE"""),"Diamond Jacks Super 17") -> Diamond Jacks Super 17 | S14: =IFERROR(__xludf.DUMMYFUNCTION("""COMPUTED_VALUE"""),2.0) -> 2 | U14: =IFERROR(__xludf.DUMMYFUNCTION("""COMPUTED_VALUE"""),"Luke Parrish") -> Luke Parrish | X14: =IFERROR(__xludf.DUMMYFUNCTION("""COMPUTED_VALUE"""),"GA") -> GA | Y14: =IFERROR(__xludf.DUMMYFUNCTION("""COMPUTED_VALUE"""),"FL Burn") -> FL Burn | Z14: =IFERROR(__xludf.DUMMYFUNCTION("""COMPUTED_VALUE"""),2.0) -> 2
B15: =IFERROR(__xludf.DUMMYFUNCTION("""COMPUTED_VALUE"""),"Hudson December") -> Hudson December | D15: =IFERROR(__xludf.DUMMYFUNCTION("""COMPUTED_VALUE"""),"CA") -> CA | E15: =IFERROR(__xludf.DUMMYFUNCTION("""COMPUTED_VALUE"""),"PNT") -> PNT | F15: =IFERROR(__xludf.DUMMYFUNCTION("""COMPUTED_VALUE"""),2.0) -> 2 | N15: =IFERROR(__xludf.DUMMYFUNCTION("""COMPUTED_VALUE"""),"Grayson Morris") -> Grayson Morris | Q15: =IFERROR(__xludf.DUMMYFUNCTION("""COMPUTED_VALUE"""),"VA") -> VA | R15: =IFERROR(__xludf.DUMMYFUNCTION("""COMPUTED_VALUE"""),"Ironbridge") -> Ironbridge | S15: =IFERROR(__xludf.DUMMYFUNCTION("""COMPUTED_VALUE"""),2.0) -> 2 | U15: =IFERROR(__xludf.DUMMYFUNCTION("""COMPUTED_VALUE"""),"Mason Sowers") -> Mason Sowers | X15: =IFERROR(__xludf.DUMMYFUNCTION("""COMPUTED_VALUE"""),"CA") -> CA | Z15: =IFERROR(__xludf.DUMMYFUNCTION("""COMPUTED_VALUE"""),2.0) -> 2
B16: =IFERROR(__xludf.DUMMYFUNCTION("""COMPUTED_VALUE"""),"Cade Filleman") -> Cade Filleman | D16: =IFERROR(__xludf.DUMMYFUNCTION("""COMPUTED_VALUE"""),"CO") -> CO | F16: =IFERROR(__xludf.DUMMYFUNCTION("""COMPUTED_VALUE"""),2.0) -> 2 | N16: =IFERROR(__xludf.DUMMYFUNCTION("""COMPUTED_VALUE"""),"Drew Pittman") -> Drew Pittman | P16: =IFERROR(__xludf.DUMMYFUNCTION("""COMPUTED_VALUE"""),"S/R") -> S/R | Q16: =IFERROR(__xludf.DUMMYFUNCTION("""COMPUTED_VALUE"""),"KS") -> KS | S16: =IFERROR(__xludf.DUMMYFUNCTION("""COMPUTED_VALUE"""),2.0) -> 2 | U16: =IFERROR(__xludf.DUMMYFUNCTION("""COMPUTED_VALUE"""),"Carter Taldo") -> Carter Taldo | W16: =IFERROR(__xludf.DUMMYFUNCTION("""COMPUTED_VALUE"""),"R/R") -> R/R | X16: =IFERROR(__xludf.DUMMYFUNCTION("""COMPUTED_VALUE"""),"KS") -> KS | Z16: =IFERROR(__xludf.DUMMYFUNCTION("""COMPUTED_VALUE"""),1.0) -> 1
B17: =IFERROR(__xludf.DUMMYFUNCTION("""COMPUTED_VALUE"""),"Jackson Fulgintine") -> Jackson Fulgintine | D17: =IFERROR(__xludf.DUMMYFUNCTION("""COMPUTED_VALUE"""),"MA") -> MA | E17: =IFERROR(__xludf.DUMMYFUNCTION("""COMPUTED_VALUE"""),"Boston Prime") -> Boston Prime | F17: =IFERROR(__xludf.DUMMYFUNCTION("""COMPUTED_VALUE"""),2.0) -> 2 | N17: =IFERROR(__xludf.DUMMYFUNCTION("""COMPUTED_VALUE"""),"Brennan Walters") -> Brennan Walters | P17: =IFERROR(__xludf.DUMMYFUNCTION("""COMPUTED_VALUE"""),"L/R") -> L/R | Q17: =IFERROR(__xludf.DUMMYFUNCTION("""COMPUTED_VALUE"""),"KY") -> KY | S17: =IFERROR(__xludf.DUMMYFUNCTION("""COMPUTED_VALUE"""),2.0) -> 2 | U17: =IFERROR(__xludf.DUMMYFUNCTION("""COMPUTED_VALUE"""),"Reign Taylor") -> Reign Taylor | X17: =IFERROR(__xludf.DUMMYFUNCTION("""COMPUTED_VALUE"""),"NC") -> NC | Y17: =IFERROR(__xludf.DUMMYFUNCTION("""COMPUTED_VALUE"""),"USA Prime Coastal") -> USA Prime Coastal | Z17: =IFERROR(__xludf.DUMMYFUNCTION("""COMPUTED_VALUE"""),2.0) -> 2
B18: =IFERROR(__xludf.DUMMYFUNCTION("""COMPUTED_VALUE"""),"Reid Gantenbein-Puchi") -> Reid Gantenbein-Puchi | D18: =IFERROR(__xludf.DUMMYFUNCTION("""COMPUTED_VALUE"""),"CA") -> CA | E18: =IFERROR(__xludf.DUMMYFUNCTION("""COMPUTED_VALUE"""),"BPA") -> BPA | F18: =IFERROR(__xludf.DUMMYFUNCTION("""COMPUTED_VALUE"""),2.0) -> 2 | N18: =IFERROR(__xludf.DUMMYFUNCTION("""COMPUTED_VALUE"""),"Ari Wells") -> Ari Wells | P18: =IFERROR(__xludf.DUMMYFUNCTION("""COMPUTED_VALUE"""),"L/L") -> L/L | Q18: =IFERROR(__xludf.DUMMYFUNCTION("""COMPUTED_VALUE"""),"KY") -> KY | S18: =IFERROR(__xludf.DUMMYFUNCTION("""COMPUTED_VALUE"""),2.0) -> 2 | U18: =IFERROR(__xludf.DUMMYFUNCTION("""COMPUTED_VALUE"""),"Joey Terhaar") -> Joey Terhaar | X18: =IFERROR(__xludf.DUMMYFUNCTION("""COMPUTED_VALUE"""),"MN") -> MN | Y18: =IFERROR(__xludf.DUMMYFUNCTION("""COMPUTED_VALUE"""),"Spects National 2027 Marsolek") -> Spects National 2027 Marsolek | Z18: =IFERROR(__xludf.DUMMYFUNCTION("""COMPUTED_VALUE"""),2.0) -> 2
B19: =IFERROR(__xludf.DUMMYFUNCTION("""COMPUTED_VALUE"""),"Carson Glose") -> Carson Glose | D19: =IFERROR(__xludf.DUMMYFUNCTION("""COMPUTED_VALUE"""),"PA") -> PA | F19: =IFERROR(__xludf.DUMMYFUNCTION("""COMPUTED_VALUE"""),2.0) -> 2 | N19: =IFERROR(__xludf.DUMMYFUNCTION("""COMPUTED_VALUE"""),"Brady Mamula") -> Brady Mamula | P19: =IFERROR(__xludf.DUMMYFUNCTION("""COMPUTED_VALUE"""),"R/R") -> R/R | Q19: =IFERROR(__xludf.DUMMYFUNCTION("""COMPUTED_VALUE"""),"MD") -> MD | R19: =IFERROR(__xludf.DUMMYFUNCTION("""COMPUTED_VALUE"""),"Dirtbags Platinum ") -> Dirtbags Platinum | S19: =IFERROR(__xludf.DUMMYFUNCTION("""COMPUTED_VALUE"""),2.0) -> 2 | U19: =IFERROR(__xludf.DUMMYFUNCTION("""COMPUTED_VALUE"""),"Walker Waggoner") -> Walker Waggoner | W19: =IFERROR(__xludf.DUMMYFUNCTION("""COMPUTED_VALUE"""),"R/R") -> R/R | X19: =IFERROR(__xludf.DUMMYFUNCTION("""COMPUTED_VALUE"""),"GA") -> GA | Y19: =IFERROR(__xludf.DUMMYFUNCTION("""COMPUTED_VALUE"""),"East Cobb Yankees") -> East Cobb Yankees | Z19: =IFERROR(__xludf.DUMMYFUNCTION("""COMPUTED_VALUE"""),2.0) -> 2
B20: =IFERROR(__xludf.DUMMYFUNCTION("""COMPUTED_VALUE"""),"Palmer Gobble") -> Palmer Gobble | D20: =IFERROR(__xludf.DUMMYFUNCTION("""COMPUTED_VALUE"""),"VA") -> VA | E20: =IFERROR(__xludf.DUMMYFUNCTION("""COMPUTED_VALUE"""),"Dirtbags 2027 Platinum") -> Dirtbags 2027 Platinum | F20: =IFERROR(__xludf.DUMMYFUNCTION("""COMPUTED_VALUE"""),2.0) -> 2 | N20: =IFERROR(__xludf.DUMMYFUNCTION("""COMPUTED_VALUE"""),"Kohen Madden") -> Kohen Madden | Q20: =IFERROR(__xludf.DUMMYFUNCTION("""COMPUTED_VALUE"""),"MD") -> MD | R20: =IFERROR(__xludf.DUMMYFUNCTION("""COMPUTED_VALUE"""),"Ole Liners") -> Ole Liners | S20: =IFERROR(__xludf.DUMMYFUNCTION("""COMPUTED_VALUE"""),2.0) -> 2 | U20: =IFERROR(__xludf.DUMMYFUNCTION("""COMPUTED_VALUE"""),"Carston Wedemeyer") -> Carston Wedemeyer | X20: =IFERROR(__xludf.DUMMYFUNCTION("""COMPUTED_VALUE"""),"NC") -> NC | Y20: =IFERROR(__xludf.DUMMYFUNCTION("""COMPUTED_VALUE"""),"SBA Bolts National 2027") -> SBA Bolts National 2027 | Z20: =IFERROR(__xludf.DUMMYFUNCTION("""COMPUTED_VALUE"""),2.0) -> 2
B21: =IFERROR(__xludf.DUMMYFUNCTION("""COMPUTED_VALUE"""),"Will Hayes") -> Will Hayes | D21: =IFERROR(__xludf.DUMMYFUNCTION("""COMPUTED_VALUE"""),"CO") -> CO | F21: =IFERROR(__xludf.DUMMYFUNCTION("""COMPUTED_VALUE"""),2.0) -> 2 | N21: =IFERROR(__xludf.DUMMYFUNCTION("""COMPUTED_VALUE"""),"Bryce Fontenot") -> Bryce Fontenot | Q21: =IFERROR(__xludf.DUMMYFUNCTION("""COMPUTED_VALUE"""),"GA") -> GA | R21: =IFERROR(__xludf.DUMMYFUNCTION("""COMPUTED_VALUE"""),"USA Scout National") -> USA Scout National | S21: =IFERROR(__xludf.DUMMYFUNCTION("""COMPUTED_VALUE"""),2.0) -> 2 | U21: =IFERROR(__xludf.DUMMYFUNCTION("""COMPUTED_VALUE"""),"Jackson Bailey") -> Jackson Bailey | X21: =IFERROR(__xludf.DUMMYFUNCTION("""COMPUTED_VALUE"""),"SC") -> SC | Y21: =IFERROR(__xludf.DUMMYFUNCTION("""COMPUTED_VALUE"""),"South Charlotte Panthers") -> South Charlotte Panthers | Z21: =IFERROR(__xludf.DUMMYFUNCTION("""COMPUTED_VALUE"""),2.0) -> 2
B22: =IFERROR(__xludf.DUMMYFUNCTION("""COMPUTED_VALUE"""),"Thurston Kiefer") -> Thurston Kiefer | D22: =IFERROR(__xludf.DUMMYFUNCTION("""COMPUTED_VALUE"""),"MA") -> MA | E22: =IFERROR(__xludf.DUMMYFUNCTION("""COMPUTED_VALUE"""),"Boston Prime") -> Boston Prime | F22: =IFERROR(__xludf.DUMMYFUNCTION("""COMPUTED_VALUE"""),2.0) -> 2 | N22: =IFERROR(__xludf.DUMMYFUNCTION("""COMPUTED_VALUE"""),"Rylin Lyemance") -> Rylin Lyemance | Q22: =IFERROR(__xludf.DUMMYFUNCTION("""COMPUTED_VALUE"""),"GA") -> GA | R22: =IFERROR(__xludf.DUMMYFUNCTION("""COMPUTED_VALUE"""),"USA Scout National") -> USA Scout National | S22: =IFERROR(__xludf.DUMMYFUNCTION("""COMPUTED_VALUE"""),1.0) -> 1 | U22: =IFERROR(__xludf.DUMMYFUNCTION("""COMPUTED_VALUE"""),"Braden Little") -> Braden Little | X22: =IFERROR(__xludf.DUMMYFUNCTION("""COMPUTED_VALUE"""),"GA") -> GA | Y22: =IFERROR(__xludf.DUMMYFUNCTION("""COMPUTED_VALUE"""),"USA Scout National") -> USA Scout National | Z22: =IFERROR(__xludf.DUMMYFUNCTION("""COMPUTED_VALUE"""),1.0) -> 1
B23: =IFERROR(__xludf.DUMMYFUNCTION("""COMPUTED_VALUE"""),"Robert Kilpatrick") -> Robert Kilpatrick | D23: =IFERROR(__xludf.DUMMYFUNCTION("""COMPUTED_VALUE"""),"VA") -> VA | E23: =IFERROR(__xludf.DUMMYFUNCTION("""COMPUTED_VALUE"""),"Prime Time Aces") -> Prime Time Aces | F23: =IFERROR(__xludf.DUMMYFUNCTION("""COMPUTED_VALUE"""),2.0) -> 2 | N23: =IFERROR(__xludf.DUMMYFUNCTION("""COMPUTED_VALUE"""),"Jameson Mayfield") -> Jameson Mayfield | Q23: =IFERROR(__xludf.DUMMYFUNCTION("""COMPUTED_VALUE"""),"TX") -> TX | R23: =IFERROR(__xludf.DUMMYFUNCTION("""COMPUTED_VALUE"""),"Dallas Tigers") -> Dallas Tigers | S23: =IFERROR(__xludf.DUMMYFUNCTION("""COMPUTED_VALUE"""),1.0) -> 1 | U23: =IFERROR(__xludf.DUMMYFUNCTION("""COMPUTED_VALUE"""),"Chance Williams") -> Chance Williams | X23: =IFERROR(__xludf.DUMMYFUNCTION("""COMPUTED_VALUE"""),"GA") -> GA | Y23: =IFERROR(__xludf.DUMMYFUNCTION("""COMPUTED_VALUE"""),"USA Scout National") -> USA Scout National | Z23: =IFERROR(__xludf.DUMMYFUNCTION("""COMPUTED_VALUE"""),1.0) -> 1
B24: =IFERROR(__xludf.DUMMYFUNCTION("""COMPUTED_VALUE"""),"Wyatt Libbert") -> Wyatt Libbert | D24: =IFERROR(__xludf.DUMMYFUNCTION("""COMPUTED_VALUE"""),"MO") -> MO | E24: =IFERROR(__xludf.DUMMYFUNCTION("""COMPUTED_VALUE"""),"Royals Scout Team ") -> Royals Scout Team | F24: =IFERROR(__xludf.DUMMYFUNCTION("""COMPUTED_VALUE"""),2.0) -> 2 | N24: =IFERROR(__xludf.DUMMYFUNCTION("""COMPUTED_VALUE"""),"Cole Schott") -> Cole Schott | Q24: =IFERROR(__xludf.DUMMYFUNCTION("""COMPUTED_VALUE"""),"TX") -> TX | R24: =IFERROR(__xludf.DUMMYFUNCTION("""COMPUTED_VALUE"""),"Dallas Tigers") -> Dallas Tigers | S24: =IFERROR(__xludf.DUMMYFUNCTION("""COMPUTED_VALUE"""),1.0) -> 1 | U24: =IFERROR(__xludf.DUMMYFUNCTION("""COMPUTED_VALUE"""),"Makayle Moon") -> Makayle Moon | X24: =IFERROR(__xludf.DUMMYFUNCTION("""COMPUTED_VALUE"""),"SC") -> SC | Y24: =IFERROR(__xludf.DUMMYFUNCTION("""COMPUTED_VALUE"""),"USA Scout National") -> USA Scout National | Z24: =IFERROR(__xludf.DUMMYFUNCTION("""COMPUTED_VALUE"""),2.0) -> 2
B25: =IFERROR(__xludf.DUMMYFUNCTION("""COMPUTED_VALUE"""),"Hayden Moore") -> Hayden Moore | D25: =IFERROR(__xludf.DUMMYFUNCTION("""COMPUTED_VALUE"""),"NC") -> NC | E25: =IFERROR(__xludf.DUMMYFUNCTION("""COMPUTED_VALUE"""),"SCP") -> SCP | F25: =IFERROR(__xludf.DUMMYFUNCTION("""COMPUTED_VALUE"""),2.0) -> 2 | N25: =IFERROR(__xludf.DUMMYFUNCTION("""COMPUTED_VALUE"""),"Connor Jennings") -> Connor Jennings | Q25: =IFERROR(__xludf.DUMMYFUNCTION("""COMPUTED_VALUE"""),"TX") -> TX | R25: =IFERROR(__xludf.DUMMYFUNCTION("""COMPUTED_VALUE"""),"Dallas Tigers") -> Dallas Tigers | S25: =IFERROR(__xludf.DUMMYFUNCTION("""COMPUTED_VALUE"""),2.0) -> 2 | U25: =IFERROR(__xludf.DUMMYFUNCTION("""COMPUTED_VALUE"""),"Reid Williams") -> Reid Williams | X25: =IFERROR(__xludf.DUMMYFUNCTION("""COMPUTED_VALUE"""),"TX") -> TX | Y25: =IFERROR(__xludf.DUMMYFUNCTION("""COMPUTED_VALUE"""),"Dallas Tigers") -> Dallas Tigers | Z25: =IFERROR(__xludf.DUMMYFUNCTION("""COMPUTED_VALUE"""),1.0) -> 1
B26: =IFERROR(__xludf.DUMMYFUNCTION("""COMPUTED_VALUE"""),"Winston Patterson") -> Winston Patterson | D26: =IFERROR(__xludf.DUMMYFUNCTION("""COMPUTED_VALUE"""),"CO") -> CO | E26: =IFERROR(__xludf.DUMMYFUNCTION("""COMPUTED_VALUE"""),"Franklin Scout Team") -> Franklin Scout Team | F26: =IFERROR(__xludf.DUMMYFUNCTION("""COMPUTED_VALUE"""),2.0) -> 2 | N26: =IFERROR(__xludf.DUMMYFUNCTION("""COMPUTED_VALUE"""),"Hudson Hardesty") -> Hudson Hardesty | Q26: =IFERROR(__xludf.DUMMYFUNCTION("""COMPUTED_VALUE"""),"MO") -> MO | R26: =IFERROR(__xludf.DUMMYFUNCTION("""COMPUTED_VALUE"""),"Royals Scout Team ") -> Royals Scout Team | S26: =IFERROR(__xludf.DUMMYFUNCTION("""COMPUTED_VALUE"""),2.0) -> 2 | U26: =IFERROR(__xludf.DUMMYFUNCTION("""COMPUTED_VALUE"""),"Carson Roy") -> Carson Roy | X26: =IFERROR(__xludf.DUMMYFUNCTION("""COMPUTED_VALUE"""),"TX") -> TX | Y26: =IFERROR(__xludf.DUMMYFUNCTION("""COMPUTED_VALUE"""),"Dallas Tigers") -> Dallas Tigers | Z26: =IFERROR(__xludf.DUMMYFUNCTION("""COMPUTED_VALUE"""),1.0) -> 1
B27: =IFERROR(__xludf.DUMMYFUNCTION("""COMPUTED_VALUE"""),"Nolan Plourde") -> Nolan Plourde | D27: =IFERROR(__xludf.DUMMYFUNCTION("""COMPUTED_VALUE"""),"CT") -> CT | F27: =IFERROR(__xludf.DUMMYFUNCTION("""COMPUTED_VALUE"""),2.0) -> 2 | N27: =IFERROR(__xludf.DUMMYFUNCTION("""COMPUTED_VALUE"""),"Mason Borders") -> Mason Borders | Q27: =IFERROR(__xludf.DUMMYFUNCTION("""COMPUTED_VALUE"""),"TN") -> TN | R27: =IFERROR(__xludf.DUMMYFUNCTION("""COMPUTED_VALUE"""),"Rawlings SE MAD Mavericks") -> Rawlings SE MAD Mavericks | S27: =IFERROR(__xludf.DUMMYFUNCTION("""COMPUTED_VALUE"""),2.0) -> 2 | U27: =IFERROR(__xludf.DUMMYFUNCTION("""COMPUTED_VALUE"""),"Owen Lester") -> Owen Lester | X27: =IFERROR(__xludf.DUMMYFUNCTION("""COMPUTED_VALUE"""),"KS") -> KS | Y27: =IFERROR(__xludf.DUMMYFUNCTION("""COMPUTED_VALUE"""),"Royals Scout Team ") -> Royals Scout Team | Z27: =IFERROR(__xludf.DUMMYFUNCTION("""COMPUTED_VALUE"""),1.0) -> 1
B28: =IFERROR(__xludf.DUMMYFUNCTION("""COMPUTED_VALUE"""),"Luke Rafferty") -> Luke Rafferty | D28: =IFERROR(__xludf.DUMMYFUNCTION("""COMPUTED_VALUE"""),"TX") -> TX | E28: =IFERROR(__xludf.DUMMYFUNCTION("""COMPUTED_VALUE"""),"Boston Prime") -> Boston Prime | F28: =IFERROR(__xludf.DUMMYFUNCTION("""COMPUTED_VALUE"""),2.0) -> 2 | N28: =IFERROR(__xludf.DUMMYFUNCTION("""COMPUTED_VALUE"""),"Ty Lange") -> Ty Lange | Q28: =IFERROR(__xludf.DUMMYFUNCTION("""COMPUTED_VALUE"""),"MO") -> MO | R28: =IFERROR(__xludf.DUMMYFUNCTION("""COMPUTED_VALUE"""),"Team KC 2027") -> Team KC 2027 | S28: =IFERROR(__xludf.DUMMYFUNCTION("""COMPUTED_VALUE"""),2.0) -> 2 | U28: =IFERROR(__xludf.DUMMYFUNCTION("""COMPUTED_VALUE"""),"Carson Reffel") -> Carson Reffel | X28: =IFERROR(__xludf.DUMMYFUNCTION("""COMPUTED_VALUE"""),"CO") -> CO | Y28: =IFERROR(__xludf.DUMMYFUNCTION("""COMPUTED_VALUE"""),"Slammers") -> Slammers | Z28: =IFERROR(__xludf.DUMMYFUNCTION("""COMPUTED_VALUE"""),2.0) -> 2
B29: =IFERROR(__xludf.DUMMYFUNCTION("""COMPUTED_VALUE"""),"Braden Richardson") -> Braden Richardson | D29: =IFERROR(__xludf.DUMMYFUNCTION("""COMPUTED_VALUE"""),"SC") -> SC | E29: =IFERROR(__xludf.DUMMYFUNCTION("""COMPUTED_VALUE"""),"CBA Orioles") -> CBA Orioles | F29: =IFERROR(__xludf.DUMMYFUNCTION("""COMPUTED_VALUE"""),2.0) -> 2 | N29: =IFERROR(__xludf.DUMMYFUNCTION("""COMPUTED_VALUE"""),"Ryan Kume") -> Ryan Kume | Q29: =IFERROR(__xludf.DUMMYFUNCTION("""COMPUTED_VALUE"""),"TX") -> TX | R29: =IFERROR(__xludf.DUMMYFUNCTION("""COMPUTED_VALUE"""),"Lonestar Baseball Club") -> Lonestar Baseball Club | S29: =IFERROR(__xludf.DUMMYFUNCTION("""COMPUTED_VALUE"""),2.0) -> 2 | U29: =IFERROR(__xludf.DUMMYFUNCTION("""COMPUTED_VALUE"""),"Ayden Collier") -> Ayden Collier | X29: =IFERROR(__xludf.DUMMYFUNCTION("""COMPUTED_VALUE"""),"TX") -> TX | Y29: =IFERROR(__xludf.DUMMYFUNCTION("""COMPUTED_VALUE"""),"Wildcatters") -> Wildcatters | Z29: =IFERROR(__xludf.DUMMYFUNCTION("""COMPUTED_VALUE"""),1.0) -> 1
B30: =IFERROR(__xludf.DUMMYFUNCTION("""COMPUTED_VALUE"""),"Tyler Roach") -> Tyler Roach | D30: =IFERROR(__xludf.DUMMYFUNCTION("""COMPUTED_VALUE"""),"LA") -> LA | F30: =IFERROR(__xludf.DUMMYFUNCTION("""COMPUTED_VALUE"""),2.0) -> 2 | N30: =IFERROR(__xludf.DUMMYFUNCTION("""COMPUTED_VALUE"""),"Finn Torvik") -> Finn Torvik | Q30: =IFERROR(__xludf.DUMMYFUNCTION("""COMPUTED_VALUE"""),"CO") -> CO | R30: =IFERROR(__xludf.DUMMYFUNCTION("""COMPUTED_VALUE"""),"Slammers") -> Slammers | S30: =IFERROR(__xludf.DUMMYFUNCTION("""COMPUTED_VALUE"""),2.0) -> 2 | U30: =IFERROR(__xludf.DUMMYFUNCTION("""COMPUTED_VALUE"""),"Miles Norman") -> Miles Norman | X30: =IFERROR(__xludf.DUMMYFUNCTION("""COMPUTED_VALUE"""),"GA") -> GA | Y30: =IFERROR(__xludf.DUMMYFUNCTION("""COMPUTED_VALUE"""),"5 Star Mafia") -> 5 Star Mafia | Z30: =IFERROR(__xludf.DUMMYFUNCTION("""COMPUTED_VALUE"""),1.0) -> 1
B31: =IFERROR(__xludf.DUMMYFUNCTION("""COMPUTED_VALUE"""),"Sully Townley") -> Sully Townley | D31: =IFERROR(__xludf.DUMMYFUNCTION("""COMPUTED_VALUE"""),"SC") -> SC | E31: =IFERROR(__xludf.DUMMYFUNCTION("""COMPUTED_VALUE"""),"Palmetto Blacksmiths SC 2027") -> Palmetto Blacksmiths SC 2027 | F31: =IFERROR(__xludf.DUMMYFUNCTION("""COMPUTED_VALUE"""),2.0) -> 2 | N31: =IFERROR(__xludf.DUMMYFUNCTION("""COMPUTED_VALUE"""),"Koa Peters") -> Koa Peters | Q31: =IFERROR(__xludf.DUMMYFUNCTION("""COMPUTED_VALUE"""),"GA") -> GA | S31: =IFERROR(__xludf.DUMMYFUNCTION("""COMPUTED_VALUE"""),2.0) -> 2 | U31: =IFERROR(__xludf.DUMMYFUNCTION("""COMPUTED_VALUE"""),"Logan Grubbs") -> Logan Grubbs | X31: =IFERROR(__xludf.DUMMYFUNCTION("""COMPUTED_VALUE"""),"NV") -> NV | Y31: =IFERROR(__xludf.DUMMYFUNCTION("""COMPUTED_VALUE"""),"5 Star") -> 5 Star | Z31: =IFERROR(__xludf.DUMMYFUNCTION("""COMPUTED_VALUE"""),2.0) -> 2
B32: =IFERROR(__xludf.DUMMYFUNCTION("""COMPUTED_VALUE"""),"Cooper Mengel") -> Cooper Mengel | D32: =IFERROR(__xludf.DUMMYFUNCTION("""COMPUTED_VALUE"""),"MD") -> MD | E32: =IFERROR(__xludf.DUMMYFUNCTION("""COMPUTED_VALUE"""),"DCP") -> DCP | F32: =IFERROR(__xludf.DUMMYFUNCTION("""COMPUTED_VALUE"""),2.0) -> 2
B33: =IFERROR(__xludf.DUMMYFUNCTION("""COMPUTED_VALUE"""),"Ethan Noyes") -> Ethan Noyes | D33: =IFERROR(__xludf.DUMMYFUNCTION("""COMPUTED_VALUE"""),"MD") -> MD | F33: =IFERROR(__xludf.DUMMYFUNCTION("""COMPUTED_VALUE"""),2.0) -> 2
B34: =IFERROR(__xludf.DUMMYFUNCTION("""COMPUTED_VALUE"""),"Kason Webb") -> Kason Webb | D34: =IFERROR(__xludf.DUMMYFUNCTION("""COMPUTED_VALUE"""),"AZ") -> AZ | E34: =IFERROR(__xludf.DUMMYFUNCTION("""COMPUTED_VALUE"""),"California PFA") -> California PFA | F34: =IFERROR(__xludf.DUMMYFUNCTION("""COMPUTED_VALUE"""),2.0) -> 2
B35: =IFERROR(__xludf.DUMMYFUNCTION("""COMPUTED_VALUE"""),"Jack Burke") -> Jack Burke | D35: =IFERROR(__xludf.DUMMYFUNCTION("""COMPUTED_VALUE"""),"GA") -> GA | E35: =IFERROR(__xludf.DUMMYFUNCTION("""COMPUTED_VALUE"""),"USA Scout National") -> USA Scout National | F35: =IFERROR(__xludf.DUMMYFUNCTION("""COMPUTED_VALUE"""),2.0) -> 2
B36: =IFERROR(__xludf.DUMMYFUNCTION("""COMPUTED_VALUE"""),"Jackson Barker") -> Jackson Barker | D36: =IFERROR(__xludf.DUMMYFUNCTION("""COMPUTED_VALUE"""),"KS") -> KS | E36: =IFERROR(__xludf.DUMMYFUNCTION("""COMPUTED_VALUE"""),"Building Champions") -> Building Champions | F36: =IFERROR(__xludf.DUMMYFUNCTION("""COMPUTED_VALUE"""),2.0) -> 2
B37: =IFERROR(__xludf.DUMMYFUNCTION("""COMPUTED_VALUE"""),"Peyton Landers") -> Peyton Landers | D37: =IFERROR(__xludf.DUMMYFUNCTION("""COMPUTED_VALUE"""),"FL") -> FL | E37: =IFERROR(__xludf.DUMMYFUNCTION("""COMPUTED_VALUE"""),"Lousiville Baseball Club National") -> Lousiville Baseball Club National | F37: =IFERROR(__xludf.DUMMYFUNCTION("""COMPUTED_VALUE"""),2.0) -> 2
B38: =IFERROR(__xludf.DUMMYFUNCTION("""COMPUTED_VALUE"""),"Cooper Daniel") -> Cooper Daniel | D38: =IFERROR(__xludf.DUMMYFUNCTION("""COMPUTED_VALUE"""),"TN") -> TN | E38: =IFERROR(__xludf.DUMMYFUNCTION("""COMPUTED_VALUE"""),"FTB Tennessee") -> FTB Tennessee | F38: =IFERROR(__xludf.DUMMYFUNCTION("""COMPUTED_VALUE"""),2.0) -> 2

Sheet Event Lists
A1: PG Ft Myers | D1: PBR Grand Park Fall Championship | G1: PBR 17U '25 | I1: @ | J1: Mattingly | M1: WWBA 17U '25 | P1: prospect SELECT palm beach classic | S1: Beast of East 6/5-6/9 | V1: AZ Fall Nat. Champ. 26s | Y1: AZ Senior Fall Classic | AB1: PBR Grand Park 9/13-9/15 | AE1: AZ Junior Fall Classic | AH1: PBR 17u Lakepoint | AK1: Mattingly | AN1: Hoover | AQ1: NPI | AS1: 17U WWBA | AV1: Super 17 | AY1: Boston | BB1: Cincinatti | BE1: Prospect Select 17U Philly - 9/15-9/17 | BH1: AZ Senior Fall Classic - 9/28-10/1
A2: TEAM | B2: PLAYER | D2: TEAM | E2: PLAYER | G2: TEAM | H2: PLAYER | J2: TEAM | K2: PLAYER | M2: TEAM | N2: PLAYER | P2: TEAM | Q2: PLAYER | S2: TEAM | T2: PLAYER | V2: TEAM | W2: PLAYER | Y2: TEAM | Z2: PLAYER | AB2: TEAM | AC2: PLAYER | AE2: TEAM | AF2: PLAYER | AH2: TEAM | AI2: PLAYER | AK2: TEAM | AL2: PLAYER | AN2: TEAM | AO2: PLAYER | AQ2: TEAM | AS2: TEAM | AT2: PLAYER | AV2: TEAM | AW2: PLAYER | AY2: TEAM | AZ2: PLAYER | BB2: TEAM | BC2: PLAYER | BE2: TEAM | BF2: PLAYER | BH2: TEAM | BI2: PLAYER
A3: East coast sox | B3: Dekhota Jones | G3: 643 DP | H3: Roshan Bullard (4) - '26 RHP | J3: 5 Star Ark Desola | K3: Will Stewart - INF | M3: 5 Star Great Lakes Midwest | N3: Lucas Batrez - RHP(CA) | P3: FL Dodger scout | Q3: (SAT) Mason O'Neil LHP 84-86 | S3: CBU 26 Scout Stofsky | T3: Tyler Reeder-RHP | V3: Marucci Stng | W3: Eli McBryde - C-jok/spring follow | Y3: CCB Scout Team | Z3: Evan Bradshaw - SS--ok/maybe see again | AB3: Sparks | AC3: Swanson C (FG) #30 | AE3: Trosky | AF3: Henry Verhamme ss | AH3: Cincy flames | AI3: Colin Milligan OF 6.7 run 34ACT | AL3: David Litle SS TX | AN3: 5 Star Mafia Gold | AO3: Caleb Allen LHP GA | AQ3: Carson Zagryn | AT3: Nick Manning RHP FL (Sunday June 23rd 1:40pm Starr's Mill) | AV3: 9ers | AW3: Owen otoole wed 8am | AZ3: Felix Stork LHP CA (May be coming to camp) | BC3: Noah Stopnick RHP CO
B4: Dominic Naylor | D4: Gamers | E4: Joseph Gonzalez INF/OF '26 | G4: Bo Jackson Elite | H4: Logan Minamyer (3) - '26 RHP | J4: ABA 26 Navy | M4: Rawlings SE Mad mavericks | N4: Caleb Lear - RHP(TN) | P4: coach Jon Shiver | Q4: (SAT) Colvin Proto RHP 3pitch | T4: Jude McDonald-RHP | W4: Kyle Miller - 1B | Y4: *Marucci Sting/2026 event | Z4: Kelton Floan - SS (26)/Follow | AC4: Kinnane RHP #43 | AE4: Coach Brett Harper | AF4: Brent Sollars of | AI4: Ayden Wall C | AK4: Trosky Tx Ina | AL4: Grant Winkle LHP TX | AN4: Barwis Dragons | AO4: Daniel Norbeck RHP FL | AQ4: Mason Gazaway? OF | AS4: fl burn | AT4: Owen Phypers RHP FL (Saturday east Cobb field 1 3pm) | AW4: Justin MacCormick Tues
B5: Alex Hernandez Fri 245 | E5: Andrew Reed RHP '27 | G5: Canes South | H5: Luke Young (4) - '26 C | J5: Stix Scout | K5: Kolton Christie - C | M5: Royals Scout | N5: Grayton Gross - LHP(KS) | Q5: Chase Staley CINF/RHP90 | S5: Rough Riders National | T5: Henry Verhamme-ss | W5: Hunter Walker - 3B/2b | Z5: Cole McCombs - RHP -just ok | AB5: Canes National | AC5: Denny OF #65 runs | AF5: Cory Dean Carver
G6: Dirtbags | H6: Colton Hicks (3) - '26 CINF | K6: Kyle Tanksley - SS | M6: 5 Star Carolina | N6: Ben Dudash - C | Q6: Tim Pellicer C | T6: Preston Burke-RHP | W6: Parker Rahn - 3B/not a fit/not int | Z6: Blake Moore - LHP //Saturday due to football | AC6: DeHart OF (FG) #24
A7: 5 Star performance | B7: Aidan Avalos SS | D7: White Sox | E7: Keith Mitchell OF 27 | G7: Dirtbags | H7: Gordon Cozad (4) - '26 MINF | K7: Nicholas Smith - SS | N7: Trevor Friend - RHP | P7: Ostingers | Q7: Carter Sprague OF 6.6 CF 196FL | T7: Eli McBryde-C | V7: Slammers Anderson | W7: Britain Fox - OF | Z7: Toby Trotter - LHP// Possible academic game | AC7: Watson C #49 | AI7: Drew Kindlon RHP FRI 11:30 CASS | AL7: Donovan Abel C
E8: Charlie Herr RHP 27. 9/13 3pm | G8: FL Pokers | H8: Reid Dadic (2) - '26 RHP | K8: Rylan Alaniz - SS | M8: Keystone Bombers | N8: Braydon Bown - RHP | Q8: Carson Binder C pwr 169FL | S8: Slammers Anderson | T8: Reached out | W8: Tommy Humphrey - OF | Y8: Admirals | Z8: Jake Fletcher - C-jok/not enough | AC8: Marcum RHP #48 | AE8: BBNW Green | AF8: No arms | AH8: Dulins Dodgers | AI8: Hunter Vincent LHP TH 1:40 GH | AK8: Scorpions Black | AL8: Gehrig Heckathorn OF TX | AO8: Jake Finnegan SS FL | AQ8: Jackson Rose LHP | AT8: Trey Greenwell OF AL | AW8: Finn Hains/Dobis Tues 215 field 5
A9: Ostingers | B9: Conor Gavigan OF military interest | E9: Ben Schaeffer OF 27 | G9: FTB Phillies Scout | H9: Michael Chin (4) - '26 C | K9: Nawrocki - LHP | N9: Ty Callahan - RHP | Q9: Alec Chin OF hit n/aFL | S9: CBA 26 National | T9: Dru Gaddy '27 LHP (interest) | W9: Yale Johnson - C | Z9: Caden Whitten - SS-2026 follow | AB9: GRB Rays 26 | AC9: Hietpas RHP (FG) #24 | AF9: Ethan Swallom C | AH9: VBA (AL) | AI9: Luke Holbrook RHP FRI 7pm start Cass HS | AN9: VBA 17U Black | AO9: Luke Holbrook RHP AL | AQ9: Nathan Shaffer C | AS9: troskey national | AT9: Carter Brown 1B/RHP AZ | AV9: ECNE | AW9: Tony Silva RHP Tues 430 field 5
G10: Indiana Bulls | H10: Eli Hampton (4) - '26 C | K10: Josh Horvath - RHP | M10: Wow Factor | N10: EJ Allen - MINF | Q10: Reid Freda OF hit/run (AF) n/aFL | S10: Soldier Spects | T10: Tanner Evans ss | V10: Trosky AZ Regional | W10: Cory Dean Carver - SS | Y10: Dallas Patriots | Z10: George Willis - C | AC10: Hawley OF (FG) #27 | AE10: BBNW Black | AF10: Jacob Rolling SS? | AH10: Richmond Braves platinum prospect | AI10: Brad Marks RHP WED F13 3pm | AK10: Stix 2025 Scout | AL10: Bryce Wells C TX | AO10: Trey Greenwell OF AL | AQ10: Bennett Wright? (3.5) C | AS10: 643dp | AT10: Jackson rose LHP GA | AW10: Harssh Ramayanm Venkkat RHP/SS NJ
A11: Team Elite / AZ scout | B11: Andrew Brech RHP | D11: Slammers Fiscus 27 | E11: Tyler Reeves OF 27 | G11: Legacy Baseball | H11: Peter Jackson (4) - '26 RHP | J11: Wildcatters | K11: Lawson Behan - SS | N11: Jet McNelis - OF | Q11: Ocean Cozart 2B/3B hit n/aFL | W11: Brent Sollars - OF-follow | Y11: Southern Nevada | Z11: Niko Carpenter - RHP-2026 follow | AC11: Brenner C (FG) #35 | AF11: Caleb Zawadzki pitching Sat 10am Mariner 4 (texted) | AH11: Wow factor national scout | AI11: Connor Cavo RHP SAT 3pm F13 | AK11: 5 Star Performance National | AL11: Aiden Poirier SS | AN11: Marucci Elite Texas - Dunn | AO11: Hayden Wiley SS TX | AQ11: James Pitts? (3.1) | AS11: east coast sox | AT11: Brody Winemiller 1B TN | AV11: Show Baseball | AW11: Henry Hebert--Thurs 215 field 3
A12: he doesn't know grades | B12: Kai Gambill LHP | E12: Jayden Witkamp RHP 27 6'7 | G12: NEB | H12: Hawk Stickney (2) - '26 RHP | K12: Ty Higginbotham - LHP | M12: Sandlot | N12: Caden Atkinson - RHP | P12: Scorpions scout | Q12: Mikey Ramsey RHP | W12: Henry Verhamme - P/SS-follow | Y12: CBA Marucci | Z12: Trenton Uyeda - SS-jok/not enough | AC12: Alonso SS (FG) #6 | AF12: Silas Meuli OF LHH | AH12: Bell ringers ? | AI12: Kevin Ruff LHP TH 2pm Allatoona | AK12: Dulins Dodgers Prime | AL12: Will McKinzie SS | AO12: Ty Thames INF TX
B13: Nick Santobello RHP | G13: NEB | H13: Eric Willi (2) - '26 C | J13: Marruci elite Holle | K13: Alex mayon - SS | M13: South Charlotte | N13: Heath Kilingsmen - RHP | P13: coach Goodrich | Q13: Drew Boivin RHP | Z13: RHP Ryan Popkins (Fri 1030am/Rangers 3)
B14: Sam GodBout SS | D14: SPARKS | E14: None | G14: Ostingers | H14: Carson Binder (3) - '26 C | K14: Grant Shepherd - LHP | M14: Rough Riders | N14: Henry Verhamme - SS | Q14: Alex Davis CF/LF speed | V14: Marucci Ath Elite | W14: Daniel Martinez - C | Y14: TB SoCal | Z14: Pierson Howe - YES/visit/offer | AB14: GBR STIKS Black | AC14: Kawczynski SS #53 | AE14: GBG Navy American | AF14: Chase Stewart C | AH14: Wow factor scout | AI14: Phoenix Williams OF | AL14: Hunter Vincent LHP | AN14: Original FL Pokers | AO14: Eddie Marshall C | AS14: Braves Scout | AT14: Austin Treadwell RHP GA - | AV14: Baseball U | AW14: Jack Murray
G15: Ostingers | H15: Ocean Cozart (3) - '26 MINF | K15: Jack herncall - lhp | N15: Ronan O'Brien - RHP | Q15: Jack Fults RHP | W15: Thomas Pascanu - 1B/LHP/contact | Y15: Stacked | Z15: Issac Aguiire - RHP | AF15: Lucas blackwood ss
D16: Team Indiana | E16: Cal Carmichael RHP 9/13 5:45pm | G16: Ostingers | H16: Andrew Steele Thalleen (3) - '26 RHP | K16: Seth martin- RHP | M16: Power 26 Marucci | N16: Oliver Swartz - LHP | Q16: Jake Helms RHP (interest) | Z16: SS Tyler Smith-ok/not enough
E17: Peter Ward RHP 9/13 5:45pm relief | G17: Ostingers | H17: Drew Cothren (4) - '26 COF | J17: Lonestar National | K17: Jack kieke - ss | M17: CBU Stofsky | N17: Tyler Reeder - RHP | Q17: Tripp Rosenberger RHP | Z17: RHP Nick Murray
G18: Stix | H18: Rylan Alaniz (1) - '26 SS | K18: Bobby wilkinson - ss | N18: Max McDougal - RHP | Q18: Derek Rubin UTL 6.7 run | Y18: SC Birds | Z18: SS Jagger Snitko/see again if possible | AF18: Max weddle emailed
D19: Iowa sticks 27 | E19: Brady Smith RHP 27 9/13 12:30pm Kokomo | G19: Stix | H19: Preston Lewis (1) - '26 C | K19: Jason mazoch - rhp | M19: Legacy | N19: Brise Boop - ss | Q19: Cooper West LHP | Y19: 5 Star | Z19: RHP Jacob Janeta (Th/4pm) Royals 5 | AF19: Kanon schiller emailed
G20: Team Elite | H20: Jack Ryan (1) - '26 RHP | J20: Dulins Dodgers Goodwin | K20: Brett Hill LHP | M20: Phillies American | N20: Landon McMahon - OF | Q20: Chase Andress LHP (interest) | Z20: LHP Matthew Garrison (Sun | AF20: Jaden Taylor emailed
G21: Team Elite | H21: Ronan Owens (4) - '26 RHP | K21: brenden selph rhp | N21: Leo Anterpen - LHP | Z21: SS Max Biehl/just ok good little player. NAG | AF21: Dylan Johnson emailed
G22: Team Elite | H22: Nick Linares (4) - '26 RHP | K22: shane parker inf | M22: REB Sports Aacdemy | N22: Lukas Botkin - LHP | P22: Original FL Pokers | Q22: Julian Diaz RHP | Y22: Swarm Red Elite | Z22: LHP Brooken Stevens-interesting | AC22: Ruby SS (FG) #5 | AE22: Swarm Red Elite | AF22: Zandre Bratspis SS | AH22: Atlanta Braves Scout | AI22: Sinjon Lash WED 3pm F10 | AK22: Houston Kyle Chapman | AL22: George Willis C | AN22: Wow Factor Northeast | AO22: Harsh Venkatt SS | AQ22: Sinjon Lash | AV22: ECNE | AW22: Jett Jones
G23: Top Tier | H23: Eric McAtee (3) - '26 RHP | J23: DFW twins scout | K23: will cayce ss | M23: Charlotte megastars | N23: Caden Tarr - SS | P23: coach Fitz | Q23: Reggie Rodriguez 1B LHH | Z23: LHP Michael Horne-contact | AC23: Grulkowski RHP #9 | AH23: PrimeTime Aces-Skaggs | AI23: Kailen Hackman RHP FRI 3pm LP | AN23: Wow Factor National | AO23: Brayden Mann C: | AQ23: Josh Taylor? SS | AS23: slammers holzimer | AT23: Sam Harry OF CO | AV23: Team Boston rams | AW23: Chris Klueber wed 1215 field 4
G24: Top Tier | H24: Jack Stefani (4) - '26 RHP | J24: Dallas Tigers ahearne | K24: Broc burns rhp | M24: 5 Star Carolina National | N24: Cooper Summerlin - LHP | Q24: Roman Zavala SS | Z24: RHP JT Price-contact/check int
G25: Top Tier | H25: Caden Schlotterbeck (4) - '26 LHP | M25: Atlanta Blue Jays | N25: Cameron Bergloff - LHP | Q25: Reid Dadic LHH OF/RHP | Y25: Top Level (CO) | Z25: LHP Thomas Novak (Fri 11am/Royals 5)No int | AC25: Angle OF #31 | AE25: Factory 1 Royal | AF25: Trevelyan Podawitz C | AH25: Hounds baseball | AI25: Gino Zagorac RHP FRI 4pm GH | AK25: C2 Baseball TX Scout | AL25: Kaenen Kiefer SS | AN25: USG/Elev8 | AO25: Connor Cavo RHP | AQ25: Tyler Fallmann? RHP | AS25: slammers holzimer | AT25: Spike Magill C CO
G26: Knights Knation | J26: Dallas patriots 17u | K26: Cory Carver | Q26: both Catchers | AC26: Semnelmann LHP (FG) #240 Nat | AE26: ABA Navy | AF26: Dean Ellison LHP 745am Saturday maryvale 4 | AH26: Cadets | AI26: Ryan Nelson OF TH 2pm Allatoona | AK26: TBT Texas National | AL26: Tate Elliott C | AN26: Team Elite Scout | AO26: Grayson Stroumpis??? | AQ26: Brayden Antonelli? RHP | AS26: Wow Factor Nation 17U | AT26: Brayden Mann C VA
G27: 5 Star Virginia | J27: Canes sw national | M27: East Coast Sox | N27: Ronin McCraw - ss | Q27: Cade Raley LHH 2B | Y27: IMG | Z27: RHP Wade Hartrick (Sun 11am/Rangers 4) | AC27: Bitter RHP (FG) #20 | AF27: Jack Byers RHP following Ellison saturday | AK27: Austin Wings | AL27: Matt Pazak C | AN27: Georgia Jckets | AO27: Ben Chatham C | AQ27: Hunter Edwards? C | AS27: Nokona | AT27: Sachin Gopal RHP MA (Sun 1:40 Creekview HS)
G28: Marucci Blackhawks | J28: Austin wings national | K28: nathan taparauskas rhp | M28: Ghost National | N28: Miles Keogh - SS | Z28: RHP Thomas Egbert (Fri/830am/Royals 3) | AB28: Hitters | AC28: Carter RHP (FG) #14 | AF28: Cole Darnell RHP thurs 130pm | AH28: Virginia Cardinals | AI28: See team | AK28: Dallas Tigers Hernandez | AL28: Colton McClure SS | AN28: Soldier Spects | AO28: Jackson Estes LHP | AQ28: Ty Householder? OF | AS28: midland redskins (oh) | AT28: Jax Heid SS TX
G29: Academy Baseball Canada | J29: 5 star national | K29: carter hoffman lhp | N29: dan ditullio - lhp | P29: power baseball victus | Q29: Jacob Calton 3B (interest) | AC29: Humes RHP #48 6'5 | AF29: Kaiden Nerhood OF | AH29: Black Sox (AL) | AI29: FRI 10:20 LP12 Easton Nelms SS | AL29: Landon Ammerman LHP | AN29: USA prime SE | AO29: Trent Wilson C. No good | AQ29: Jarron Swick? OF | AS29: USA Prime American 17U | AT29: Wade Hartrick RHP CO (Sunday 5:20pm Pickens County HS)
G30: AquaSox | K30: troy alexander rhp | M30: LI Body Armor Titans Robles | N30: Vaughan Steinert - OF | P30: power baseball BLUE | Q30: Logan Page RHP 82 | Y30: SoCal Giants | Z30: SS/RHP Thomas Gonzalez/threw well/too small | AB30: IN Bulls Black | AC30: Gilley LHP #37 | AE30: Legacy baseball group #2 | AF30: Drew Kostich INF | AL30: Parker Ivy C (Stats aren't great put him on here since he's been in contact) | AT30: Rilee Hutchinson (saw at NPI took a couple powerful swings but stiff mover. If there to see Wade take a look)
G31: ASBA | J31: Marucci elie veliquette | K31: matt de jager ss | N31: Shane Meehan-C | P31: power baseball Marucci | Q31: Maddox Bultema CF 6.5 | Y31: HitDogs | Z31: RHP Thor Pelczarski | AC31: Francis OF (FG) #156 Nat | AE31: Dulins Dodgers | AF31: Payne Cearnal OF | AH31: Show Baseball | AI31: Ryan Moreschi | AK31: Dallas Patriots 17U | AL31: Clayton Norrell LHP | AT31: Anthony Elezja C (Had phone call video looked good, doesn't sound like he can hit but if he's catching Hartrick take a look)
G32: Athletes Lab | M32: Dirtbags national | N32: Greyson Jones - RHP | Z32: C Cooper Kruk | AF32: cade antosca emailed
G33: Atlanta Blue Jays | N33: Tyler Komorner - RHP
G34: Atlanta Braves Scout | N34: Carosn Moser - RHP | P34: richmond braves platinum | Q34: Chris martinez SS | Z34: LHP Zach Hull (2026/only 3.2 gpa listed) | AC34: Smith SS #57 | AE34: Big Sky Baseball | AF34: Colton Bush RHP (emailed) Fri 830am / Sat 8am | AQ34: Ben Sibert? RHP 4.44 | AS34: Tri State Arsenal Scout | AT34: Jack Pye RHP PA Saturday 1:40 Chestatee HS/Monday 3pm East Cobb
G35: Bell Ringers | N35: Anthony Zezza - LHP | Z35: Rhp Hayden Greene-did not see/no grades
M36: Top Level Baseball | N36: Avery Deustch - OF emailed good stats | P36: EC Astros Navy | Q36: Preston Stout OF LHH | Y36: Badlands Baseball | Z36: SS Josh Avery/awful rec | AC36: Lowrey RHP (FG) #30 | AE36: West coast ghost national | AF36: Noah Gelles OF (emailed) | AK36: Dallas Tigers Cecil | AL36: Reese Ogden C | AT36: Jason Brown IF
M37: Indiana Prospects National | N37: Colton Busch - RHP | Q37: Jayden Whittlesey RHP | Y37: Catalyst Cardinals | Z37: SS Riley Summers-jok
G38: Building Champions | M38: Wildcatters | N38: Lawson Behan - SS | Z38: Lhp Isaac Low-did not see
G39: Cadets | N39: Ty Higginbotham - LHP | P39: GatorBall | Q39: Gabe Garcia SS | Y39: Stacked | Z39: SS Tyler Smith | AB39: PF Flyers | AC39: Schumacher SS (FG) #20 | AF39: Miles Keogh SS | AS39: Sticks | AT39: Bryce Wells C TX
G40: Canes Central | M40: Dallas Patriots | N40: Cory Dean Carver | Q40: Dion Wilburn RHP 6'6 | Z40: Rhp Nick Murray | AC40: Canan RHP (FG) #14 | AE40: CBA summitt 2026 | AF40: Cutter christensen (emailed) | AK40: DFW Twins | AL40: Grady Baetz LHP (Threw Tues) | AT40: Dylan Prince INF FL
G41: Canes KY | M41: Devine | N41: Ethan Curtis - LHP | Q41: Reed Thomas RHP | Y41: Hawaii Elite | Z41: Cade Watson-pitched poorly/cant offer | AC41: Gaerke RHP #42 | AE41: Trinity Baseball | AF41: Noah Darnell LHP (acadmeic tryout/ starting sat game 1) | AK41: Hawaii Elite 2G Toro | AL41: Cade Watson RHP (Threw Tues) | AQ41: No Roster | AS41: .9ers | AT41: Owen OToole RHP NJ
G42: Canes Mid Atlantic | N42: Zach Diaz - SS | Q42: Cohen Lafler RHP 88 | Y42: Norcal | Z42: Beau Blake-follow/good player/pot. visit | AC42: Schmittou SS #46 runs | AF42: chase marlow C | AK42: GPS Legends Puffer | AL42: Xander Covar C | AQ42: No Roster | AS42: Charlotte megastars | AT42: Nick Russo RHP NC (Sun June 23rd 11:20am Sprayberry HS)
N43: Joe Soto - LHP | Q43: maybe a few more | Y43: BPA (Draft Bracket) | Z43: 2027 LHP Logan Schmidt/dude 90-92 | AB43: Louisville Baseball Club Nat | AC43: Ritchie SS (FG) #15 | AF43: Luke blanchard of | AL43: Jonas Anderson LHP (Threw Tues) | AS43: Wow factor Atlantic | AT43: Patrick Walsh 1B
G44: Canes North | M44: ZT Elite Midwest Black | N44: Kye Jacobs - SS | Y44: TB SocCal (Draft Bracket) | Z44: SS Hayden Woodson-good/contact | AC44: Sizemore SS (FG) #21 | AF44: nick gifoli | AK44: C2 Baseball Texas Scout | AL44: Kaenan Kiefer SS | AQ44: No Roster | AS44: Trosky TX - Ina | AT44: Donovan Abel C TX
G45: Canes Palmetto | M45: Homeplate Chilidogs | N45: Khalon Davis - SS | Z45: LHP Brayden Schaff-contact
M46: Team Elite National | N46: Dylan Foltz - SS | P46: Elite squad 17u | Y46: TB SoCal | Z46: SS Hank Hansen | AC46: Lawrence OF #41 runs | AF46: vincent milo sun | AS46: KC royals scout | AT46: Will Howard C TX
G47: Canes Southeast | M47: Stacked America | N47: Trevor Deack ss | Y47: Baseball Northwest | Z47: SS Wyatt Minto/ good player/undersized | AC47: Devine SS (FG) #25 runs | AF47: tyler unter game 2 sat | AQ47: No roster | AT47: Lucas Grant LHP IL ????
G48: Canes Upstate | M48: 9ers | N48: Ryan McCabe -C | P48: citius velocracy | Q48: Cruz Banuelas C | Y48: JGB Rockstars | Z48: 2026 RHP Jose Borregos-follow | AC48: Grundy 3B (FG) #8 | AE48: TB Socal | AF48: andre owens inf | AQ48: Jackson Freeman? C | AS48: Sandlot | AT48: Cameron Fausset RHP CA (Area Code may be there late)
G49: Cangelosi Sparks | M49: Marucci Elite Peoria | N49: Cameron Davidson - SS | Y49: Marucci Athletics | Z49: 1B Bode Acton-not enough | AC49: Hornback OF (FG) #40 | AQ49: Landon Kemp? SS | AT49: Gabe Winans RHP TX
G50: Carolina Prime | M50: Elite National | N50: Sergio Hernandez- SS | Y50: Legacy Baseball | Z50: IF Brooks Fischer: not enough | AC50: Vander Plaats RHP (FG) #27 | AQ50: Brody Winemiller? | AS50: knights knation National | AT50: Rowen Bergereon INF LA
G51: CBA | Y51: SC Bombers | Z51: SS/3b Michale Velardez-contact | AB51: Top Tier American | AC51: Chin LHP #39 | AQ51: Micah Taguiam? C | AS51: east coast sox | AT51: Micah Taguiam C CA
G52: CBC Marucci | Y52: SC Giants | Z52: LHP Nathan Pimentel-contact (no grades) | AC52: Matise RHP #38 | AQ52: Halton Donnelly? OF | AS52: Trosky Brewers | AT52: Hunter Manning RHP CA (Throwing Saturday 22nd/time on sheet)
G53: Coastal Stars | Z53: LHP Ty Hanley-contact | AB53: Top Tier IN | AC53: Jackson 3B (FG) #29 | AE53: Marruccci sting | AF53: Kyle miller | AQ53: No Roster | AS53: Selects Baseball National | AT53: Teddy Juaire RHP MN (Wednesday 8am Hank Aaron field at Gresham park. Starting)
G54: D Las Vegas | Z54: LHP Enoch Yi | AC54: Mcatee RHP #53 6'4 | AF54: hunter walker | AQ54: No Roster | AT54: Caleb Hill SS TX (16U)
G55: DCP | Z55: SS David Aguirre-contact? | AE55: TPR Baseball | AF55: Check pitching rotations each day | AQ55: Noah Blackburn? C 4.3/30 | AS55: NEB | AT55: Liam Childs RHP MA --tbd
G56: Devine Baseball | Y56: SD Show | Z56: RHP Gavin Kramer-not enough | AE56: ca dukes baseball | AF56: carson baker | AQ56: Chase Rafferty? LHP 3.8 | AT56: Alec Murray RHP CA- Sat June 22 1:40 pm Centennial HS
G57: DFW TWINS | Z57: SS Noah Solano-not enough | AE57: gbg ie | AF57: bobby anderson emailed | AT57: Bourke Reid NJ RHP
G58: Dirtbags National | H58: Anthony Zezza LHP(Relief16th & 20th) | AQ58: Bray Goode? 4.0 LHP | AS58: NOVA Premier | AT58: Luke Forde IF
AQ59: William Andre? RHP 4.1 | AS59: Upstate Mavz | AT59: Aiden Brusman C VA--only if convenient
G60: Dulin Dodgers | AE60: academic tryout | AF60: tommy moro RHP | AQ60: Colby Durden? RHP | AT60: Mac Dawsey C SC--only
G61: East Coast Lumberjacks | AQ61: No roster | AS61: Canes MidAtlantic Scout Gold | AT61: Aiden Syzdlik IF/OF
G62: East Coast Sox | AQ62: Check w/ Christman | AS62: Wow Factor | AT62: Brendan Lanigan RHP GA--June 24 (pen)
G63: East Cobb Astros | AS63: MPH 101 Dragum | AT63: Brian Archer C VA
G64: East Cobb Patriots | AQ64: Seth Pettett C 4.3 | AS64: Mid Atl Red Sox | AT64: Mark Windle SS MD
G65: East Cobb Yankees | AQ65: Ben Chatham C | AS65: Mid Atl Red Sox | AT65: Cam Vachon C MD--will see when we see Windle
G66: EBC | AQ66: Jackson Stanley SS/OF | AS66: Richmond Braves Platinum | AT66: Benjy Cardone C VA-- up to Pavs if we want to see again
G67: Edge Baseball | AQ67: Ean Marria 3B/RHP | AS67: Atlanta Blue Jays | AT67: Vince Menard RHP CA
G68: Elite Baseball Training | AS68: Angels Scout (Lakeland FL) | AT68: Matthew Hall OF (Prep Candidate)
G69: Excel Blue Wave National | H69: Jack Pritchett RHP (Need date) | AQ69: Drew Abney C | AS69: Richmond Braves 2025 Platinum | AT69: Brenden Moehnke RHP--Tuesday Start
G70: Factory SELECT | AQ70: Charles Chappelle OF
G71: Fieldhouse Pirates | AQ71: David Jackson LHP | AS71: Canes VA | AT71: Ryan Steeper RHP (Sat June 22/2:45pm at Brook Run)
AQ72: Knox Bingham INF | AS72: Midland Braves 17u Premier | AT72: Eddie Tanner SS
G73: Florida Sluggers | AQ73: Ethan Dorsey? RHP 3.7 | AS73: Kachi Ninjas?/CrosBros? | AT73: Landy Garcia RHP
AQ74: Trent Kulig? RHP | AS74: South Charlotte Panthers | AT74: Brett Kutner 1B/LHH
G75: GBG Northeast | AQ75: Trevor Corbett? SS | AS75: Baseball U | AT75: Peter Karloutsos OF
G76: Georgia Bombers | AT76: Jake Murray C
G77: Georgia Jackets National | H77: Drew Payne RHP(Need Date) | AQ77: Bo Cooper C | AS77: CBA Marucci | AT77: Brady Luyben C
G78: Ghost | AQ78: Drew McTagertt C | AS78: XPress National 17u | AT78: Chet Kosnar RHP-9am Monday June 24/Location TBD
G79: Great Lake Canadians | AS79: 9th Inn Royals Honeycutt | AT79: Kacey Shanks C
G80: Halos National | AS80: Stars VA | AT80: Nathan Lake LHP-Monday Start-confirming
G81: Hitters Black | AQ81: Connor Fuhrer RHP 4.4 | AS81: Stars VA | AT81: Connor Smith LHP-Sunday Start-confirming
AQ82: Bobby Gummere SS | AS82: Stars VA | AT82: Ryu Johnson C-catches at Gonazaga//will see
G83: Indiana Mustangs | AS83: NE Ruffnecks | AT83: Lorcan Lee LHP
G84: Indiana Nitro | AS84: NE Ruffnecks | AT84: Drew Reagan CIF/COF/Hitter
G85: Indiana Prospects | AQ85: All 24s | AS85: Georgia Jackets 17U American | AT85: Brayden Seabold RHP GA (Alpharetta Legion 11:20am Saturday)
G86: Inevitable A's | AQ86: No roster | AT86: Mason Holgerson C
G87: Ironbridge | AQ87: Nate Webb 1B | AT87: Owen Graf RHP OH (High level arm from video, had a call with him. Sounded like he had a lot of heat and not sure of interest but he was responsive)
G88: KBC | AQ88: Rylan Mose OF 6.7 | AS88: USA Prime 17u Scout | AT88: Trent Wilson C
G89: Knights | AQ89: Gunnar Waldrop C | AS89: SBA | AT89: Austin Moran 3b
AS90: Texas senators 17U Scout | AT90: Collin Pence - RHP TX - Has talked to Army mild interest in military. Pitching in relief over two games
G91: Launch | AQ91: Max Reimers RHP | AS91: Ghost Nation | AT91: Ryan Williams - Physical Bat recommended by John Murphy
AQ92: Caleb Thatcher LHP | AS92: On deck O's | AT92: Caden Beaver RHP - High academic don't know anything else about him will do some digging. Starting the 6/24 monday game
G93: Legends Scout | AQ93: Dominic Cadiz 1B(Bat) | AS93: Time to sign | AT93: Julian Lemoer-Turkisher ss NY
G94: Lynx Scout Team | AQ94: Miguel Villegas 1B/RHP | AS94: Barwis Dragons | AT94: Michael Tight RHP FL
AQ95: Sutton Frost C/P | AT95: Jake Finnegan ss FL
G96: Marucci Prospects East Coast | AQ96: Alex Byun C/P
G97: Marucci Spikes | AQ97: Jackson Alex RHP
G98: MASH | AQ98: Etan Price OF | AS98: Team Elite 17U Scout | AT98: Grayson Stroumpis(when is he pitching?)
G99: MBG | AQ99: Jacob Madrid RHP/C/UT
G100: Memphis Tigers | AQ100: Evan Alexander RHP
...

Sheet 2027 Plan
A1: Date Added: | B1: Text type | C1: Coach | D1: First Name | E1: Last Name | F1: Details | G1: ★ | H1: Hometown | I1: State | J1: High School | K1: Summer Team | L1: Academic | N1: Phone Number | O1: Form Filled Out? | P1: Red Flags | Q1: Intrest? | S1: Call Date/Time | T1: Call Notes | U1: Seen
A2: 45865 | B2: Futures | C2: TR | D2: George | E2: Ferguson | F2: 27 RHP TX | G2: 1 | H2: Abilene | I2: TX | J2: Abilene | M2: =D2&" "&E2 -> George Ferguson | N2: 325-665-7151 | O2: {=XLOOKUP(M2,'Recruiting Form Responses'!C:C,'Recruiting Form Responses'!A:A,"",0,1)} | Q2: N | U2: PBR Futures '27
A3: 45865 | B3: Futures | C3: AP | D3: Gerad | E3: Hanle | F3: 27 LHP MN | G3: 1 | H3: Clear lake | I3: MN | J3: Acellus (MN) | L3: 3.8 | M3: =D3&" "&E3 -> Gerad Hanle | O3: {=XLOOKUP(M3,'Recruiting Form Responses'!C:C,'Recruiting Form Responses'!A:A,"",0,1)} | Q3: N | U3: PBR Futures '27
A4: 45865 | B4: Futures | C4: CB | D4: Angelo | E4: Geraldo | F4: 27 3B FL | G4: 1 | H4: Miami | I4: FL | J4: American Heritage (Plantation) (FL) | L4: 3.8 | M4: =D4&" "&E4 -> Angelo Geraldo | N4: 305-815-4607 | O4: {=XLOOKUP(M4,'Recruiting Form Responses'!C:C,'Recruiting Form Responses'!A:A,"",0,1)} | U4: PBR Futures '27
A5: 45865 | B5: Futures | C5: AP | D5: Hunter | E5: Minner | F5: 27 RHP IA | G5: 1 | H5: Ankeny | I5: IA | J5: Ankeny (IA) | L5: 4 | M5: =D5&" "&E5 -> Hunter Minner | N5: 515-210-1407 | O5: {=XLOOKUP(M5,'Recruiting Form Responses'!C:C,'Recruiting Form Responses'!A:A,"",0,1)} | U5: PBR Futures '27
A6: 45865 | B6: Futures | C6: TR | D6: Joseph | E6: Flores | F6: 27 SS CA | G6: 1 | H6: Riverside | I6: CA | J6: Arlington | L6: 4.2 | M6: =D6&" "&E6 -> Joseph Flores | N6: 951-205-9701 | O6: {=XLOOKUP(M6,'Recruiting Form Responses'!C:C,'Recruiting Form Responses'!A:A,"",0,1)} | U6: PBR Futures '27
A7: 45865 | B7: Futures | C7: CB | D7: Brady | E7: Sack | F7: 27 RHP AL | G7: 1 | H7: Auburn | I7: AL | J7: Auburn | L7: 3.87 | M7: =D7&" "&E7 -> Brady Sack | N7: 334-329-2111 | O7: {=XLOOKUP(M7,'Recruiting Form Responses'!C:C,'Recruiting Form Responses'!A:A,"",0,1)} | U7: PBR Futures '27
A8: 45855 | B8: This Summer | C8: CB | D8: Zach | E8: Floyd | F8: 27 CF MA | G8: 1 | I8: MA | J8: Austin Prep | K8: Antonelli | M8: =D8&" "&E8 -> Zach Floyd | N8: 978-880-4692 | O8: {=XLOOKUP(M8,'Recruiting Form Responses'!C:C,'Recruiting Form Responses'!A:A,"",0,1)} -> XX | Q8: N
B9: Personal | C9: CB | D9: Lucas | E9: Sarno | F9: 27 SS MA | G9: 1 | I9: MA | J9: Austin Prep | K9: Team Boston | M9: =D9&" "&E9 -> Lucas Sarno | O9: {=XLOOKUP(M9,'Recruiting Form Responses'!C:C,'Recruiting Form Responses'!A:A,"",0,1)} -> XX | Q9: Y | S9: Confirm Visit | T9: Good call interested. Talk next week. 2ND CALL: visit September 6?
A10: 45865 | B10: This Summer | C10: AP | D10: Nick | E10: Malinowski | F10: 27 RHP NJ | G10: 1 | I10: NJ | J10: Barnegat | K10: .9ers Baseball Club | L10: 4.24 | M10: =D10&" "&E10 -> Nick Malinowski | N10: 609-891-7759 | O10: {=XLOOKUP(M10,'Recruiting Form Responses'!C:C,'Recruiting Form Responses'!A:A,"",0,1)} -> XX | P10: Walnut allergy | Q10: Y | S10: 45883 | T10: coming oct 25th weekend for official visit. Offer from Stetson, visiting UPenn sept 6.
A11: 45865 | B11: Futures | C11: TR | D11: Colin | E11: Zimbelman | F11: 27 C KS | G11: 2 | H11: Basehor | I11: KS | J11: Basehor-Linwood | L11: 4 | M11: =D11&" "&E11 -> Colin Zimbelman | N11: 913-669-8733 | O11: {=XLOOKUP(M11,'Recruiting Form Responses'!C:C,'Recruiting Form Responses'!A:A,"",0,1)} -> XX | P11: Dyslexic | Q11: Y | U11: PBR Futures '27
A12: 45865 | B12: Futures | C12: CB | D12: Cooper | E12: McGowan | F12: 27 SS WA | G12: 1 | H12: Battle Ground | I12: WA | J12: Battle Ground (WA) | L12: 3.8 | M12: =D12&" "&E12 -> Cooper McGowan | N12: 360-667-8091 | O12: {=XLOOKUP(M12,'Recruiting Form Responses'!C:C,'Recruiting Form Responses'!A:A,"",0,1)} | U12: PBR Futures '27
A13: 45865 | B13: Futures | C13: TR | D13: Mac | E13: Morris | F13: 27 INF SC | G13: 1 | H13: Taylors | I13: SC | J13: Baylor | M13: =D13&" "&E13 -> Mac Morris | N13: 864-999-0942 | O13: {=XLOOKUP(M13,'Recruiting Form Responses'!C:C,'Recruiting Form Responses'!A:A,"",0,1)} | U13: PBR Futures '27
B14: Personal | C14: CB | D14: Jack | E14: Swanson | F14: 27 C MA | G14: 2 | I14: CT | J14: Berlin | K14: Swanson Baseball | M14: =D14&" "&E14 -> Jack Swanson | O14: {=XLOOKUP(M14,'Recruiting Form Responses'!C:C,'Recruiting Form Responses'!A:A,"",0,1)} -> XX | Q14: Y | S14: Next week | T14: Intro call. Need to follow up in August
A15: 45865 | B15: Futures | C15: CB | D15: Justin | E15: Rodrigues | F15: 27 MINF NV | G15: 1 | H15: Las Vegas | I15: NV | J15: Bishop Gorman | L15: 4 | M15: =D15&" "&E15 -> Justin Rodrigues | N15: 702-480-7500 | O15: {=XLOOKUP(M15,'Recruiting Form Responses'!C:C,'Recruiting Form Responses'!A:A,"",0,1)} | U15: PBR Futures '27
A16: 45865 | B16: Futures | C16: CB | D16: Brody | E16: Baxmann | F16: 27 OF FL | G16: 1 | H16: Fort myers | I16: FL | J16: Bishop Verot (FL) | L16: 3.9 | M16: =D16&" "&E16 -> Brody Baxmann | N16: 239-671-0473 | O16: {=XLOOKUP(M16,'Recruiting Form Responses'!C:C,'Recruiting Form Responses'!A:A,"",0,1)} | U16: PBR Futures '27
B17: This Summer | C17: AP | D17: Wyatt | E17: Libbert | F17: 27 RHP MO | G17: 2 | I17: MO | J17: Blair Oaks | K17: Royals Scout Team | L17: 3.96? | M17: =D17&" "&E17 -> Wyatt Libbert | N17: 573-619-0017 | O17: {=XLOOKUP(M17,'Recruiting Form Responses'!C:C,'Recruiting Form Responses'!A:A,"",0,1)}
A18: 45865 | B18: Futures | C18: CB | D18: Drew | E18: Pittman | F18: 27 MINF KS | G18: 2 | H18: Overland Park | I18: KS | J18: Blue Valley Southwest | M18: =D18&" "&E18 -> Drew Pittman | N18: 913-553-9868 | O18: {=XLOOKUP(M18,'Recruiting Form Responses'!C:C,'Recruiting Form Responses'!A:A,"",0,1)} | U18: PBR Futures '27
A19: 45865 | B19: Futures | C19: AP | D19: Hayden | E19: Henry | F19: 27 RHP KY | G19: 1 | H19: Webster | I19: KY | J19: Breckinridge County | L19: 4 | M19: =D19&" "&E19 -> Hayden Henry | N19: 502-271-9652 | O19: {=XLOOKUP(M19,'Recruiting Form Responses'!C:C,'Recruiting Form Responses'!A:A,"",0,1)} | T19: sent form, ghosted | U19: PBR Futures '27
A20: 45865 | B20: Futures | C20: TR | D20: Cruz | E20: Garcia | F20: 27 C CA | G20: 2 | H20: Brentwood | I20: CA | J20: Brent International | L20: 3.7 | M20: =D20&" "&E20 -> Cruz Garcia | N20: 925-537-4599 | O20: {=XLOOKUP(M20,'Recruiting Form Responses'!C:C,'Recruiting Form Responses'!A:A,"",0,1)} | U20: PBR Futures '27
A21: 45865 | B21: Futures | C21: TR | D21: Daniel | E21: Sanchez | F21: 27 RHP VA | G21: 1 | H21: Broadlands | I21: VA | J21: Briar Woods | L21: 4 | M21: =D21&" "&E21 -> Daniel Sanchez | N21: 571-521-9536 | O21: {=XLOOKUP(M21,'Recruiting Form Responses'!C:C,'Recruiting Form Responses'!A:A,"",0,1)} | U21: PBR Futures '27
A22: 45865 | B22: Futures | C22: CB | D22: Jake | E22: Lopez | F22: 27 SS OK | G22: 1 | H22: Broken Arrow | I22: OK | J22: Broken Arrow (OK) | L22: 3.6 | M22: =D22&" "&E22 -> Jake Lopez | N22: 760-694-5576 | O22: {=XLOOKUP(M22,'Recruiting Form Responses'!C:C,'Recruiting Form Responses'!A:A,"",0,1)} -> XX | P22: Peanuts | Q22: N | S22: 45869.417 | T22: Severe peanut allergy | U22: PBR Futures '27
A23: 45865 | B23: Futures | C23: TR | D23: Jackson | E23: Shepherd | F23: 27 3B CO | G23: 1 | H23: Superior | I23: CO | J23: Broomfield | M23: =D23&" "&E23 -> Jackson Shepherd | N23: 720-990-3199 | O23: {=XLOOKUP(M23,'Recruiting Form Responses'!C:C,'Recruiting Form Responses'!A:A,"",0,1)} | P23: Peanuts. No medication | Q23: Y | U23: PBR Futures '27
A24: 45865 | B24: Futures | C24: CB | D24: Grady | E24: Openden | F24: 27 RHP AZ | G24: 1 | H24: Phoenix | I24: AZ | J24: Brophy Prep | L24: 3.77 | M24: =D24&" "&E24 -> Grady Openden | N24: 602-413-4603 | O24: {=XLOOKUP(M24,'Recruiting Form Responses'!C:C,'Recruiting Form Responses'!A:A,"",0,1)} -> XX | P24: Grades | Q24: Y | S24: Follow up | T24: Great call. Air Force and others. Wants to visit campus soon. | U24: PBR Futures '27
A25: 45865 | B25: Futures | C25: TR | D25: Selvin | E25: Garrett | F25: 27 SS TX | G25: 2 | H25: Buda | I25: TX | J25: Buda Johnson | M25: =D25&" "&E25 -> Selvin Garrett | N25: 737-414-2553 | O25: {=XLOOKUP(M25,'Recruiting Form Responses'!C:C,'Recruiting Form Responses'!A:A,"",0,1)} | U25: PBR Futures '27
A26: 45865 | B26: Futures | C26: TR | D26: Jackson | E26: Schilling | F26: 27 C OH | G26: 1 | H26: Vandalia | I26: OH | J26: Butler High School | L26: 3.8 | M26: =D26&" "&E26 -> Jackson Schilling | N26: 937-605-2868 | O26: {=XLOOKUP(M26,'Recruiting Form Responses'!C:C,'Recruiting Form Responses'!A:A,"",0,1)} | U26: PBR Futures '27
A27: 45865 | B27: Futures | C27: CB | D27: Andrew | E27: Talbert | F27: 27 CF IL | G27: 1 | H27: Byron | I27: IL | J27: Byron | L27: 4.5 | M27: =D27&" "&E27 -> Andrew Talbert | N27: 815-990-5514 | O27: {=XLOOKUP(M27,'Recruiting Form Responses'!C:C,'Recruiting Form Responses'!A:A,"",0,1)} | U27: PBR Futures '27
A28: 45865 | B28: Futures | C28: TR | D28: Kenson | E28: Buth | F28: 27 SS TX | G28: 1 | H28: trophy club | I28: TX | J28: Byron Nelson | L28: 4 | M28: =D28&" "&E28 -> Kenson Buth | N28: 817-917-2186 | O28: {=XLOOKUP(M28,'Recruiting Form Responses'!C:C,'Recruiting Form Responses'!A:A,"",0,1)} | P28: Eczema | Q28: Y | T28: Sounded interested. Sent eczema stuff waiting to hear. | U28: PBR Futures '27
A29: 45865 | B29: Futures | C29: AP | D29: Ari | E29: Wells | F29: 27 1B KY | G29: 1 | H29: Princeton | I29: KY | J29: Caldwell County | L29: 4.3 | M29: =D29&" "&E29 -> Ari Wells | N29: 270-963-3482 | O29: {=XLOOKUP(M29,'Recruiting Form Responses'!C:C,'Recruiting Form Responses'!A:A,"",0,1)} | U29: PBR Futures '27
B30: Personal | C30: AP | D30: Jacob | E30: Henderson | G30: 2 | I30: FL | J30: Calvary Christian | K30: Orlando Scorpions | L30: 4.0 / 1490 | M30: =D30&" "&E30 -> Jacob Henderson | O30: {=XLOOKUP(M30,'Recruiting Form Responses'!C:C,'Recruiting Form Responses'!A:A,"",0,1)} -> XX | Q30: Y | S30: texted | T30: not coming to camp...maybe fall camp
A31: 45865 | B31: Futures | C31: AP | D31: Troy | E31: Stimpson | F31: 27 C PA | G31: 1 | H31: Canonsburg | I31: PA | J31: Canon-Mcmillan | L31: 4.3 | M31: =D31&" "&E31 -> Troy Stimpson | N31: 412-506-1154 | O31: {=XLOOKUP(M31,'Recruiting Form Responses'!C:C,'Recruiting Form Responses'!A:A,"",0,1)} | Q31: N | U31: PBR Futures '27
B32: This Summer | C32: AP | D32: Colton | E32: Hyde | F32: 27 RHP FL | G32: 2 | I32: FL | J32: Cardinal Mooney | K32: FL Burn | L32: 3.6? risky | M32: =D32&" "&E32 -> Colton Hyde | N32: 773-683-7095 | O32: {=XLOOKUP(M32,'Recruiting Form Responses'!C:C,'Recruiting Form Responses'!A:A,"",0,1)} -> XX | Q32: Y | T32: live arm but no breaking ball...do we go after this?
A33: 45865 | B33: Futures | C33: TR | D33: Hudson | E33: Cuevas | F33: 27 SS TX | G33: 1 | H33: Cedar Park | I33: TX | J33: Cedar Park | L33: 5.3 | M33: =D33&" "&E33 -> Hudson Cuevas | N33: 512-969-9940 | O33: {=XLOOKUP(M33,'Recruiting Form Responses'!C:C,'Recruiting Form Responses'!A:A,"",0,1)} | Q33: N | U33: PBR Futures '27
A34: 45865 | B34: Futures | C34: CB | D34: Liam | E34: Delp | F34: 27 MINF IN | G34: 1 | H34: Bargersville | I34: IN | J34: Center Grove | L34: 3.7 | M34: =D34&" "&E34 -> Liam Delp | N34: 719-338-0088 | O34: {=XLOOKUP(M34,'Recruiting Form Responses'!C:C,'Recruiting Form Responses'!A:A,"",0,1)} -> XX | U34: PBR Futures '27
A35: 45865 | B35: Futures | C35: CB | D35: Charlie | E35: Beck | F35: 27 MINF NC | G35: 2 | H35: Thomasville | I35: NC | J35: Central Davidson High | L35: 3.87 | M35: =D35&" "&E35 -> Charlie Beck | N35: 336-880-6126 | O35: {=XLOOKUP(M35,'Recruiting Form Responses'!C:C,'Recruiting Form Responses'!A:A,"",0,1)} | U35: PBR Futures '27
B36: This Summer | C36: AP | D36: Cody | E36: Branham | F36: 27 C SC | G36: 2 | I36: SC | J36: Central HS | K36: Dirtbags | L36: 4.69 | M36: =D36&" "&E36 -> Cody Branham | N36: 843-680-0298 | O36: {=XLOOKUP(M36,'Recruiting Form Responses'!C:C,'Recruiting Form Responses'!A:A,"",0,1)} -> 3 | Q36: Y | S36: -- | T36: Not a priority right now
A37: 45865 | B37: Futures | C37: TR | D37: Vinny | E37: Boatwright | F37: 27 RHP CA | G37: 1 | H37: Chico | I37: CA | J37: Chico | M37: =D37&" "&E37 -> Vinny Boatwright | N37: 530-588-5673 | O37: {=XLOOKUP(M37,'Recruiting Form Responses'!C:C,'Recruiting Form Responses'!A:A,"",0,1)} | U37: PBR Futures '27
A38: 45865 | B38: Futures | C38: TR | D38: Jacob | E38: Lessman | F38: 27 RHP TX | G38: 1 | H38: Whitney | I38: TX | J38: China Spring | L38: 3.7 | M38: =D38&" "&E38 -> Jacob Lessman | N38: 254-855-6997 | O38: {=XLOOKUP(M38,'Recruiting Form Responses'!C:C,'Recruiting Form Responses'!A:A,"",0,1)} | U38: PBR Futures '27
A39: 45865 | B39: Futures | C39: CB | D39: Caleb | E39: Lynn | F39: 27 OF NC | G39: 1 | H39: Garner | I39: NC | J39: Cleveland | L39: 3.6 | M39: =D39&" "&E39 -> Caleb Lynn | N39: 919-599-1976 | O39: {=XLOOKUP(M39,'Recruiting Form Responses'!C:C,'Recruiting Form Responses'!A:A,"",0,1)} | U39: PBR Futures '27
A40: 45865 | B40: Futures | C40: CB | D40: Lincoln | E40: Eure | F40: 27 RHP UT | G40: 1 | H40: Sandy | I40: UT | J40: Corner Canyon | L40: 3.98 | M40: =D40&" "&E40 -> Lincoln Eure | N40: 801-949-7591 | O40: {=XLOOKUP(M40,'Recruiting Form Responses'!C:C,'Recruiting Form Responses'!A:A,"",0,1)} -> XX | Q40: Y | S40: Follow up | T40: Has thought about service and is interested. I95. AZ fall classic ft. Myers, then wrestling. Money big factor. | U40: PBR Futures '27
A41: 45865 | B41: Futures | C41: CB | D41: Jack | E41: Munson | F41: 27 OF UT | G41: 2 | H41: Sandy | I41: UT | J41: Corner Canyon | L41: 3.87 | M41: =D41&" "&E41 -> Jack Munson | N41: 225-819-6390 | O41: {=XLOOKUP(M41,'Recruiting Form Responses'!C:C,'Recruiting Form Responses'!A:A,"",0,1)} -> XX | Q41: Y | S41: 45868.688 | T41: Has thought about academies. Wants high academic. Parents used to live in Maryland/DC. | U41: PBR Futures '27
A42: 45865 | B42: Futures | C42: TR | D42: Ike | E42: Crouser | F42: 27 RHP MN | G42: 1 | H42: Saint Paul | I42: MN | J42: Cretin (MN) | L42: 4.09 | M42: =D42&" "&E42 -> Ike Crouser | N42: 651-279-3977 | O42: {=XLOOKUP(M42,'Recruiting Form Responses'!C:C,'Recruiting Form Responses'!A:A,"",0,1)} | P42: Pistachios hazelnuts | Q42: Y | U42: PBR Futures '27
A43: 45865 | B43: Futures | C43: AP | D43: Brady | E43: Smith | F43: 27 RHP IA | G43: 2 | H43: Grimes | I43: IA | J43: Dallas Center-Grimes (IA) | L43: 3.9 | M43: =D43&" "&E43 -> Brady Smith | N43: 515-776-2873 | O43: {=XLOOKUP(M43,'Recruiting Form Responses'!C:C,'Recruiting Form Responses'!A:A,"",0,1)} | U43: PBR Futures '27
A44: 45865 | B44: Futures | C44: TR | D44: Luke | E44: McAtee | F44: 27 C MO | G44: 2 | H44: Town and Country | I44: MO | J44: De Smet Jesuit (MO) | L44: 3.7 | M44: =D44&" "&E44 -> Luke McAtee | N44: 314-705-7103 | O44: {=XLOOKUP(M44,'Recruiting Form Responses'!C:C,'Recruiting Form Responses'!A:A,"",0,1)} -> XX | Q44: Y | U44: PBR Futures '27
B45: This Summer | C45: CB | D45: Kyle | E45: McBride | F45: 27 RHP NJ | G45: 1 | I45: NJ | J45: Delbarton | K45: TKR Reds | L45: 4.1 | M45: =D45&" "&E45 -> Kyle McBride | N45: 908-455-4292 | O45: {=XLOOKUP(M45,'Recruiting Form Responses'!C:C,'Recruiting Form Responses'!A:A,"",0,1)} | Q45: XX | S45: Wake Forest
A46: 45865 | B46: Futures | C46: TR | D46: Steven | E46: Pannullo | F46: 27 RHP NJ | G46: 1 | H46: Essex Fells | I46: NJ | J46: Delbarton | L46: 3.6 | M46: =D46&" "&E46 -> Steven Pannullo | N46: 201-755-6396 | O46: {=XLOOKUP(M46,'Recruiting Form Responses'!C:C,'Recruiting Form Responses'!A:A,"",0,1)} | P46: Sesame allergy. Takes Ritalin | Q46: Y | U46: PBR Futures '27
A47: 45865 | B47: Futures | C47: TR | D47: Curt | E47: Friedrich | F47: 27 OF NJ | G47: 1 | H47: Summit | I47: NJ | J47: Delbarton | L47: 3.9 | M47: =D47&" "&E47 -> Curt Friedrich | N47: 646-887-7191 | O47: {=XLOOKUP(M47,'Recruiting Form Responses'!C:C,'Recruiting Form Responses'!A:A,"",0,1)} | U47: PBR Futures '27
A48: 45865 | B48: Futures | C48: TR | D48: Ted | E48: Masino | F48: 27 RHP NJ | G48: 1 | H48: Maplewood | I48: NJ | J48: Delbarton | L48: 4.1 | M48: =D48&" "&E48 -> Ted Masino | N48: 973-768-7392 | O48: {=XLOOKUP(M48,'Recruiting Form Responses'!C:C,'Recruiting Form Responses'!A:A,"",0,1)} | U48: PBR Futures '27
B49: Personal | C49: CB | D49: Patrick | E49: Bryan | F49: 27 C MA | G49: 1 | I49: MA | J49: Dexter Southfield | K49: MDB Knights | M49: =D49&" "&E49 -> Patrick Bryan | O49: {=XLOOKUP(M49,'Recruiting Form Responses'!C:C,'Recruiting Form Responses'!A:A,"",0,1)} | P49: Grades | Q49: XX | S49: Stanford | T49: Will be a long shot but parents want him to really consider it. Asked good questions. Circle back next week.
A50: 45865 | B50: Futures | C50: TR | D50: Connor | E50: Wells | F50: 27 LHP SC | G50: 1 | H50: Spartanburg | I50: SC | J50: Dorman | M50: =D50&" "&E50 -> Connor Wells | N50: 864-327-6853 | O50: {=XLOOKUP(M50,'Recruiting Form Responses'!C:C,'Recruiting Form Responses'!A:A,"",0,1)} | U50: PBR Futures '27
A51: 45865 | B51: Futures | C51: TR | D51: Max | E51: Mangum | F51: 27 RHP TX | G51: 1 | H51: East Bernard | I51: TX | J51: East Bernard | L51: 3.8 | M51: =D51&" "&E51 -> Max Mangum | N51: 979-758-1047 | O51: {=XLOOKUP(M51,'Recruiting Form Responses'!C:C,'Recruiting Form Responses'!A:A,"",0,1)} | U51: PBR Futures '27
A52: 45865 | B52: Futures | C52: AP | D52: Ty | E52: McGinley | F52: 27 RHP AL | G52: 1 | H52: Fairhope | I52: AL | J52: Fairhope | L52: 3.8 | M52: =D52&" "&E52 -> Ty McGinley | N52: 251-923-9916 | O52: {=XLOOKUP(M52,'Recruiting Form Responses'!C:C,'Recruiting Form Responses'!A:A,"",0,1)} | U52: PBR Futures '27
A53: 45865 | B53: Futures | C53: AP | D53: Eli | E53: Quinley | F53: 27 C AL | G53: 1 | H53: Mobile | I53: AL | J53: Faith Academy | L53: 4.57 | M53: =D53&" "&E53 -> Eli Quinley | N53: 251-895-6167 | O53: {=XLOOKUP(M53,'Recruiting Form Responses'!C:C,'Recruiting Form Responses'!A:A,"",0,1)} | U53: PBR Futures '27
A54: 45865 | B54: Futures | C54: CB | D54: Omar | E54: Avalos | F54: 27 CF IL | G54: 2 | H54: Edwardsville | I54: IL | J54: Father McGivney (IL) | L54: 3.75 | M54: =D54&" "&E54 -> Omar Avalos | N54: 618-799-1030 | O54: {=XLOOKUP(M54,'Recruiting Form Responses'!C:C,'Recruiting Form Responses'!A:A,"",0,1)} | U54: PBR Futures '27
A55: 45865 | B55: Futures | C55: CB | D55: Carter | E55: Kelly | F55: 27 INF SC | G55: 2 | H55: Simpsonville | I55: SC | J55: Fountain Inn High | L55: 4 | M55: =D55&" "&E55 -> Carter Kelly | N55: 267-456-6673 | O55: {=XLOOKUP(M55,'Recruiting Form Responses'!C:C,'Recruiting Form Responses'!A:A,"",0,1)} | U55: PBR Futures '27
A56: 45865 | B56: Futures | C56: AP | D56: Colt | E56: Bradshaw | F56: 27 SS VA | G56: 1 | H56: Virginia Beach | I56: VA | J56: Frank W. Cox | L56: 4.1 | M56: =D56&" "&E56 -> Colt Bradshaw | N56: 757-362-4010 | O56: {=XLOOKUP(M56,'Recruiting Form Responses'!C:C,'Recruiting Form Responses'!A:A,"",0,1)} | Q56: Y | S56: 45909 | T56: interested in first talk. hamstring pull late summer. will play richmond braves in PG ft Myers | U56: PBR Futures '27
A57: 45865 | B57: Futures | C57: TR | D57: Luke | E57: Crawford | F57: 27 C MD | G57: 2 | H57: Potomac | I57: MD | J57: Georgetown Preparatory School | L57: 4 | M57: =D57&" "&E57 -> Luke Crawford | N57: 202-420-1263 | O57: {=XLOOKUP(M57,'Recruiting Form Responses'!C:C,'Recruiting Form Responses'!A:A,"",0,1)} -> XX | Q57: Y | U57: PBR Futures '27
A58: 45865 | B58: Futures | C58: CB | D58: Brady | E58: Yates | F58: 27 3B MO | G58: 1 | H58: Springfield | I58: MO | J58: Glendale | L58: 4.25 | M58: =D58&" "&E58 -> Brady Yates | N58: 417-371-8915 | O58: {=XLOOKUP(M58,'Recruiting Form Responses'!C:C,'Recruiting Form Responses'!A:A,"",0,1)} | U58: PBR Futures '27
A59: 45865 | B59: Futures | C59: CB | D59: Jacob | E59: Babcock | F59: 27 MINF VA | G59: 2 | H59: Richmond | I59: VA | J59: Godwin | L59: 4 | M59: =D59&" "&E59 -> Jacob Babcock | N59: 804-921-5443 | O59: {=XLOOKUP(M59,'Recruiting Form Responses'!C:C,'Recruiting Form Responses'!A:A,"",0,1)} -> XX | Q59: Y | S59: 45870.396 | T59: Interested. Need to see him play more. | U59: PBR Futures '27
A60: 45865 | B60: Futures | C60: CB | D60: Lucas | E60: Collure | F60: 27 OF NY | G60: 2 | H60: Grand Island | I60: NY | J60: Grand Island | M60: =D60&" "&E60 -> Lucas Collure | N60: 716-435-8460 | O60: {=XLOOKUP(M60,'Recruiting Form Responses'!C:C,'Recruiting Form Responses'!A:A,"",0,1)} | Q60: Y | S60: 45869.646 | T60: Interested. Back burner. | U60: PBR Futures '27
B61: This Summer | C61: AP | D61: Roy | E61: Kim | F61: 27 LHP CA | G61: 2 | I61: CA | J61: Great Oak | K61: Sandlot Baseball Club | L61: 4.3 | M61: =D61&" "&E61 -> Roy Kim | N61: 951-557-1360 | O61: {=XLOOKUP(M61,'Recruiting Form Responses'!C:C,'Recruiting Form Responses'!A:A,"",0,1)} | Q61: XX | S61: Stanford
A62: 45865 | B62: Futures | C62: TR | D62: Jake | E62: Ivey | F62: 27 LHP TX | G62: 1 | H62: Gunter | I62: TX | J62: Gunter | M62: =D62&" "&E62 -> Jake Ivey | N62: 469-858-1768 | O62: {=XLOOKUP(M62,'Recruiting Form Responses'!C:C,'Recruiting Form Responses'!A:A,"",0,1)} | U62: PBR Futures '27
A63: 45865 | B63: Futures | C63: TR | D63: Riley | E63: Jackson | F63: 27 INF CA | G63: 2 | H63: El Granada | I63: CA | J63: Half Moon Bay | L63: 4 | M63: =D63&" "&E63 -> Riley Jackson | N63: 650-784-5055 | O63: {=XLOOKUP(M63,'Recruiting Form Responses'!C:C,'Recruiting Form Responses'!A:A,"",0,1)} -> XX | Q63: Y | U63: PBR Futures '27
A64: 45865 | B64: Futures | C64: TR | D64: Colt | E64: Babic | F64: 27 INF SC | G64: 2 | H64: Camden | I64: SC | J64: Hammond | M64: =D64&" "&E64 -> Colt Babic | N64: 803-427-5757 | O64: {=XLOOKUP(M64,'Recruiting Form Responses'!C:C,'Recruiting Form Responses'!A:A,"",0,1)} | U64: PBR Futures '27
A65: 45865 | B65: Futures | C65: CB | D65: Dylan | E65: Crowe | F65: 27 SS MI | G65: 1 | H65: Brighton | I65: MI | J65: Hartland | L65: 3.96 | M65: =D65&" "&E65 -> Dylan Crowe | N65: 248-417-8452 | O65: {=XLOOKUP(M65,'Recruiting Form Responses'!C:C,'Recruiting Form Responses'!A:A,"",0,1)} | U65: PBR Futures '27
A66: 45865 | B66: Futures | C66: TR | D66: Freddy | E66: Corrado | F66: 27 RHP PA | G66: 1 | H66: Hazle Township | I66: PA | J66: Hazleton Area | L66: 4 | M66: =D66&" "&E66 -> Freddy Corrado | N66: 570-599-7516 | O66: {=XLOOKUP(M66,'Recruiting Form Responses'!C:C,'Recruiting Form Responses'!A:A,"",0,1)} | U66: PBR Futures '27
A67: 45865 | B67: Futures | C67: CB | D67: Charlie | E67: Herr | F67: 27 RHP IN | G67: 2 | H67: Fort Wayne | I67: IN | J67: Homestead Senior | L67: 4 | M67: =D67&" "&E67 -> Charlie Herr | N67: 260-415-4805 | O67: {=XLOOKUP(M67,'Recruiting Form Responses'!C:C,'Recruiting Form Responses'!A:A,"",0,1)} -> XX | Q67: Y | U67: PBR Futures '27
A68: 45865 | B68: Futures | C68: TR | D68: Cason | E68: Borchardt | F68: 27 OF ND | G68: 1 | H68: Horace | I68: ND | J68: Horace (ND) | L68: 3.8 | M68: =D68&" "&E68 -> Cason Borchardt | N68: 701-306-4751 | O68: {=XLOOKUP(M68,'Recruiting Form Responses'!C:C,'Recruiting Form Responses'!A:A,"",0,1)} | U68: PBR Futures '27
A69: 45865 | B69: Futures | C69: TR | D69: Parker | E69: Leoff | F69: 27 SS CA | G69: 1 | H69: Redondo Beach | I69: CA | J69: Huntington Beach | M69: =D69&" "&E69 -> Parker Leoff | N69: 310-922-6369 | O69: {=XLOOKUP(M69,'Recruiting Form Responses'!C:C,'Recruiting Form Responses'!A:A,"",0,1)} | U69: PBR Futures '27
A70: 45865 | B70: Futures | C70: CB | D70: Bode | E70: Schenewerk | F70: 27 MINF MO | G70: 2 | H70: Jefferson City | I70: MO | J70: Jefferson City (MO) | L70: 3.6 | M70: =D70&" "&E70 -> Bode Schenewerk | N70: 573-789-8889 | O70: {=XLOOKUP(M70,'Recruiting Form Responses'!C:C,'Recruiting Form Responses'!A:A,"",0,1)} -> XX | P70: Grades | Q70: Y | U70: PBR Futures '27
B71: This Summer | C71: AP | D71: Brennan | E71: Jones | F71: 27 SS FL | G71: 2 | I71: FL | J71: John Carroll | K71: Florida Burn | L71: 3.75 | M71: =D71&" "&E71 -> Brennan Jones | N71: 772-208-7544 | O71: {=XLOOKUP(M71,'Recruiting Form Responses'!C:C,'Recruiting Form Responses'!A:A,"",0,1)} -> 3 | Q71: Y | S71: 45882 | T71: interested in second call. FAU interest. would like to visit. possible oct 25 visit if we like him. might need to see again. Conch baseball in fall ball
B72: This Summer | C72: AP | D72: Evan | E72: Brand | F72: 27 2B GA | G72: 1 | I72: GA | J72: Kell | K72: 643 DP | L72: 4 | M72: =D72&" "&E72 -> Evan Brand | N72: 770-235-6962 | O72: {=XLOOKUP(M72,'Recruiting Form Responses'!C:C,'Recruiting Form Responses'!A:A,"",0,1)}
A73: 45865 | B73: Futures | C73: TR | D73: Ryan | E73: Younglas | F73: 27 3B OH | G73: 1 | H73: Wellington | I73: OH | J73: Keystone | M73: =D73&" "&E73 -> Ryan Younglas | N73: 440-420-8186 | O73: {=XLOOKUP(M73,'Recruiting Form Responses'!C:C,'Recruiting Form Responses'!A:A,"",0,1)} | U73: PBR Futures '27
A74: 45865 | B74: Futures | C74: CB | D74: Lincoln | E74: Norris | F74: 27 MINF IA | G74: 1 | H74: Knoxville | I74: IA | J74: Knoxville (IA) | L74: 4 | M74: =D74&" "&E74 -> Lincoln Norris | N74: 641-205-9390 | O74: {=XLOOKUP(M74,'Recruiting Form Responses'!C:C,'Recruiting Form Responses'!A:A,"",0,1)} | Q74: Y | S74: Visit BOOKED | T74: Great talk very interested. Circle back next week. B10 schools | U74: PBR Futures '27
A75: 45865 | B75: Futures | C75: AP | D75: Boston | E75: Brown | F75: 27 RHP AL | G75: 1 | H75: Phenix City | I75: AL | J75: Lakeside | L75: 4.2 | M75: =D75&" "&E75 -> Boston Brown | O75: {=XLOOKUP(M75,'Recruiting Form Responses'!C:C,'Recruiting Form Responses'!A:A,"",0,1)} -> XX | Q75: XX | S75: Auburn | U75: PBR Futures '27
A76: 45865 | B76: Futures | C76: TR | D76: Cooper | E76: Hillen | F76: 27 SS PA | G76: 2 | H76: Lancaster | I76: PA | J76: Lampeter-Strasburg | L76: 4.1 | M76: =D76&" "&E76 -> Cooper Hillen | N76: 717-380-5334 | O76: {=XLOOKUP(M76,'Recruiting Form Responses'!C:C,'Recruiting Form Responses'!A:A,"",0,1)} -> XX | Q76: Y | U76: PBR Futures '27
B77: This Summer | C77: AP | D77: Ryker | E77: Mahnke | F77: 27 OF KS | G77: 1 | I77: KS | J77: Lawrence Free State HS | K77: Royals Scout Team | L77: 3.8? | M77: =D77&" "&E77 -> Ryker Mahnke | N77: 785-218-4351 | O77: {=XLOOKUP(M77,'Recruiting Form Responses'!C:C,'Recruiting Form Responses'!A:A,"",0,1)} -> XX | Q77: Y | S77: 45882 | T77: good call. interested. sent visit dates oct25.
A78: 45865 | B78: Futures | C78: TR | D78: Beckett | E78: York | F78: 27 SS MO | G78: 2 | H78: Lebanon | I78: MO | J78: Lebanon (MO) | L78: 3.8 | M78: =D78&" "&E78 -> Beckett York | N78: 417-650-5737 | O78: {=XLOOKUP(M78,'Recruiting Form Responses'!C:C,'Recruiting Form Responses'!A:A,"",0,1)} | U78: PBR Futures '27
A79: 45865 | B79: Futures | C79: AP | D79: Sam | E79: Pearson | F79: 27 SS KY | G79: 1 | H79: Lexington | I79: KY | J79: Lexington Christian Academy | L79: 4 | M79: =D79&" "&E79 -> Sam Pearson | N79: 502-542-5318 | O79: {=XLOOKUP(M79,'Recruiting Form Responses'!C:C,'Recruiting Form Responses'!A:A,"",0,1)} -> XX | Q79: Y | S79: 45881 | T79: good call. visiting VT, offers from Toledo, CofC. football player | U79: PBR Futures '27
A80: 45865 | B80: Futures | C80: TR | D80: Stevie | E80: Wellens | F80: 27 MINF CA | G80: 1 | H80: Brentwood | I80: CA | J80: Liberty | L80: 4 | M80: =D80&" "&E80 -> Stevie Wellens | N80: 925-357-5516 | O80: {=XLOOKUP(M80,'Recruiting Form Responses'!C:C,'Recruiting Form Responses'!A:A,"",0,1)} | Q80: Y | T80: Very interested. Have calls with his coaches and follwoing up this week | U80: PBR Futures '27
A81: 45865 | B81: Futures | C81: TR | D81: Grant | E81: Stafford | F81: 27 SS TX | G81: 1 | H81: Lufkin | I81: TX | J81: Lufkin | M81: =D81&" "&E81 -> Grant Stafford | N81: 936-208-1965 | O81: {=XLOOKUP(M81,'Recruiting Form Responses'!C:C,'Recruiting Form Responses'!A:A,"",0,1)} -> XX | P81: Dyslexic | Q81: Y | U81: PBR Futures '27
B82: This Summer | C82: AP | D82: Ryan | E82: Hawken | F82: 27 OF NJ | G82: 2 | I82: NJ | J82: Mahwah | K82: Ghost | L82: ? | M82: =D82&" "&E82 -> Ryan Hawken | N82: 551-579-0901 | O82: {=XLOOKUP(M82,'Recruiting Form Responses'!C:C,'Recruiting Form Responses'!A:A,"",0,1)} -> 2 | Q82: Y | S82: 45881 | T82: possibly coming to oct NAVY camp
A83: 45865 | B83: Futures | C83: AP | D83: Cale | E83: Hackenberg | F83: 27 C MI | G83: 2 | H83: Marcellus | I83: MI | J83: Marcellus | L83: 3.95 | M83: =D83&" "&E83 -> Cale Hackenberg | N83: 269-532-0807 | O83: {=XLOOKUP(M83,'Recruiting Form Responses'!C:C,'Recruiting Form Responses'!A:A,"",0,1)} | U83: PBR Futures '27
A84: 45865 | B84: Futures | C84: TR | D84: Isaac | E84: Lockwood | F84: 27 RHP CO | G84: 1 | H84: Mead | I84: CO | J84: Mead | M84: =D84&" "&E84 -> Isaac Lockwood | N84: 720-724-0474 | O84: {=XLOOKUP(M84,'Recruiting Form Responses'!C:C,'Recruiting Form Responses'!A:A,"",0,1)} | U84: PBR Futures '27
A85: 45865 | B85: Futures | C85: CB | D85: Braden | E85: Swaney | F85: 27 OF NE | G85: 2 | H85: Omaha | I85: NE | J85: Millard South (NE) | L85: 3.7 | M85: =D85&" "&E85 -> Braden Swaney | N85: 531-203-3504 | O85: {=XLOOKUP(M85,'Recruiting Form Responses'!C:C,'Recruiting Form Responses'!A:A,"",0,1)} | U85: PBR Futures '27
A86: 45865 | B86: Futures | C86: TR | D86: Briar | E86: Persing | F86: 27 RHP PA | G86: 2 | H86: Montgomery | I86: PA | J86: Montgomery | M86: =D86&" "&E86 -> Briar Persing | N86: 570-506-7759 | O86: {=XLOOKUP(M86,'Recruiting Form Responses'!C:C,'Recruiting Form Responses'!A:A,"",0,1)} | U86: PBR Futures '27
B87: This Summer | C87: AP | D87: Ryan | E87: Harless | F87: 27 OF FL | G87: 2 | I87: FL | J87: Mosley | K87: TE Scout | L87: 4 | M87: =D87&" "&E87 -> Ryan Harless | N87: 850-774-3154 | O87: {=XLOOKUP(M87,'Recruiting Form Responses'!C:C,'Recruiting Form Responses'!A:A,"",0,1)} -> XX | Q87: Y | S87: -- | T87: Not a priority right now
A88: 45865 | B88: Futures | C88: TR | D88: Drew | E88: Cross | F88: 27 C TX | G88: 1 | H88: Mount Pleasant | I88: TX | J88: Mount Pleasant | L88: 4 | M88: =D88&" "&E88 -> Drew Cross | N88: 903-285-0299 | O88: {=XLOOKUP(M88,'Recruiting Form Responses'!C:C,'Recruiting Form Responses'!A:A,"",0,1)} | P88: Deaf 1 Ear | Q88: Y | T88: Out with deafness | U88: PBR Futures '27
A89: 45865 | B89: Futures | C89: CB | D89: Jude | E89: Davidson | F89: 27 RHP AL | G89: 1 | H89: Mountain Brook | I89: AL | J89: Mountain Brook | L89: 4.6 | M89: =D89&" "&E89 -> Jude Davidson | N89: 205-922-1753 | O89: {=XLOOKUP(M89,'Recruiting Form Responses'!C:C,'Recruiting Form Responses'!A:A,"",0,1)} -> 0.1 | U89: PBR Futures '27
A90: 45865 | B90: Futures | C90: CB | D90: Jackson | E90: Crawford | F90: 27 OF CO | G90: 1 | H90: Highlands Ranch | I90: CO | J90: Mountain Vista | L90: 3.8 | M90: =D90&" "&E90 -> Jackson Crawford | N90: 303-579-8413 | O90: {=XLOOKUP(M90,'Recruiting Form Responses'!C:C,'Recruiting Form Responses'!A:A,"",0,1)} | Q90: Y | S90: Follow up | T90: Big on academics. Navy on the list, talking to Air Force. Circle back next week | U90: PBR Futures '27
A91: 45865 | B91: Futures | C91: TR | D91: Caden | E91: Christianson | F91: 27 RHP CO | G91: 2 | H91: Greenwood Village | I91: CO | J91: Mountain Vista | M91: =D91&" "&E91 -> Caden Christianson | N91: 352-657-0093 | O91: {=XLOOKUP(M91,'Recruiting Form Responses'!C:C,'Recruiting Form Responses'!A:A,"",0,1)} | U91: PBR Futures '27
A92: 45865 | B92: Futures | C92: CB | D92: Mason | E92: Meyer | F92: 27 C IN | G92: 1 | H92: Indianapolis | I92: IN | J92: Mt Vernon | L92: 4 | M92: =D92&" "&E92 -> Mason Meyer | N92: 317-453-5676 | O92: {=XLOOKUP(M92,'Recruiting Form Responses'!C:C,'Recruiting Form Responses'!A:A,"",0,1)} | U92: PBR Futures '27
A93: 45865 | B93: Futures | C93: TR | D93: Carson | E93: Richter | F93: 27 OF CA | G93: 1 | H93: Newbury Park | I93: CA | J93: Newbury Park | M93: =D93&" "&E93 -> Carson Richter | N93: 805-368-4166 | O93: {=XLOOKUP(M93,'Recruiting Form Responses'!C:C,'Recruiting Form Responses'!A:A,"",0,1)} | U93: PBR Futures '27
A94: 45865 | B94: Futures | C94: CB | D94: Parker | E94: Vandercook | F94: 27 RHP TN | G94: 1 | H94: Nolensville | I94: TN | J94: Nolensville | M94: =D94&" "&E94 -> Parker Vandercook | N94: 331-442-9901 | O94: {=XLOOKUP(M94,'Recruiting Form Responses'!C:C,'Recruiting Form Responses'!A:A,"",0,1)} | U94: PBR Futures '27
A95: 45865 | B95: Futures | C95: TR | D95: Zion | E95: Martinez | F95: 27 SS CA | G95: 1 | H95: Yucaipa | I95: CA | J95: Norco | L95: 4.3 | M95: =D95&" "&E95 -> Zion Martinez | N95: 909-723-6176 | O95: {=XLOOKUP(M95,'Recruiting Form Responses'!C:C,'Recruiting Form Responses'!A:A,"",0,1)} -> XX | Q95: Y | T95: Have talked twice. Saying he wants to visit, sent dates. Not sure this will materialize | U95: PBR Futures '27
A96: 45865 | B96: Futures | C96: CB | D96: JJ | E96: Mancuso | F96: 27 COF PA | G96: 2 | H96: Bradfordwoods | I96: PA | J96: North Allegheny (PA) | L96: 3.8 | M96: =D96&" "&E96 -> JJ Mancuso | N96: 412-526-6676 | O96: {=XLOOKUP(M96,'Recruiting Form Responses'!C:C,'Recruiting Form Responses'!A:A,"",0,1)} -> XX | Q96: Y | S96: 45869.792 | T96: Friends with Posey, grandfather in navy. Great talk. | U96: PBR Futures '27
A97: 45865 | B97: Futures | C97: CB | D97: Carson | E97: Bruce | F97: 27 OF GA | G97: 1 | H97: Powder Springs | I97: GA | J97: North Cobb Christian (GA) | L97: 4 | M97: =D97&" "&E97 -> Carson Bruce | N97: 980-829-4226 | O97: {=XLOOKUP(M97,'Recruiting Form Responses'!C:C,'Recruiting Form Responses'!A:A,"",0,1)} -> XX | Q97: Y | S97: Follow up | T97: Grandfathers both in the Navy, has talked to Air Force. Interested. Circle back next week. | U97: PBR Futures '27
A98: 45865 | B98: Futures | C98: AP | D98: Austin | E98: Kightlinger | F98: 27 INF AL | G98: 1 | H98: Northport | I98: AL | J98: Northside | L98: 3.87 | M98: =D98&" "&E98 -> Austin Kightlinger | N98: 205-650-2213 | O98: {=XLOOKUP(M98,'Recruiting Form Responses'!C:C,'Recruiting Form Responses'!A:A,"",0,1)} | U98: PBR Futures '27
A99: 45865 | B99: Futures | C99: CB | D99: Jameson | E99: Moan | F99: 27 C FL | G99: 1 | H99: Saint Petersburg | I99: FL | J99: Northside Christian (FL) | M99: =D99&" "&E99 -> Jameson Moan | N99: 727-643-4923 | O99: {=XLOOKUP(M99,'Recruiting Form Responses'!C:C,'Recruiting Form Responses'!A:A,"",0,1)} -> XX | Q99: Y | S99: Follow up | T99: Medium interest doesn't know anything about us. Follow up next week. | U99: PBR Futures '27
B100: This Summer | C100: AP | D100: Jeter | E100: Farina | F100: 27 SS FL | G100: 1 | I100: FL | J100: Oakleaf HS | K100: Orlando Scorpions | L100: 3.9 | M100: =D100&" "&E100 -> Jeter Farina | N100: 904-449-1072 | O100: {=XLOOKUP(M100,'Recruiting Form Responses'!C:C,'Recruiting Form Responses'!A:A,"",0,1)}
...

Sheet Fall Visit Dates 2025
B1: Sept 13 [No Football] | C1: Sept 20 [No Football] | D1: Sept 27 Rice | E1: Oct 4 Air Force | F1: Oct 11 [No Football] | G1: 45948 | H1: Oct 25 FAU | I1: Nov 1 [No Football] | J1: Nov 8 [No Football] | K1: Nov 15 USF | L1: Nov 22 [No Football] | M1: Dec 6 [No Football] | N1: 45673
A2: Caleb Flannery '27 C PA | D2: Lincoln Norris '27 SS IA | E2: Connor Brooks '27 RHP SC | G2: NAVY CAMP | H2: Ryker Mahnke '27 OF KS | I2: Garrett Koshkin '26 RHP | J2: ND Weekend | K2: Jack Tarbox '27 SS MA | L2: George Minjack '27 INF DC | M2: Matthew Gorman '27 LHP NE | N2: Jackson Phillips '27 RHP CO
A3: Ethan Wisler '27 P NC | D3: Sam Pearson '27 SS KY | E3: Conor Secrist '26 SS MA | G3: Mikah Krystofolski '27 RHP MA | H3: Nick Malinowski '27 RHP NJ | K3: Jack Van Gemert '27 RHP MN | L3: Braden Mackay '27 INF FL | N3: Kolby Crosby '27 RHP NY
D4: Lincoln Eure '27 RHP UT | E4: Hawk Stickney '26 RHP MA | H4: Zach Madar '27 SS TN | N4: Jude Davidson '27 RHP AL
D5: Tyler Reeder '26 RHP FL | E5: Stevie Wellens '27 SS CA | H5: Owen Shirey '27 SS SC
D6: Nixon Warren '27 CF UT | E6: Hummel 3 tickets | H6: Eli Cash '27 RHP NC
H7: Santiago Arismendi '26 RHP ITL | K7: Mateu Dalmau 5 tickets
A17: ARMS
A18: No Action
A19: Received OV Survey
A20: Flight Purchased
A21: Itinerary Recieved
A22: Pre Visit Form - Completed
A23: Post Visit Form - Completed

Sheet Sheet13
C1: First | D1: Last | E1: Class | F1: Rank | H1: Navy Pos | I1: Pos2 | J1: B/T | K1: City | L1: St | M1: School | O1: GPA | Q1: Phone | S1: Twitter
A2: {=XLOOKUP(B2,'High School Players'!D:D,'High School Players'!K:K,"",0,1)} -> 0.1 | B2: Caleb Flannery | C2: Caleb | D2: Flannery | E2: 2027 | F2: 0.1 | H2: C | I2: 9 | J2: R/R | K2: Broomall | L2: PA | M2: Devon Preparatory School (PA) | Q2: 267-252-9630 | S2: C_Flannery2027
A3: {=XLOOKUP(B3,'High School Players'!D:D,'High School Players'!K:K,"",0,1)} -> 2 | B3: Eli Quinley | C3: Eli | D3: Quinley | E3: 2027 | F3: 1 | H3: 3B | J3: R/R | K3: Mobile | L3: AL | M3: Faith Academy | O3: 4.57 | Q3: 251-895-6167 | R3: PBR Futures '27 | S3: Eli_quinley
A4: {=XLOOKUP(B4,'High School Players'!D:D,'High School Players'!K:K,"",0,1)} -> XX | B4: Austin Kightlinger | C4: Austin | D4: Kightlinger | E4: 2027 | F4: 1 | H4: INF | J4: L/R | K4: Northport | L4: AL | M4: Northside | O4: 3.87 | Q4: 205-650-2213 | R4: PBR Futures '27 | S4: A_Kightlinger99
A5: {=XLOOKUP(B5,'High School Players'!D:D,'High School Players'!K:K,"",0,1)} -> XX | B5: Brady Sack | C5: Brady | D5: Sack | E5: 2027 | F5: 1 | H5: RHP | J5: R/R | K5: Auburn | L5: AL | M5: Auburn | O5: 3.87 | Q5: 334-329-2111 | R5: PBR Futures '27 | S5: Brady_Sack
A6: {=XLOOKUP(B6,'High School Players'!D:D,'High School Players'!K:K,"",0,1)} -> 0.1 | B6: Jude Davidson | C6: Jude | D6: Davidson | E6: 2027 | F6: 1 | H6: RHP | J6: R/R | K6: Mountain Brook | L6: AL | M6: Mountain Brook | O6: 4.6 | Q6: 205-922-1753 | R6: PBR Futures '27
A7: {=XLOOKUP(B7,'High School Players'!D:D,'High School Players'!K:K,"",0,1)} -> XX | B7: Connor Greb | C7: Connor | D7: Greb | E7: 2027 | F7: 1 | H7: 3B | J7: L/R | K7: Birmingham | L7: AL | M7: Spain Park | O7: 4 | Q7: 205-983-2183 | R7: PBR Futures '27 | S7: connor_greb_3
A8: {=XLOOKUP(B8,'High School Players'!D:D,'High School Players'!K:K,"",0,1)} -> XX | B8: Ty McGinley | C8: Ty | D8: McGinley | E8: 2027 | F8: 1 | H8: RHP | J8: R/R | K8: Fairhope | L8: AL | M8: Fairhope | O8: 3.8 | Q8: 251-923-9916 | R8: PBR Futures '27 | S8: TyMcginley
A9: {=XLOOKUP(B9,'High School Players'!D:D,'High School Players'!K:K,"",0,1)} -> XX | B9: Boston Brown | C9: Boston | D9: Brown | E9: 2027 | F9: 1 | H9: RHP | J9: R/R | K9: Phenix City | L9: AL | M9: Lakeside | O9: 4.2 | Q9: 706-442-8282 | R9: PBR Futures '27 | S9: BostonBrown24
A10: {=XLOOKUP(B10,'High School Players'!D:D,'High School Players'!K:K,"",0,1)} -> XX | B10: Grady Openden | C10: Grady | D10: Openden | E10: 2027 | F10: 1 | H10: RHP | J10: R/R | K10: Phoenix | L10: AZ | M10: Brophy Prep | O10: 3.77 | Q10: 602-413-4603 | R10: PBR Futures '27 | S10: grady_openden
A11: {=XLOOKUP(B11,'High School Players'!D:D,'High School Players'!K:K,"",0,1)} -> 0.1 | B11: Stevie Wellens | C11: Stevie | D11: Wellens | E11: 2027 | F11: 1 | H11: MINF | J11: R/R | K11: Brentwood | L11: CA | M11: Liberty | O11: 4 | Q11: 925-357-5516 | R11: PBR Futures '27 | S11: StevieWellens16
A12: {=XLOOKUP(B12,'High School Players'!D:D,'High School Players'!K:K,"",0,1)} -> XX | B12: Colton Hadfield | C12: Colton | D12: Hadfield | E12: 2027 | F12: 1 | H12: SS | J12: R/R | K12: Newark | L12: CA | M12: Valley Christian San Jose | O12: 4 | Q12: 510-320-6479 | R12: PBR Futures '27 | S12: Colton_Hadfield
A13: {=XLOOKUP(B13,'High School Players'!D:D,'High School Players'!K:K,"",0,1)} -> XX | B13: Mariano Gonzalez | C13: Mariano | D13: Gonzalez | E13: 2027 | F13: 1 | H13: LHP | J13: L/L | K13: Fairfield | L13: CA | M13: Vanden | Q13: 707-426-2124 | R13: PBR Futures '27 | S13: Mariano_Gonzo22
A14: {=XLOOKUP(B14,'High School Players'!D:D,'High School Players'!K:K,"",0,1)} -> XX | B14: Vinny Boatwright | C14: Vinny | D14: Boatwright | E14: 2027 | F14: 1 | H14: RHP | J14: R/R | K14: Chico | L14: CA | M14: Chico | R14: PBR Futures '27
A15: {=XLOOKUP(B15,'High School Players'!D:D,'High School Players'!K:K,"",0,1)} -> XX | B15: Zion Martinez | C15: Zion | D15: Martinez | E15: 2027 | F15: 1 | H15: SS | J15: L/R | K15: Yucaipa | L15: CA | M15: Norco | O15: 4.3 | Q15: 909-723-6176 | R15: PBR Futures '27 | S15: zion_24_
A16: {=XLOOKUP(B16,'High School Players'!D:D,'High School Players'!K:K,"",0,1)} -> 1 | B16: Luke Bacon | C16: Luke | D16: Bacon | E16: 2027 | F16: 1 | H16: C | J16: L/R | K16: Riverside | L16: CA | M16: Santiago | O16: 4.25 | Q16: 951-481-9016 | R16: PBR Futures '27 | S16: lukebacon_8
A17: {=XLOOKUP(B17,'High School Players'!D:D,'High School Players'!K:K,"",0,1)} -> XX | B17: Joseph Flores Jr. | C17: Joseph | D17: Flores Jr. | E17: 2027 | F17: 1 | H17: SS | J17: R/R | K17: Riverside | L17: CA | M17: Arlington | O17: 4.2 | Q17: 951-205-9701 | R17: PBR Futures '27 | S17: JosephFloresJr
A18: {=XLOOKUP(B18,'High School Players'!D:D,'High School Players'!K:K,"",0,1)} -> XX | B18: Parker Leoff | C18: Parker | D18: Leoff | E18: 2027 | F18: 1 | H18: SS | J18: L/R | K18: Redondo Beach | L18: CA | M18: Huntington Beach | Q18: 310-922-6369 | R18: PBR Futures '27 | S18: leoff_parker
A19: {=XLOOKUP(B19,'High School Players'!D:D,'High School Players'!K:K,"",0,1)} -> XX | B19: Jonah Cohen | C19: Jonah | D19: Cohen | E19: 2027 | F19: 1 | H19: RHP | J19: R/R | K19: Palos Verdes Estates | L19: CA | M19: Palos Verdes | O19: 3.7 | Q19: 424-445-8956 | R19: PBR Futures '27 | S19: Jonah_Cohen4
A20: {=XLOOKUP(B20,'High School Players'!D:D,'High School Players'!K:K,"",0,1)} -> XX | B20: Carson Richter | C20: Carson | D20: Richter | E20: 2027 | F20: 1 | H20: OF | J20: R/R | K20: Newbury Park | L20: CA | M20: Newbury Park | Q20: 805-368-4166 | R20: PBR Futures '27 | S20: CRichter2027
A21: {=XLOOKUP(B21,'High School Players'!D:D,'High School Players'!K:K,"",0,1)} -> XX | B21: Andrew Weber | C21: Andrew | D21: Weber | E21: 2027 | F21: 1 | H21: RHP | J21: R/R | K21: San Bernardino | L21: CA | M21: Upland | O21: 4 | Q21: 909-642-5322 | R21: PBR Futures '27 | S21: weber2027
A22: {=XLOOKUP(B22,'High School Players'!D:D,'High School Players'!K:K,"",0,1)} -> XX | B22: Jackson Bernosky | C22: Jackson | D22: Bernosky | E22: 2027 | F22: 1 | H22: 3B | J22: R/R | K22: Aurora | L22: CO | M22: Regis Jesuit | O22: 3.75 | Q22: 720-759-8290 | R22: PBR Futures '27 | S22: JacksonBernosky
A23: {=XLOOKUP(B23,'High School Players'!D:D,'High School Players'!K:K,"",0,1)} -> XX | B23: Jackson Shepherd | C23: Jackson | D23: Shepherd | E23: 2027 | F23: 1 | H23: 3B | J23: R/R | K23: Superior | L23: CO | M23: Broomfield | Q23: 720-990-3199 | R23: PBR Futures '27 | S23: jacksonjace16
A24: {=XLOOKUP(B24,'High School Players'!D:D,'High School Players'!K:K,"",0,1)} -> XX | B24: Isaac Lockwood | C24: Isaac | D24: Lockwood | E24: 2027 | F24: 1 | H24: RHP | J24: R/R | K24: Mead | L24: CO | M24: Mead | Q24: 720-724-0474 | R24: PBR Futures '27 | S24: IsaacL738720
A25: {=XLOOKUP(B25,'High School Players'!D:D,'High School Players'!K:K,"",0,1)} -> XX | B25: Jake Watts | C25: Jake | D25: Watts | E25: 2027 | F25: 1 | H25: RHP | J25: R/R | K25: Arvada | L25: CO | M25: Ralston Valley | O25: 3.8 | Q25: 720-592-7537 | R25: PBR Futures '27
A26: {=XLOOKUP(B26,'High School Players'!D:D,'High School Players'!K:K,"",0,1)} -> XX | B26: Jackson Phillips | C26: Jackson | D26: Phillips | E26: 2027 | F26: 1 | H26: RHP | J26: R/R | K26: Parker | L26: CO | M26: Ponderosa | O26: 3.9 | Q26: 720-900-7224 | R26: PBR Futures '27 | S26: JacksonPhiLL22
A27: {=XLOOKUP(B27,'High School Players'!D:D,'High School Players'!K:K,"",0,1)} -> XX | B27: Jackson Crawford | C27: Jackson | D27: Crawford | E27: 2027 | F27: 1 | H27: OF | J27: L/L | K27: Highlands Ranch | L27: CO | M27: Mountain Vista | O27: 3.8 | Q27: 303-579-8413 | R27: PBR Futures '27 | S27: JacksonCraw2027
A28: {=XLOOKUP(B28,'High School Players'!D:D,'High School Players'!K:K,"",0,1)} -> XX | B28: Ryan Neumann | C28: Ryan | D28: Neumann | E28: 2027 | F28: 1 | H28: RHP | J28: R/R | K28: Cherry Hills Village | L28: CO | M28: Regis Jesuit | O28: 3.9 | Q28: 720-668-3728 | R28: PBR Futures '27 | S28: NeumannRy14
A29: {=XLOOKUP(B29,'High School Players'!D:D,'High School Players'!K:K,"",0,1)} -> XX | B29: Jacob Budarz | C29: Jacob | D29: Budarz | E29: 2027 | F29: 1 | H29: OF | I29: 16 | J29: R/R | K29: Manchester | L29: CT | M29: The Loomis Chaffee School | O29: 3.7 | Q29: 959-217-8044 | S29: JacobBudarzz
A30: {=XLOOKUP(B30,'High School Players'!D:D,'High School Players'!K:K,"",0,1)} -> XX | B30: Evan Brand | C30: Evan | D30: Brand | E30: 2027 | F30: 1 | H30: 1B | I30: 10 | J30: S/R | K30: Acworth | L30: GA | M30: Kell | O30: 4.1 | Q30: 770-235-6962
A31: {=XLOOKUP(B31,'High School Players'!D:D,'High School Players'!K:K,"",0,1)} -> XX | B31: Andrew Talbert | C31: Andrew | D31: Talbert | E31: 2027 | F31: 1 | H31: CF | J31: R/R | K31: Byron | L31: IL | M31: Byron | O31: 4.5 | Q31: 815-990-5514 | R31: PBR Futures '27 | S31: andrewtalbert27
A32: {=XLOOKUP(B32,'High School Players'!D:D,'High School Players'!K:K,"",0,1)} -> XX | B32: Mason Meyer | C32: Mason | D32: Meyer | E32: 2027 | F32: 1 | H32: C | J32: R/R | K32: Indianapolis | L32: IN | M32: Mt Vernon | O32: 4 | Q32: 317-453-5676 | R32: PBR Futures '27 | S32: mason_meyer5
A33: {=XLOOKUP(B33,'High School Players'!D:D,'High School Players'!K:K,"",0,1)} -> XX | B33: Liam Delp | C33: Liam | D33: Delp | E33: 2027 | F33: 1 | H33: MINF | J33: R/R | K33: Bargersville | L33: IN | M33: Center Grove | O33: 3.7 | Q33: 719-338-0088 | R33: PBR Futures '27 | S33: liamdelp_
A34: {=XLOOKUP(B34,'High School Players'!D:D,'High School Players'!K:K,"",0,1)} -> XX | B34: Ryker Mahnke | C34: Ryker | D34: Mahnke | E34: 2027 | F34: 1 | H34: SS | I34: 2 | J34: L/R | K34: Lawrence | L34: KS | M34: Lawrence Free State | Q34: 785-766-3322 | S34: RykerMahnke2027
A35: {=XLOOKUP(B35,'High School Players'!D:D,'High School Players'!K:K,"",0,1)} -> XX | B35: Sam Pearson | C35: Sam | D35: Pearson | E35: 2027 | F35: 1 | H35: SS | J35: L/R | K35: Lexington | L35: KY | M35: Lexington Christian Academy | O35: 4 | Q35: 502-542-5318 | R35: PBR Futures '27 | S35: SamPearson1303
A36: {=XLOOKUP(B36,'High School Players'!D:D,'High School Players'!K:K,"",0,1)} -> XX | B36: Hudson Meredith | C36: Hudson | D36: Meredith | E36: 2027 | F36: 1 | H36: LHP | I36: 14 | J36: R/L | K36: Louisville | L36: KY | M36: Trinity | O36: 5.3 | Q36: 502-373-9275 | S36: hudsonmeredith_
A37: {=XLOOKUP(B37,'High School Players'!D:D,'High School Players'!K:K,"",0,1)} -> 2 | B37: Ari Wells | C37: Ari | D37: Wells | E37: 2027 | F37: 1 | H37: 1B | J37: L/L | K37: Princeton | L37: KY | M37: Caldwell County | O37: 4.3 | Q37: 270-963-3482 | R37: PBR Futures '27 | S37: AriWells22
A38: {=XLOOKUP(B38,'High School Players'!D:D,'High School Players'!K:K,"",0,1)} -> XX | B38: Hayden Henry | C38: Hayden | D38: Henry | E38: 2027 | F38: 1 | H38: RHP | J38: R/R | K38: Webster | L38: KY | M38: Breckinridge County | O38: 4 | Q38: 502-271-9652 | R38: PBR Futures '27 | S38: scout97386
A39: {=XLOOKUP(B39,'High School Players'!D:D,'High School Players'!K:K,"",0,1)} -> XX | B39: Keith Mitchell | C39: Keith | D39: Mitchell | E39: 2027 | F39: 1 | H39: OF | J39: R/R | K39: Lagrange | L39: KY | M39: South Oldham | O39: 4 | Q39: 502-755-9428 | R39: PBR Futures '27 | S39: Keith_wmitchell
A40: {=XLOOKUP(B40,'High School Players'!D:D,'High School Players'!K:K,"",0,1)} -> XX | B40: Brandon Emig | C40: Brandon | D40: Emig | E40: 2027 | F40: 1 | H40: RHP | J40: R/R | K40: Landenberg | L40: PA | M40: Salesianum (DE) | O40: 3.73 | Q40: 302-377-4804 | R40: PBR Futures '27 | S40: brandonemig27
A41: {=XLOOKUP(B41,'High School Players'!D:D,'High School Players'!K:K,"",0,1)} -> XX | B41: Judah Shirlen | C41: Judah | D41: Shirlen | E41: 2027 | F41: 1 | H41: SS | J41: R/R | K41: Severna Park | L41: MD | M41: Archbishop Spalding | O41: 3.8 | Q41: 443-340-3278 | R41: PBR Futures '27 | S41: judahshirlen
A42: {=XLOOKUP(B42,'High School Players'!D:D,'High School Players'!K:K,"",0,1)} -> 2 | B42: Cameron Aguilar | C42: Cameron | D42: Aguilar | E42: 2027 | F42: 1 | H42: OF | J42: R/R | K42: Ashland | L42: MA | M42: St Mark’s | O42: 3.95 | Q42: 774-217-4709 | R42: PBR Futures '27 | S42: camaguilar_4
A43: {=XLOOKUP(B43,'High School Players'!D:D,'High School Players'!K:K,"",0,1)} -> XX | B43: Lucas Sarno | C43: Lucas | D43: Sarno | E43: 2027 | F43: 1 | H43: SS | I43: 4 | J43: R/R | K43: Andover | L43: MA | M43: Austin Preperatory | O43: 3.8 | Q43: 978-409-9404 | S43: Lucas_Sarno33
A44: {=XLOOKUP(B44,'High School Players'!D:D,'High School Players'!K:K,"",0,1)} -> XX | B44: Patrick Bryan | C44: Patrick | D44: Bryan | E44: 2027 | F44: 1 | H44: C | I44: 7 | J44: S/R | K44: Quincy | L44: MA | M44: Dexter Southfield | Q44: 617-404-5342
A45: {=XLOOKUP(B45,'High School Players'!D:D,'High School Players'!K:K,"",0,1)} -> XX | B45: Jackson Fournier | C45: Jackson | D45: Fournier | E45: 2027 | F45: 1 | H45: OF | I45: 12 | J45: L/R | K45: Milford | L45: MA | M45: Saint John's Shrewsbury | O45: 3.68 | Q45: 508-341-4096 | S45: jaxfourn103
A46: {=XLOOKUP(B46,'High School Players'!D:D,'High School Players'!K:K,"",0,1)} -> XX | B46: Dylan Crowe | C46: Dylan | D46: Crowe | E46: 2027 | F46: 1 | H46: SS | J46: R/R | K46: Brighton | L46: MI | M46: Hartland | O46: 3.96 | Q46: 248-417-8452 | R46: PBR Futures '27 | S46: DylanCrowe02_
A47: {=XLOOKUP(B47,'High School Players'!D:D,'High School Players'!K:K,"",0,1)} -> XX | B47: Lincoln Norris | C47: Lincoln | D47: Norris | E47: 2027 | F47: 1 | H47: MINF | J47: R/R | K47: Knoxville | L47: IA | M47: Knoxville (IA) | O47: 4 | Q47: 641-205-9390 | R47: PBR Futures '27 | S47: LINCOLNNORRIS28
A48: {=XLOOKUP(B48,'High School Players'!D:D,'High School Players'!K:K,"",0,1)} -> XX | B48: Hunter Minner | C48: Hunter | D48: Minner | E48: 2027 | F48: 1 | H48: RHP | J48: R/R | K48: Ankeny | L48: IA | M48: Ankeny (IA) | O48: 4 | Q48: 515-210-1407 | R48: PBR Futures '27 | S48: Hunter_Minner
A49: {=XLOOKUP(B49,'High School Players'!D:D,'High School Players'!K:K,"",0,1)} -> XX | B49: Gerad Hanle | C49: Gerad | D49: Hanle | E49: 2027 | F49: 1 | H49: LHP | J49: L/L | K49: Clear lake | L49: MN | M49: Acellus (MN) | O49: 3.8 | Q49: 612-669-6747 | R49: PBR Futures '27 | S49: GeradHanle
A50: {=XLOOKUP(B50,'High School Players'!D:D,'High School Players'!K:K,"",0,1)} -> XX | B50: Alejandro Chavez | C50: Alejandro | D50: Chavez | E50: 2027 | F50: 1 | H50: SS | J50: R/R | K50: Brooklyn Park | L50: MN | M50: Osseo (MN) | O50: 3.92 | Q50: 612-850-9535 | R50: PBR Futures '27 | S50: AlexChavezAC21
A51: {=XLOOKUP(B51,'High School Players'!D:D,'High School Players'!K:K,"",0,1)} -> XX | B51: Cason Borchardt | C51: Cason | D51: Borchardt | E51: 2027 | F51: 1 | H51: OF | J51: L/L | K51: Horace | L51: ND | M51: Horace (ND) | O51: 3.8 | Q51: 701-306-4751 | R51: PBR Futures '27 | S51: cason_borchardt
A52: {=XLOOKUP(B52,'High School Players'!D:D,'High School Players'!K:K,"",0,1)} -> XX | B52: Ike Crouser | C52: Ike | D52: Crouser | E52: 2027 | F52: 1 | H52: RHP | J52: R/R | K52: Saint Paul | L52: MN | M52: Cretin (MN) | O52: 4.09 | Q52: 651-279-3977 | R52: PBR Futures '27 | S52: ike_crouser
A53: {=XLOOKUP(B53,'High School Players'!D:D,'High School Players'!K:K,"",0,1)} -> XX | B53: Gavin Griffin | C53: Gavin | D53: Griffin | E53: 2027 | F53: 1 | H53: OF | J53: R/R | K53: Battle Lake | L53: MN | M53: Perham (MN) | O53: 3.9 | Q53: 763-229-7969 | R53: PBR Futures '27 | S53: GGriffy5
A54: {=XLOOKUP(B54,'High School Players'!D:D,'High School Players'!K:K,"",0,1)} -> 2 | B54: Zachary DeHaas | C54: Zachary | D54: DeHaas | E54: 2027 | F54: 1 | H54: OF | J54: R/R | K54: Ashland | L54: MO | M54: Southern Boone | O54: 3.85 | Q54: 580-919-0620 | R54: PBR Futures '27 | S54: DeHaasZach24
A55: {=XLOOKUP(B55,'High School Players'!D:D,'High School Players'!K:K,"",0,1)} -> XX | B55: Parker Sansone | C55: Parker | D55: Sansone | E55: 2027 | F55: 1 | H55: RHP | J55: R/R | K55: Wentzville | L55: MO | M55: Timberland | O55: 4 | Q55: 636-459-5170 | R55: PBR Futures '27 | S55: ParkerSansone
A56: {=XLOOKUP(B56,'High School Players'!D:D,'High School Players'!K:K,"",0,1)} -> XX | B56: Rylan Sutton | C56: Rylan | D56: Sutton | E56: 2027 | F56: 1 | H56: OF/1B | J56: L/L | K56: Ozark | L56: MO | M56: Ozark | O56: 4.2 | Q56: 417-766-8235 | R56: PBR Futures '27 | S56: rylansutton2027
A57: {=XLOOKUP(B57,'High School Players'!D:D,'High School Players'!K:K,"",0,1)} -> XX | B57: Brady Yates | C57: Brady | D57: Yates | E57: 2027 | F57: 1 | H57: 3B | J57: R/R | K57: Springfield | L57: MO | M57: Glendale | O57: 4.25 | Q57: 417-371-8915 | R57: PBR Futures '27 | S57: BradyYates8
A58: {=XLOOKUP(B58,'High School Players'!D:D,'High School Players'!K:K,"",0,1)} -> XX | B58: Justin Rodrigues | C58: Justin | D58: Rodrigues | E58: 2027 | F58: 1 | H58: MINF | J58: R/R | K58: Las Vegas | L58: NV | M58: Bishop Gorman | O58: 4 | Q58: 702-480-7500 | R58: PBR Futures '27 | S58: Jrod_2027
A59: {=XLOOKUP(B59,'High School Players'!D:D,'High School Players'!K:K,"",0,1)} -> XX | B59: Curt Friedrich | C59: Curt | D59: Friedrich | E59: 2027 | F59: 1 | H59: OF | I59: LHP | J59: R/L | K59: Summit | L59: NJ | M59: Delbarton | O59: 3.9 | Q59: 646-887-7191 | R59: PBR Futures '27 | S59: curt_friedrich
A60: {=XLOOKUP(B60,'High School Players'!D:D,'High School Players'!K:K,"",0,1)} -> XX | B60: Kyle McBride | C60: Kyle | D60: McBride | E60: 2027 | F60: 1 | H60: RHP | I60: 11 | J60: R/R | K60: Clinton | L60: NJ | M60: Delbarton | Q60: 908-455-4292 | S60: 11_mcbride
A61: {=XLOOKUP(B61,'High School Players'!D:D,'High School Players'!K:K,"",0,1)} -> XX | B61: Ted Masino | C61: Ted | D61: Masino | E61: 2027 | F61: 1 | H61: RHP | J61: R/R | K61: Maplewood | L61: NJ | M61: Delbarton | O61: 4.1 | Q61: 973-768-7392 | R61: PBR Futures '27 | S61: TedMasino
A62: {=XLOOKUP(B62,'High School Players'!D:D,'High School Players'!K:K,"",0,1)} -> XX | B62: Steven Pannullo | C62: Steven | D62: Pannullo | E62: 2027 | F62: 1 | H62: RHP | J62: R/R | K62: Essex Fells | L62: NJ | M62: Delbarton | O62: 3.6 | Q62: 201-755-6396 | R62: PBR Futures '27 | S62: PannulloSteven
A63: {=XLOOKUP(B63,'High School Players'!D:D,'High School Players'!K:K,"",0,1)} -> XX | B63: Nick Malinowski | C63: Nick | D63: Malinowski | E63: 2027 | F63: 1 | H63: RHP | I63: 23 | J63: R/R | K63: Barnegat | L63: NJ | M63: Barnegat | Q63: 609-891-7759 | S63: nickmal2027
A64: {=XLOOKUP(B64,'High School Players'!D:D,'High School Players'!K:K,"",0,1)} -> XX | B64: Brady Palmer | C64: Brady | D64: Palmer | E64: 2027 | F64: 1 | H64: RHP | I64: 2 | J64: S/R | K64: Endwell | L64: NY | M64: Maine-Endwell | O64: 4 | Q64: 607-348-4519 | S64: Bradycpalmer
A65: {=XLOOKUP(B65,'High School Players'!D:D,'High School Players'!K:K,"",0,1)} -> 0.1 | B65: Kolby Crosby | C65: Kolby | D65: Crosby | E65: 2027 | F65: 1 | H65: RHP | I65: 7 | J65: R/R | K65: Staten Island | L65: NY | M65: Moore Catholic | O65: 4 | Q65: 347-659-4476 | S65: kolby_crosby
A66: {=XLOOKUP(B66,'High School Players'!D:D,'High School Players'!K:K,"",0,1)} -> 2 | B66: Lucas Collure | C66: Lucas | D66: Collure | E66: 2027 | F66: 1 | H66: OF | J66: R/R | K66: Grand Island | L66: NY | M66: Grand Island | Q66: 716-435-8460 | R66: PBR Futures '27 | S66: LucasCollure
A67: {=XLOOKUP(B67,'High School Players'!D:D,'High School Players'!K:K,"",0,1)} -> XX | B67: Cooper Ball | C67: Cooper | D67: Ball | E67: 2027 | F67: 1 | H67: RHP | I67: 17 | J67: R/R | K67: Horseheads | L67: NY | M67: Horseheads | O67: 4 | Q67: 910-742-3327 | S67: CooperBall44
A68: {=XLOOKUP(B68,'High School Players'!D:D,'High School Players'!K:K,"",0,1)} -> 1 | B68: Parker Filipek | C68: Parker | D68: Filipek | E68: 2027 | F68: 1 | H68: C | J68: L/R | K68: Arden | L68: NC | M68: TC Roberson | O68: 4 | Q68: 828-676-5114 | R68: PBR Futures '27 | S68: @parker_filipek
A69: {=XLOOKUP(B69,'High School Players'!D:D,'High School Players'!K:K,"",0,1)} -> XX | B69: Trevor Yancey | C69: Trevor | D69: Yancey | E69: 2027 | F69: 1 | H69: RHP | J69: R/R | K69: Charlotte | L69: NC | M69: Providence Day School | O69: 3.6 | Q69: 619-813-9071 | R69: PBR Futures '27 | S69: TrevorYancey_3
A70: {=XLOOKUP(B70,'High School Players'!D:D,'High School Players'!K:K,"",0,1)} -> XX | B70: Wyatt Lytle | C70: Wyatt | D70: Lytle | E70: 2027 | F70: 1 | H70: COF | J70: R/R | K70: Apex | L70: NC | M70: Pro5 Academy | O70: 3.7 | Q70: 984-999-5751 | R70: PBR Futures '27 | S70: wyattlytle27
A71: {=XLOOKUP(B71,'High School Players'!D:D,'High School Players'!K:K,"",0,1)} -> XX | B71: Ryan Younglas | C71: Ryan | D71: Younglas | E71: 2027 | F71: 1 | H71: 3B | J71: L/R | K71: Wellington | L71: OH | M71: Keystone | Q71: 440-420-8186 | R71: PBR Futures '27 | S71: ryan_younglas
A72: {=XLOOKUP(B72,'High School Players'!D:D,'High School Players'!K:K,"",0,1)} -> XX | B72: Koby Dues | C72: Koby | D72: Dues | E72: 2027 | F72: 1 | H72: SS | J72: R/R | K72: Dayton | L72: OH | M72: Vandalia Butler | O72: 4 | Q72: 937-750-3091 | R72: PBR Futures '27 | S72: Kobydues
A73: {=XLOOKUP(B73,'High School Players'!D:D,'High School Players'!K:K,"",0,1)} -> XX | B73: Jackson Schilling | C73: Jackson | D73: Schilling | E73: 2027 | F73: 1 | H73: C | J73: R/R | K73: Vandalia | L73: OH | M73: Butler High School | O73: 3.8 | Q73: 937-605-2868 | R73: PBR Futures '27 | S73: j_schill2027
A74: {=XLOOKUP(B74,'High School Players'!D:D,'High School Players'!K:K,"",0,1)} -> XX | B74: Pete Browand | C74: Pete | D74: Browand | E74: 2027 | F74: 1 | H74: C | J74: R/R | K74: Gig Harbor | L74: WA | M74: Peninsula (WA) | O74: 3.99 | Q74: 253-223-1043 | R74: PBR Futures '27 | S74: petebrowand2027
A75: {=XLOOKUP(B75,'High School Players'!D:D,'High School Players'!K:K,"",0,1)} -> XX | B75: Cooper McGowan | C75: Cooper | D75: McGowan | E75: 2027 | F75: 1 | H75: SS | J75: R/R | K75: Battle Ground | L75: WA | M75: Battle Ground (WA) | O75: 3.8 | Q75: 360-667-8091 | R75: PBR Futures '27 | S75: 22_cooper_
A76: {=XLOOKUP(B76,'High School Players'!D:D,'High School Players'!K:K,"",0,1)} -> XX | B76: Troy Stimpson | C76: Troy | D76: Stimpson | E76: 2027 | F76: 1 | H76: C | J76: R/R | K76: Canonsburg | L76: PA | M76: Canon-Mcmillan | O76: 4.3 | Q76: 412-506-1154 | R76: PBR Futures '27 | S76: stimpson_troy
A77: {=XLOOKUP(B77,'High School Players'!D:D,'High School Players'!K:K,"",0,1)} -> XX | B77: Hunter West | C77: Hunter | D77: West | E77: 2027 | F77: 1 | H77: RHP | J77: R/R | K77: West Chester | L77: PA | M77: The Episcopal Academy | O77: 3.8 | Q77: 610-545-9537 | R77: PBR Futures '27 | S77: 17hunterwest
A78: {=XLOOKUP(B78,'High School Players'!D:D,'High School Players'!K:K,"",0,1)} -> XX | B78: Freddy Corrado | C78: Freddy | D78: Corrado | E78: 2027 | F78: 1 | H78: RHP | J78: R/R | K78: Hazle Township | L78: PA | M78: Hazleton Area | O78: 4 | Q78: 570-599-7516 | R78: PBR Futures '27 | S78: Freddy_Corrado1
A79: {=XLOOKUP(B79,'High School Players'!D:D,'High School Players'!K:K,"",0,1)} -> XX | B79: Jake Lopez | C79: Jake | D79: Lopez | E79: 2027 | F79: 1 | H79: SS | J79: R/R | K79: Broken Arrow | L79: OK | M79: Broken Arrow (OK) | O79: 3.6 | Q79: 760-694-5576 | R79: PBR Futures '27 | S79: Jake__Lopez__2
A80: {=XLOOKUP(B80,'High School Players'!D:D,'High School Players'!K:K,"",0,1)} -> XX | B80: Quinn Rooney | C80: Quinn | D80: Rooney | E80: 2027 | F80: 1 | H80: 1B/OF/LHP | I80: 20 | J80: L/L | K80: Hinsdale | L80: IL | M80: Benet Academy (IL) | Q80: 206-660-5313 | S80: QuinnRooney3
A81: {=XLOOKUP(B81,'High School Players'!D:D,'High School Players'!K:K,"",0,1)} -> XX | B81: Mac Morris | C81: Mac | D81: Morris | E81: 2027 | F81: 1 | H81: INF | J81: R/R | K81: Taylors | L81: SC | M81: Baylor | Q81: 864-999-0942 | R81: PBR Futures '27 | S81: macmorris152
A82: {=XLOOKUP(B82,'High School Players'!D:D,'High School Players'!K:K,"",0,1)} -> XX | B82: Connor Wells | C82: Connor | D82: Wells | E82: 2027 | F82: 1 | H82: LHP | J82: L/L | K82: Spartanburg | L82: SC | M82: Dorman | Q82: 864-327-6853 | R82: PBR Futures '27 | S82: connorwells012
A83: {=XLOOKUP(B83,'High School Players'!D:D,'High School Players'!K:K,"",0,1)} -> XX | B83: Luke Winbush | C83: Luke | D83: Winbush | E83: 2027 | F83: 1 | H83: SS | J83: R/R | K83: Marietta | L83: GA | M83: Pope (GA) | O83: 4.46 | Q83: 678-507-8551 | R83: PBR Futures '27 | S83: Lukewinbush
A84: {=XLOOKUP(B84,'High School Players'!D:D,'High School Players'!K:K,"",0,1)} -> XX | B84: Brody Baxmann | C84: Brody | D84: Baxmann | E84: 2027 | F84: 1 | H84: OF | J84: L/R | K84: Fort myers | L84: FL | M84: Bishop Verot (FL) | O84: 3.9 | Q84: 239-671-0473 | R84: PBR Futures '27 | S84: brody_baxmann
A85: {=XLOOKUP(B85,'High School Players'!D:D,'High School Players'!K:K,"",0,1)} -> XX | B85: Vaughn Howard | C85: Vaughn | D85: Howard | E85: 2027 | F85: 1 | H85: SS | J85: R/R | K85: Santa Rosa Beach | L85: FL | M85: South Walton (FL) | O85: 4 | Q85: 850-686-7882 | R85: PBR Futures '27 | S85: VaughnHoward27
A86: {=XLOOKUP(B86,'High School Players'!D:D,'High School Players'!K:K,"",0,1)} -> XX | B86: Jameson Moan | C86: Jameson | D86: Moan | E86: 2027 | F86: 1 | H86: C | J86: R/R | K86: Saint Petersburg | L86: FL | M86: Northside Christian (FL) | Q86: 727-643-4923 | R86: PBR Futures '27 | S86: JamesonMoan
A87: {=XLOOKUP(B87,'High School Players'!D:D,'High School Players'!K:K,"",0,1)} -> XX | B87: Angelo Geraldo | C87: Angelo | D87: Geraldo | E87: 2027 | F87: 1 | H87: 3B | J87: R/R | K87: Miami | L87: FL | M87: American Heritage (Plantation) (FL) | O87: 3.8 | Q87: 305-815-4607 | R87: PBR Futures '27 | S87: AngeloGeraldo6
A88: {=XLOOKUP(B88,'High School Players'!D:D,'High School Players'!K:K,"",0,1)} -> XX | B88: Parker Vandercook | C88: Parker | D88: Vandercook | E88: 2027 | F88: 1 | H88: RHP | J88: R/R | K88: Nolensville | L88: TN | M88: Nolensville | Q88: 331-442-9901 | R88: PBR Futures '27
A89: {=XLOOKUP(B89,'High School Players'!D:D,'High School Players'!K:K,"",0,1)} -> XX | B89: Kenson Buth | C89: Kenson | D89: Buth | E89: 2027 | F89: 1 | H89: SS | J89: L/R | K89: trophy club | L89: TX | M89: Byron Nelson | O89: 4 | Q89: 817-917-2186 | R89: PBR Futures '27 | S89: kbuth29
A90: {=XLOOKUP(B90,'High School Players'!D:D,'High School Players'!K:K,"",0,1)} -> XX | B90: Drew Cross | C90: Drew | D90: Cross | E90: 2027 | F90: 1 | H90: C | J90: R/R | K90: Mount Pleasant | L90: TX | M90: Mount Pleasant | O90: 4 | Q90: 903-285-0299 | R90: PBR Futures '27 | S90: drew10cross
A91: {=XLOOKUP(B91,'High School Players'!D:D,'High School Players'!K:K,"",0,1)} -> XX | B91: Grant Stafford | C91: Grant | D91: Stafford | E91: 2027 | F91: 1 | H91: SS | J91: L/R | K91: Lufkin | L91: TX | M91: Lufkin | Q91: 936-208-1965 | R91: PBR Futures '27 | S91: GrantStafford14
A92: {=XLOOKUP(B92,'High School Players'!D:D,'High School Players'!K:K,"",0,1)} -> XX | B92: Caden Mackey | C92: Caden | D92: Mackey | E92: 2027 | F92: 1 | H92: LHP | J92: R/L | K92: Southlake | L92: TX | M92: Southlake Carroll | Q92: 682-360-8826 | R92: PBR Futures '27 | S92: CadenMackey2027
A93: {=XLOOKUP(B93,'High School Players'!D:D,'High School Players'!K:K,"",0,1)} -> XX | B93: Jake Ivey | C93: Jake | D93: Ivey | E93: 2027 | F93: 1 | H93: LHP | J93: L/L | K93: Gunter | L93: TX | M93: Gunter | Q93: 469-858-1768 | R93: PBR Futures '27 | S93: ivey_jake22
A94: {=XLOOKUP(B94,'High School Players'!D:D,'High School Players'!K:K,"",0,1)} -> XX | B94: George Ferguson | C94: George | D94: Ferguson | E94: 2027 | F94: 1 | H94: RHP | J94: R/R | K94: Abilene | L94: TX | M94: Abilene | Q94: 325-665-7151 | R94: PBR Futures '27 | S94: GeorgeFerg2027
A95: {=XLOOKUP(B95,'High School Players'!D:D,'High School Players'!K:K,"",0,1)} -> XX | B95: Hudson Cuevas | C95: Hudson | D95: Cuevas | E95: 2027 | F95: 1 | H95: SS | J95: R/R | K95: Cedar Park | L95: TX | M95: Cedar Park | O95: 5.3 | Q95: 512-969-9940 | R95: PBR Futures '27 | S95: hudsoncuevas24
A96: {=XLOOKUP(B96,'High School Players'!D:D,'High School Players'!K:K,"",0,1)} -> XX | B96: Jacob Lessman | C96: Jacob | D96: Lessman | E96: 2027 | F96: 1 | H96: RHP | J96: R/R | K96: Whitney | L96: TX | M96: China Spring | O96: 3.7 | Q96: 254-855-6997 | R96: PBR Futures '27 | S96: jacob_lessman
A97: {=XLOOKUP(B97,'High School Players'!D:D,'High School Players'!K:K,"",0,1)} -> XX | B97: Lubin Rincon | C97: Lubin | D97: Rincon | E97: 2027 | F97: 1 | H97: SS | J97: L/R | K97: Pearland | L97: TX | M97: Shadow Creek | O97: 4 | Q97: 713-294-0312 | R97: PBR Futures '27
A98: {=XLOOKUP(B98,'High School Players'!D:D,'High School Players'!K:K,"",0,1)} -> XX | B98: Hector Cadena | C98: Hector | D98: Cadena | E98: 2027 | F98: 1 | H98: CINF | J98: R/R | K98: Laredo | L98: TX | M98: United Highschool | O98: 4 | Q98: 956-744-9875 | R98: PBR Futures '27 | S98: cadena_hec8
A99: {=XLOOKUP(B99,'High School Players'!D:D,'High School Players'!K:K,"",0,1)} -> XX | B99: Max Mangum | C99: Max | D99: Mangum | E99: 2027 | F99: 1 | H99: RHP | J99: R/R | K99: East Bernard | L99: TX | M99: East Bernard | O99: 3.8 | Q99: 979-758-1047 | R99: PBR Futures '27 | S99: mmangum52_
A100: {=XLOOKUP(B100,'High School Players'!D:D,'High School Players'!K:K,"",0,1)} -> XX | B100: Lincoln Eure | C100: Lincoln | D100: Eure | E100: 2027 | F100: 1 | H100: RHP | I100: SS | J100: R/R | K100: Sandy | L100: UT | M100: Corner Canyon | O100: 3.98 | Q100: 801-949-7591 | R100: PBR Futures '27 | S100: EureLincoln_1
...

Sheet Sheet12
A1: First Name | B1: Last Name | D1: Class | F1: Tier | G1: ★ | H1: HT | I1: WT | K1: Pos | L1: POS2 | M1: B/T | R1: Hometown | S1: Hometown | T1: State | U1: High School | V1: Summer Team | X1: Seen
A9: George | B9: Willis | D9: 2026 | F9: 1 | G9: 1 | K9: C | L9: CINF | M9: R/R | T9: TX | U9: Lamar
A13: Cole | B13: Teltschik | D13: 2026 | F13: 1 | G13: 1 | K13: C | M13: R/R | S13: Colorado Springs | T13: CO | U13: Discovery Canyon Campus
A14: Martin | B14: Shelar | D14: 2026 | F14: 1 | G14: 1 | K14: COF | M14: R/R | T14: GA | U14: Marist
A15: Geno | B15: Goralski | D15: 2026 | F15: 1 | G15: 1 | K15: COF | L15: CF | M15: R/R | S15: Cumming | T15: GA | U15: Denmark
A16: Cruz | B16: Luna | D16: 2026 | F16: 1 | G16: 1 | K16: C | L16: COF | M16: L/R | S16: Crownsville | T16: MD | U16: Archbishop Spalding
A17: Carson | B17: Hart | D17: 2026 | F17: 1 | G17: 1 | K17: COF | L17: LHP | M17: L/L | S17: Mankato | T17: MN
A18: Chase | B18: Bagley | D18: 2026 | F18: 1 | G18: 1 | K18: C | L18: MINF | M18: L/R | S18: Whippany | T18: NJ | U18: Don Bosco Prep
A19: Mason | B19: Myers | D19: 2026 | F19: 1 | G19: 1 | K19: CF | L19: MINF | M19: L/R | S19: Gibbstown | T19: NJ | U19: Paul VI
A20: Keaton | B20: Bowers | D20: 2026 | F20: 1 | G20: 1 | K20: C | M20: L/R | S20: Hilliard Bradley | T20: OH
A21: Jake | B21: Earnest | D21: 2026 | F21: 1 | G21: 1 | K21: CF | M21: L/L | T21: TX | U21: Memorial
A22: Lash | B22: Henderson | D22: 2026 | F22: 1 | G22: 1 | K22: CF | M22: R/R | T22: TX | U22: Prestonwood Christian Academy
A23: Noah | B23: Sky Kranz | D23: 2026 | F23: 1 | G23: 1 | K23: 1B | M23: R/R | T23: VA
A24: Luke | B24: Severns | D24: 2026 | F24: 1 | G24: 1 | K24: C | M24: L/R | T24: CA | U24: Etiwanda High School | X24: Dude Day
A25: Peter | B25: Jackson | D25: 2026 | F25: 1 | G25: 1 | K25: RHP | M25: R/R | T25: CA | V25: Legacy Baseball | X25: Dude Day
A26: Brody | B26: Buoncristiani | D26: 2026 | F26: 1 | G26: 1 | K26: LHP | L26: 1B | M26: L/L | T26: CA | U26: Chino Hills | X26: So Cal Giants
A27: Cache | B27: Poulson | D27: 2026 | F27: 1 | G27: 1 | K27: C | M27: R/R | T27: UT | U27: American Fork | X27: Futures Games
A28: Cooper | B28: Summerlin | D28: 2026 | F28: 1 | G28: 1 | K28: LHP | M28: L/L | T28: NC | U28: Gaston Christian School | X28: Twitter
A29: Patrick | B29: Weaving | D29: 2026 | F29: 1 | G29: 1 | K29: LHP | M29: L/L | T29: CT | U29: Lakeview High | X29: Super17/Clubhouse
A30: Quinn | B30: Melson | D30: 2026 | F30: 1 | G30: 1 | K30: CF | L30: 1B | M30: L/R | T30: TX | U30: Lake Highlands | V30: Dallas Tigers | X30: Twitter
A31: Sergio | B31: Hernandez | D31: 2026 | F31: 1 | G31: 1 | K31: MINF | M31: R/R | T31: PA | U31: Monsignoor Banner | X31: WWBA Ft.
A32: Evan | B32: McElvain | D32: 2026 | F32: 1 | G32: 1 | K32: C | L32: CINF | M32: R/R | T32: TN | U32: Nolesville | X32: WWBA Ft.
A33: Brandt | B33: Johnson | D33: 2026 | F33: 1 | G33: 1 | K33: C | M33: L/R | T33: PA | U33: Northeastern HS | X33: WWBA Ft.
A34: Caden | B34: Schlotterbeck | D34: 2026 | F34: 1 | G34: 1 | K34: LHP | M34: L/L | T34: FL | U34: Calvary Christian | V34: Top Tier | X34: WWBA Ft.
A35: Brayden | B35: Charness | D35: 2026 | F35: 1 | G35: 1 | K35: LHP | M35: L/L | T35: CA | U35: Sierra Canyon | X35: Email
A36: Noah | B36: Darnell | D36: 2026 | F36: 1 | G36: 1 | K36: LHP | M36: L/L | T36: CA | U36: Santa Margarita | X36: Reco.
A37: Luke | B37: Young | D37: 2026 | F37: 1 | G37: 1 | K37: C | M37: R/R | T37: SC | U37: Clinton | V37: Canes South | X37: Futures
A38: Jacob | B38: Hunter | D38: 2026 | F38: 1 | G38: 1 | K38: CF | M38: L/R | S38: Monaca | T38: PA | U38: Central Valley | V38: Pittsburgh Diamond Dawgs | X38: Frank Mergliano reco.
A39: Bode | B39: Bromley | D39: 2026 | F39: 1 | G39: 1 | K39: 1B | L39: LHP | M39: L/L | T39: TX | U39: Lamar HS | V39: Off-Season Baseball | X39: Twitter/Phone
A40: Lawson | B40: Behan | D40: 2026 | F40: 1 | G40: 1 | K40: MINF | L40: RHP | M40: R/R | T40: TX | U40: Lamar HS | X40: Twitter/Phone
A41: Noah | B41: Kim | D41: 2026 | F41: 1 | G41: 1 | K41: CF | L41: COF | M41: R/R | T41: NY | U41: Chaminade | V41: East Coast Lumberjacks | X41: Pembroke Reco.
A42: Christopher | B42: McLaughlin | D42: 2026 | F42: 1 | G42: 1 | K42: CINF | L42: RHP | M42: R/R | T42: NY | U42: Christian Brothers Academy | V42: Allstars Academy | X42: D. Healy recommend.
A43: Cooper | B43: Russel | D43: 2026 | F43: 1 | G43: 1 | K43: MINF | M43: R/R | T43: OH | U43: Lakewood HS | X43: Patterson Reco.
A44: Hayden | B44: O | D44: 2026 | F44: 1 | G44: 1 | K44: RHP | L44: COF | M44: R/R | T44: TX | U44: Centenial HS | X44: CBA
A45: Chase | B45: Shollenberger | D45: 2026 | F45: 1 | G45: 1 | K45: RHP | L45: 1B | M45: L/R | T45: PA | U45: Easton | X45: Frank Cooney reco.
A46: Michael | B46: Chin | D46: 2026 | F46: 1 | G46: 1 | K46: C | M46: R/R | T46: TX | U46: Episcopal | V46: FTB Phillies Scout | X46: Jeff Burton rec.
A47: Heath | B47: Klingensmith | D47: 2026 | F47: 1 | G47: 1 | K47: RHP | M47: R/R | T47: NC | U47: North Stanly HS | X47: Josh Rudd
A48: Will | B48: Suslow | D48: 2026 | F48: 1 | G48: 1 | K48: CF | M48: R/R | T48: CA | U48: Marantha HS | V48: Legacy Baseball Group | X48: Scottie T./Dude Day
A49: Gordon | B49: Cozad | D49: 2026 | F49: 1 | G49: 1 | K49: MINF | M49: R/R | T49: VA | U49: Oakton HS | V49: Dirtbags | X49: Jeff Burton recommend.
A50: Tayegan | B50: Briskey | D50: 2026 | F50: 1 | G50: 1 | K50: CF | M50: R/R | T50: FL | U50: West Boca Raton HS
A51: Kaleb | B51: LaFavor | D51: 2026 | F51: 1 | G51: 1 | K51: RHP | M51: R/R | T51: IA | U51: Bishop Heelan | X51: Josh Rudd client
A52: Will | B52: Watson | D52: 2026 | F52: 1 | G52: 1 | K52: COF | L52: COF | M52: R/R | T52: SC | U52: Pinewood Prep | V52: Power Baseball | X52: Futures
A53: Charles | B53: Chappelle | D53: 2026 | F53: 1 | G53: 1 | K53: COF | L53: RHP | M53: R/R | T53: GA | U53: Dalton | V53: Georgia Jackets
A54: Christian | B54: Haupt | D54: 2027 | F54: 1 | G54: 1 | K54: LHP | L54: COF | M54: L/L | T54: CA | U54: Har-Ber High School | X54: Dude Day
A55: Gavin | B55: Williams | D55: 2027 | F55: 1 | G55: 1 | K55: MINF | L55: C | M55: S/R | T55: CA | U55: Garces Memorial | V55: So Cal Giants | X55: Dude Day
A56: Bear | B56: Calvo | D56: 2027 | F56: 1 | G56: 1 | K56: CINF | M56: R/R | T56: CA | U56: La Miranda | V56: East Cobb Astros | X56: Dude Day
A57: Zion | B57: Martinez | D57: 2027 | F57: 1 | G57: 1 | K57: MINF | M57: L/R | T57: CA | U57: Yocaipa | V57: So Cal Giants | X57: So Cal Giants
A58: Dezi | B58: Delgado | D58: 2027 | F58: 1 | G58: 1 | K58: C | L58: CINF | M58: L/R | T58: CA | U58: Sierra Canyon | V58: So Cal Giants | X58: So Cal Giants
A59: Michael | B59: Doherty | D59: 2027 | F59: 1 | G59: 1 | K59: LHP | L59: COF | M59: L/L | T59: MA | U59: Phillips Andover | V59: NEB | X59: Crimson Camp
A60: Max | B60: Boehm | D60: 2027 | F60: 1 | G60: 1 | K60: RHP | L60: CINF | M60: R/R | T60: MA | U60: Wellsley | V60: Nokona | X60: Crimson Camp
A61: Jack | B61: O'Grady | D61: 2027 | F61: 1 | G61: 1 | K61: RHP | M61: R/R | T61: MA | U61: Wellsley | V61: Nokona | X61: Crimson Camp
A62: Wells | B62: Cunningham | D62: 2027 | F62: 1 | G62: 1 | K62: CF | L62: CINF | M62: R/R | T62: NY | U62: Canterbury School | V62: Clubhouse CT | X62: Clubhouse Fall
A63: Kaiden | B63: McCarthy | D63: 2027 | F63: 1 | G63: 1 | K63: RHP | M63: R/R | T63: VT | U63: Vermont Academy | V63: Allstars Academy
A64: Gabriel | B64: Norman | D64: 2027 | F64: 1 | G64: 1 | K64: LHP | M64: L/L | S64: Melbourne | T64: FL | U64: Rockledge Senior | V64: Atlanta Braves Scout | X64: Twitter
A65: Anthony | B65: Iatarola | D65: 2027 | F65: 1 | G65: 1 | K65: LHP | S65: Lakeland | T65: FL | U65: George W. Jenkins | V65: Team Elite | X65: Twitter
A66: Curt | B66: Friedrich | D66: 2027 | F66: 1 | G66: 1 | K66: LHP | L66: COF | M66: L/R | T66: NJ | U66: Delbarton | V66: Artillery | X66: John Murphy reco.
A67: Jackson | B67: Hornick | D67: 2027 | F67: 1 | G67: 1 | K67: RHP | L67: COF | M67: R/R | T67: PA | U67: Central Bucks - West | V67: Diamond Jacks | X67: Twitter
A68: Malcolm | B68: Blaqman | D68: 2027 | F68: 1 | G68: 1 | K68: MINF | L68: RHP | M68: R/R | T68: MD | U68: Avalon HS | V68: Five Star National | X68: Twitter/Duke Camp
A69: Tyler | B69: Priest | D69: 2027 | F69: 1 | G69: 1 | K69: RHP | M69: R/R | T69: ME | U69: Old Town HS | V69: NEB | X69: Patterson Reco.
A70: Kyle | B70: McBride | D70: 2027 | F70: 1 | G70: 1 | K70: RHP | M70: R/R | T70: NJ | U70: Delbarton | V70: NJ Rising Rebels | X70: Garden State Games/Super17
A71: Wyatt | B71: Derose | D71: 2027 | F71: 1 | G71: 1 | K71: RHP | M71: R/R | T71: NY | U71: Poly Prep | V71: East Coast Ghost | X71: John Murphy rec.
A72: Patrick | B72: Bryan | D72: 2027 | F72: 1 | G72: 1 | K72: CINF | L72: RHP | M72: R/R | T72: MA | U72: Dexter Southfield | V72: MDB Knights | X72: HS Game
A73: Tyler | B73: Koski | D73: 2027 | F73: 1 | G73: 1 | K73: MINF | M73: R/R | T73: MA | U73: Dexter Southfield | V73: MDB Knights | X73: HS Game
A74: Cameron | B74: Aguilar | D74: 2027 | F74: 1 | G74: 1 | K74: CF | M74: R/R | T74: MA | U74: St. Marks School | V74: Nokona | X74: HS Game - KD
A75: Owen | B75: Burnes | D75: 2028 | F75: 1 | G75: 1 | K75: LHP | L75: CINF | M75: L/L | T75: MA | U75: Dexter Southfield | V75: Boston Prime | X75: HS Game
A76: Owen | B76: Burnes | D76: 2028 | F76: 1 | G76: 1 | K76: 1B | L76: LHP | M76: L/L | T76: MA | U76: Dexter Southfield | V76: Team Elite | X76: HS Game
A77: Rory | B77: Funke | D77: 2028 | F77: 1 | G77: 1 | K77: LHP | M77: L/L | T77: MA | U77: Dexter Southfield | V77: Team Elite | X77: HS Game
A78: Grady | B78: Tempesta | D78: 2028 | F78: 1 | G78: 1 | K78: MINF | M78: R/R | T78: MA | U78: Dexter Southfield | V78: GBG Northeast | X78: HS Game
A79: Jason | B79: Jutronich | D79: 2026 | F79: 1 | G79: 1 | K79: LHP | M79: L/L | T79: CA | U79: Torrey Pines | X79: Twitter
A80: Ben | B80: Burke | D80: 2026 | F80: 1 | G80: 1 | K80: LHP | M80: L/L | T80: FL | U80: Tampa Jesuit | X80: Twitter/Reco.
A81: Dylan | B81: Cunningham | D81: 2028 | F81: 1 | G81: 1 | K81: RHP | L81: CINF | M81: R/R | S81: Peabody | T81: MA | U81: Austin Prep | V81: Canes National | X81: HS Game
A83: Max | B83: Naantai-Vlahovich | D83: 2027 | F83: 1 | G83: 1 | K83: RHP | M83: R/R | T83: Canada | U83: Missepequa | V83: Ontario Blue Jays | X83: Luca A. Reco.
A84: Luca | B84: Marucci | D84: 2026 | F84: 1 | G84: 1 | K84: C | M84: R/R | S84: Loyola | T84: CA | U84: Loyala HS | X84: Rob Murray recommended.
A85: Sean | B85: Brian | D85: 2027 | F85: 1 | G85: 1 | K85: C | M85: R/R | T85: CA | U85: Los Osos | V85: PFA | X85: Reco.
A86: Connor | B86: Couch | D86: 2026 | F86: 1 | G86: 1 | K86: UTIL | L86: RHP | M86: R/R | T86: IN | U86: Bloomington High School South | V86: Indiana Bulls | X86: NPI
A87: Charlie | B87: Delp | D87: 2026 | F87: 1 | G87: 1 | K87: COF | L87: 1B | M87: L/L | T87: GA | U87: West Forsyth | V87: East Cobb Astros | X87: Twitter
A88: Tripp | B88: Surber | D88: 2027 | F88: 1 | G88: 1 | K88: LHP | M88: L/L | T88: TX | U88: Concordia Lutheran HS | V88: USA Prime | X88: email/twitter
A89: Shane | B89: Meehan | D89: 2026 | F89: 1 | G89: 1 | K89: C | M89: R/R | T89: NY | U89: Sayville | X89: Super 17
A90: Jacob | B90: Mayfield | D90: 2026 | F90: 1 | G90: 1 | K90: COF | L90: RHP | M90: R/R | T90: GA | U90: Dacula | V90: Five Star GA | X90: Beast of East
A91: Otto | B91: Knust | D91: 2026 | F91: 1 | G91: 1 | K91: RHP | M91: R/R | T91: KS | U91: Shawnee Mission South | X91: NPI
A92: Carson | B92: Pratt | D92: 2027 | F92: 1 | G92: 1 | K92: RHP | M92: R/R | T92: TX | U92: Second Baptist | V92: Houston Wildcatters | X92: NPI
A93: Eli | B93: Hampton | D93: 2026 | F93: 1 | G93: 1 | K93: C | M93: R/R | T93: KY | U93: Owensboro HS | V93: Indiana Bulls | X93: NPI
A94: Jalen | B94: Bowman | D94: 2027 | F94: 1 | G94: 1 | K94: COF | L94: MINF | M94: R/R | T94: PA | U94: Malvern Prep | V94: Canes Mid Atlantic | X94: PA State Games
A95: JJ | B95: Mancuso | D95: 2027 | F95: 1 | G95: 1 | K95: COF | L95: CINF | M95: R/R | T95: PA | U95: North Allagheny | V95: Marucci Elite | X95: PA State Games
A96: Chris | B96: Grasso | D96: 2027 | F96: 1 | G96: 1 | K96: RHP | M96: R/R | T96: PA | U96: St. Joseph's Prep | V96: Canes Mid Atlantic | X96: PA State Games
A97: Graham | B97: Keen | D97: 2027 | F97: 1 | G97: 1 | K97: MINF | L97: COF | M97: R/R | T97: PA | U97: Mt. Lebanon HS | V97: Motor City Hit Dogs | X97: PA State Games
A98: Johnny | B98: Saunders | D98: 2027 | F98: 1 | G98: 1 | K98: RHP | M98: R/R | T98: PA | U98: Gateway HS | X98: PA State Games
A99: Freddy | B99: Corrado | D99: 2027 | F99: 1 | G99: 1 | K99: RHP | M99: R/R | T99: PA | U99: Hazelton | X99: PA State Games
A100: Brady | B100: Guzzie | D100: 2027 | F100: 1 | G100: 1 | K100: LHP | L100: COF | M100: L/L | T100: PA | U100: Conwell-Egan Catholic | V100: East Coast Ghost | X100: PA State Games
A101: Cole | B101: Kuhn | D101: 2027 | F101: 1 | G101: 1 | K101: RHP | M101: R/R | T101: PA | U101: St. Joseph's Prep | V101: Ascent | X101: PA State Games
A102: Thomas | B102: Collins | D102: 2026 | F102: 1 | G102: 1 | K102: LHP | L102: COF | M102: L/L | T102: NJ | U102: Don Bosco Prep | X102: Garden State Games
A103: Nick | B103: Malinowski | D103: 2027 | F103: 1 | G103: 1 | K103: RHP | M103: R/R | T103: NJ | U103: Barnegat HS | V103: .9ers Baseball Club | X103: Garden State Games
A104: Ryan | B104: Wetmore | D104: 2027 | F104: 1 | G104: 1 | K104: C | M104: R/R | T104: NJ | U104: Christian Brothers Academy | V104: Diamond Jacks | X104: Garden State/Super17
A105: Ajani | B105: Borwin | D105: 2026 | F105: 1 | G105: 1 | K105: C | M105: R/R | T105: NJ | U105: West Morris Mednham | X105: Super 17
A106: Cooper | B106: Ball | D106: 2027 | F106: 1 | G106: 1 | K106: RHP | L106: 1B | M106: R/R | T106: NY | U106: Horseheads HS | V106: Northeast Pride | X106: Super 17
A107: Jackson | B107: Staples | D107: 2027 | F107: 1 | G107: 1 | K107: COF | M107: L/R | T107: PA | U107: Hun | V107: Diamond Jacks | X107: Super 17
A108: Nick | B108: Do | D108: 2027 | F108: 1 | G108: 1 | K108: CF | L108: COF | M108: R/R | T108: NJ | U108: Jefferson | V108: Diamond Jacks | X108: SUper 17
A109: Jackson | B109: Hornick | D109: 2027 | F109: 1 | G109: 1 | K109: RHP | M109: R/R | T109: PA | U109: Central Bucks - West | V109: Diamond Jacks | X109: SUper 17
A110: Patrick | B110: Bryan | D110: 2027 | F110: 1 | G110: 1 | K110: C | M110: S/R | T110: MA | U110: Dexter Southfield | V110: MDB Knights | X110: Area Codes
A111: Colin | B111: Raymond | D111: 2028 | F111: 1 | G111: 1 | K111: COF | M111: L/R | T111: NY | U111: The Stony Brook School | V111: TRAVEL PROGRAMS | X111: Area Codes
...

Sheet Depth & Recruits AUTO PULL
G1: Recruiting Class: | K1: 2026 | N1: Depth Chart: | R1: =K1+1 -> 2027
AI2: Sr.
C3: TEAM | D3: RHP | G3: LHP | J3: UTL | M3: C | Q3: MINF | U3: CINF | Y3: OF | AI3: Jr.
D4: =IFERROR(__xludf.DUMMYFUNCTION("iferror(FILTER('Depth Chart Input'!$C:$C,$R$1='Depth Chart Input'!$A:$A,$D$3='Depth Chart Input'!$B:$B))"),"Aiden Healy") -> Aiden Healy | F4: =IFERROR(__xludf.DUMMYFUNCTION("iferror(FILTER('Depth Chart Input'!$G:$G,$R$1='Depth Chart Input'!$A:$A,$D$3='Depth Chart Input'!$B:$B))"),"Sr.") -> Sr. | G4: =IFERROR(__xludf.DUMMYFUNCTION("iferror(FILTER('Depth Chart Input'!$C:$C,$R$1='Depth Chart Input'!$A:$A,$G$3='Depth Chart Input'!$B:$B))"),"Timmy Virtudes") -> Timmy Virtudes | I4: =IFERROR(__xludf.DUMMYFUNCTION("iferror(FILTER('Depth Chart Input'!$G:$G,$R$1='Depth Chart Input'!$A:$A,$G$3='Depth Chart Input'!$B:$B))"),"Sr.") -> Sr. | J4: =IFERROR(__xludf.DUMMYFUNCTION("iferror(FILTER('Depth Chart Input'!$C:$C,$R$1='Depth Chart Input'!$A:$A,$J$3='Depth Chart Input'!$B:$B))"),"") | L4: =IFERROR(__xludf.DUMMYFUNCTION("iferror(FILTER('Depth Chart Input'!$G:$G,$R$1='Depth Chart Input'!$A:$A,$J$3='Depth Chart Input'!$B:$B))"),"") | M4: =IFERROR(__xludf.DUMMYFUNCTION("iferror(FILTER('Depth Chart Input'!$C:$C,$R$1='Depth Chart Input'!$A:$A,$M$3='Depth Chart Input'!$B:$B))"),"Ty Deperno") -> Ty Deperno | O4: {=XLOOKUP(M4,'Depth Chart Input'!$C:$C,'Depth Chart Input'!$F:$F,"",0,1)} -> R/R | P4: =IFERROR(__xludf.DUMMYFUNCTION("iferror(FILTER('Depth Chart Input'!$G:$G,$R$1='Depth Chart Input'!$A:$A,$M$3='Depth Chart Input'!$B:$B))"),"Jr.") -> Jr. | Q4: =IFERROR(__xludf.DUMMYFUNCTION("iferror(FILTER('Depth Chart Input'!$C:$C,$R$1='Depth Chart Input'!$A:$A,$Q$3='Depth Chart Input'!$B:$B))"),"Noah Ditas") -> Noah Ditas | S4: {=XLOOKUP(Q4,'Depth Chart Input'!$C:$C,'Depth Chart Input'!$F:$F,"",0,1)} -> R/R | T4: =IFERROR(__xludf.DUMMYFUNCTION("iferror(FILTER('Depth Chart Input'!$G:$G,$R$1='Depth Chart Input'!$A:$A,$Q$3='Depth Chart Input'!$B:$B))"),"Jr.") -> Jr. | U4: =IFERROR(__xludf.DUMMYFUNCTION("iferror(FILTER('Depth Chart Input'!$C:$C,$R$1='Depth Chart Input'!$A:$A,$U$3='Depth Chart Input'!$B:$B))"),"Evan Brown") -> Evan Brown | W4: {=XLOOKUP(U4,'Depth Chart Input'!$C:$C,'Depth Chart Input'!$F:$F,"",0,1)} -> R/R | X4: =IFERROR(__xludf.DUMMYFUNCTION("iferror(FILTER('Depth Chart Input'!$G:$G,$R$1='Depth Chart Input'!$A:$A,$U$3='Depth Chart Input'!$B:$B))"),"Sr.") -> Sr. | Y4: =IFERROR(__xludf.DUMMYFUNCTION("iferror(FILTER('Depth Chart Input'!$C:$C,$R$1='Depth Chart Input'!$A:$A,$Y$3='Depth Chart Input'!$B:$B))"),"Andrew Manning") -> Andrew Manning | AA4: {=XLOOKUP(Y4,'Depth Chart Input'!$C:$C,'Depth Chart Input'!$F:$F,"",0,1)} -> L/R | AB4: =IFERROR(__xludf.DUMMYFUNCTION("iferror(FILTER('Depth Chart Input'!$G:$G,$R$1='Depth Chart Input'!$A:$A,$Y$3='Depth Chart Input'!$B:$B))"),"Sr.") -> Sr. | AD4: SENIOR | AF4: =COUNTIF($C$3:$AB$21,AI2) -> 11 | AI4: So.
D5: =IFERROR(__xludf.DUMMYFUNCTION("""COMPUTED_VALUE"""),"Brady Bendik") -> Brady Bendik | F5: =IFERROR(__xludf.DUMMYFUNCTION("""COMPUTED_VALUE"""),"Sr.") -> Sr. | G5: =IFERROR(__xludf.DUMMYFUNCTION("""COMPUTED_VALUE"""),"Ian Brown") -> Ian Brown | I5: =IFERROR(__xludf.DUMMYFUNCTION("""COMPUTED_VALUE"""),"Jr.") -> Jr. | M5: =IFERROR(__xludf.DUMMYFUNCTION("""COMPUTED_VALUE"""),"Will Howard") -> Will Howard | O5: {=XLOOKUP(M5,'Depth Chart Input'!$C:$C,'Depth Chart Input'!$F:$F,"",0,1)} -> R/R | P5: =IFERROR(__xludf.DUMMYFUNCTION("""COMPUTED_VALUE"""),"So.") -> So. | Q5: =IFERROR(__xludf.DUMMYFUNCTION("""COMPUTED_VALUE"""),"Noah Stead") -> Noah Stead | S5: {=XLOOKUP(Q5,'Depth Chart Input'!$C:$C,'Depth Chart Input'!$F:$F,"",0,1)} -> R/R | T5: =IFERROR(__xludf.DUMMYFUNCTION("""COMPUTED_VALUE"""),"So.") -> So. | U5: =IFERROR(__xludf.DUMMYFUNCTION("""COMPUTED_VALUE"""),"Jack Killelea") -> Jack Killelea | W5: {=XLOOKUP(U5,'Depth Chart Input'!$C:$C,'Depth Chart Input'!$F:$F,"",0,1)} -> R/R | X5: =IFERROR(__xludf.DUMMYFUNCTION("""COMPUTED_VALUE"""),"Sr.") -> Sr. | Y5: =IFERROR(__xludf.DUMMYFUNCTION("""COMPUTED_VALUE"""),"Tyler Bouchard") -> Tyler Bouchard | AA5: {=XLOOKUP(Y5,'Depth Chart Input'!$C:$C,'Depth Chart Input'!$F:$F,"",0,1)} -> L/R | AB5: =IFERROR(__xludf.DUMMYFUNCTION("""COMPUTED_VALUE"""),"Sr.") -> Sr. | AD5: JUNIOR | AF5: =COUNTIF($C$3:$AB$21,AI3) -> 10 | AI5: Fr.
D6: =IFERROR(__xludf.DUMMYFUNCTION("""COMPUTED_VALUE"""),"Matt Archibald") -> Matt Archibald | F6: =IFERROR(__xludf.DUMMYFUNCTION("""COMPUTED_VALUE"""),"Sr.") -> Sr. | G6: =IFERROR(__xludf.DUMMYFUNCTION("""COMPUTED_VALUE"""),"John Carroll") -> John Carroll | I6: =IFERROR(__xludf.DUMMYFUNCTION("""COMPUTED_VALUE"""),"Jr.") -> Jr. | M6: =IFERROR(__xludf.DUMMYFUNCTION("""COMPUTED_VALUE"""),"Keaton Bowers") -> Keaton Bowers | O6: {=XLOOKUP(M6,'Depth Chart Input'!$C:$C,'Depth Chart Input'!$F:$F,"",0,1)} -> L/R | P6: =IFERROR(__xludf.DUMMYFUNCTION("""COMPUTED_VALUE"""),"Fr.") -> Fr. | Q6: =IFERROR(__xludf.DUMMYFUNCTION("""COMPUTED_VALUE"""),"Brooks Franklin") -> Brooks Franklin | S6: {=XLOOKUP(Q6,'Depth Chart Input'!$C:$C,'Depth Chart Input'!$F:$F,"",0,1)} -> L/R | T6: =IFERROR(__xludf.DUMMYFUNCTION("""COMPUTED_VALUE"""),"Fr.") -> Fr. | U6: =IFERROR(__xludf.DUMMYFUNCTION("""COMPUTED_VALUE"""),"Leo Mangiamele") -> Leo Mangiamele | W6: {=XLOOKUP(U6,'Depth Chart Input'!$C:$C,'Depth Chart Input'!$F:$F,"",0,1)} -> R/R | X6: =IFERROR(__xludf.DUMMYFUNCTION("""COMPUTED_VALUE"""),"Sr.") -> Sr. | Y6: =IFERROR(__xludf.DUMMYFUNCTION("""COMPUTED_VALUE"""),"Chris Klug") -> Chris Klug | AA6: {=XLOOKUP(Y6,'Depth Chart Input'!$C:$C,'Depth Chart Input'!$F:$F,"",0,1)} -> R/R | AB6: =IFERROR(__xludf.DUMMYFUNCTION("""COMPUTED_VALUE"""),"Jr.") -> Jr. | AD6: SOPHOMORE | AF6: =COUNTIF($C$3:$AB$21,AI4) -> 10
D7: =IFERROR(__xludf.DUMMYFUNCTION("""COMPUTED_VALUE"""),"Owen Geiger") -> Owen Geiger | F7: =IFERROR(__xludf.DUMMYFUNCTION("""COMPUTED_VALUE"""),"Sr.") -> Sr. | G7: =IFERROR(__xludf.DUMMYFUNCTION("""COMPUTED_VALUE"""),"Kevin Maurer") -> Kevin Maurer | I7: =IFERROR(__xludf.DUMMYFUNCTION("""COMPUTED_VALUE"""),"Jr.") -> Jr. | O7: {=XLOOKUP(M7,'Depth Chart Input'!$C:$C,'Depth Chart Input'!$F:$F,"",0,1)} | Q7: =IFERROR(__xludf.DUMMYFUNCTION("""COMPUTED_VALUE"""),"Connor Seacrist") -> Connor Seacrist | S7: {=XLOOKUP(Q7,'Depth Chart Input'!$C:$C,'Depth Chart Input'!$F:$F,"",0,1)} -> R/R | T7: =IFERROR(__xludf.DUMMYFUNCTION("""COMPUTED_VALUE"""),"Fr.") -> Fr. | U7: =IFERROR(__xludf.DUMMYFUNCTION("""COMPUTED_VALUE"""),"Julian Friedman") -> Julian Friedman | W7: {=XLOOKUP(U7,'Depth Chart Input'!$C:$C,'Depth Chart Input'!$F:$F,"",0,1)} -> R/R | X7: =IFERROR(__xludf.DUMMYFUNCTION("""COMPUTED_VALUE"""),"So.") -> So. | Y7: =IFERROR(__xludf.DUMMYFUNCTION("""COMPUTED_VALUE"""),"Mason Ceccarelli") -> Mason Ceccarelli | AA7: {=XLOOKUP(Y7,'Depth Chart Input'!$C:$C,'Depth Chart Input'!$F:$F,"",0,1)} -> L/R | AB7: =IFERROR(__xludf.DUMMYFUNCTION("""COMPUTED_VALUE"""),"Jr.") -> Jr. | AD7: FRESHMAN | AF7: =COUNTIF($C$3:$AB$21,AI5) -> 12
